Workbook

Sheet Executive_Summary
A1: Chile Regional Tourism Competitiveness: Decision Dashboard
A2: 15-region legacy analytical frame | Prepared from DB1–DB5| v2: identities for Metropolitana, Aysén and Magallanes revised (see Identity_Scoring)
A4: Code | B4: Region | C4: Priority Tier | D4: Primary Identity | E4: Secondary Identity | F4: Traveler Segment | G4: Historical Composite | H4: Asset Score | I4: Enabler Score | J4: Recent Demand | K4: Digital Readiness | L4: Priority Score | M4: Latest Occupancy % | N4: Intl Recovery %
A5: XV | B5: Arica y Parinacota | C5: Wait | D5: Community & Indigenous | E5: Culture & Heritage | F5: responsible cultural and community-based travelers; culture-led city-break and heritage travelers | G5: 29.215553 | H5: 27.938624 | I5: 29.534786 | J5: 36.264197 | K5: 28.834379 | L5: =0.5*G5+0.3*J5+0.2*K5 -> 31.253912 | M5: 57 | N5: 138.39133
A6: I | B6: Tarapacá | C6: Wait | D6: Wellness & Thermal | E6: Astro & Desert | F6: wellness, thermal and regional leisure travelers; experience-seeking, astronomy and photography travelers | G6: 26.625575 | H6: 21.418694 | I6: 27.927295 | J6: 39.520943 | K6: 34.144353 | L6: =0.5*G6+0.3*J6+0.2*K6 -> 31.997941 | M6: 57.15 | N6: 148.02766
A7: II | B7: Antofagasta | C7: Prepare First | D7: Astro & Desert | E7: Culture & Heritage | F7: experience-seeking, astronomy and photography travelers; culture-led city-break and heritage travelers | G7: 36.163446 | H7: 32.600886 | I7: 37.054085 | J7: 35.384703 | K7: 50.625421 | L7: =0.5*G7+0.3*J7+0.2*K7 -> 38.822218 | M7: 54.2 | N7: 126.89083
A8: III | B8: Atacama | C8: Prepare First | D8: Astro & Desert | E8: Coastal & Cruise | F8: experience-seeking, astronomy and photography travelers; coastal leisure, cruise and family travelers | G8: 26.283286 | H8: 21.979582 | I8: 27.359212 | J8: 41.227633 | K8: 29.863337 | L8: =0.5*G8+0.3*J8+0.2*K8 -> 31.482601 | M8: 57.35 | N8: 138.212
A9: IV | B9: Coquimbo | C9: Scale Now | D9: Coastal & Cruise | E9: Astro & Desert | F9: coastal leisure, cruise and family travelers; experience-seeking, astronomy and photography travelers | G9: 34.386152 | H9: 29.848072 | I9: 35.520672 | J9: 62.310224 | K9: 57.674328 | L9: =0.5*G9+0.3*J9+0.2*K9 -> 47.421009 | M9: 61.475 | N9: 158.34572
A10: V | B10: Valparaíso | C10: Scale Now | D10: Coastal & Cruise | E10: Culture & Heritage | F10: coastal leisure, cruise and family travelers; culture-led city-break and heritage travelers | G10: 42.497286 | H10: 46.007667 | I10: 41.619691 | J10: 70.904002 | K10: 68.955855 | L10: =0.5*G10+0.3*J10+0.2*K10 -> 56.311015 | M10: 64.325 | N10: 128.76497
A11: RM | B11: Metropolitana | C11: Scale Now | D11: Culture & Heritage | E11: Winter & Mountain | F11: culture-led city-break and heritage travelers; winter-sports and mountain-adventure travelers | G11: 51.027407 | H11: 34.494686 | I11: 55.160587 | J11: 95.230769 | K11: 97.883598 | L11: =0.5*G11+0.3*J11+0.2*K11 -> 73.659654 | M11: 62 | N11: 174.71414
A12: VI | B12: O'Higgins | C12: Prepare First | D12: Wine & Gastronomy | E12: Culture & Heritage | F12: affluent culinary and wine travelers; culture-led city-break and heritage travelers | G12: 27.690385 | H12: 29.737326 | I12: 27.17865 | J12: 30.399641 | K12: 18.715728 | L12: =0.5*G12+0.3*J12+0.2*K12 -> 26.70823 | M12: 58.25 | N12: 122.28954
A13: VII | B13: Maule | C13: Prepare First | D13: Wellness & Thermal | E13: Winter & Mountain | F13: wellness, thermal and regional leisure travelers; winter-sports and mountain-adventure travelers | G13: 28.117204 | H13: 28.723329 | I13: 27.965673 | J13: 59.352236 | K13: 77.15703 | L13: =0.5*G13+0.3*J13+0.2*K13 -> 47.295679 | M13: 62.75 | N13: 157.65687
A14: VIII | B14: Biobío | C14: Prepare First | D14: Culture & Heritage | E14: Winter & Mountain | F14: culture-led city-break and heritage travelers; winter-sports and mountain-adventure travelers | G14: 36.846173 | H14: 26.559771 | I14: 39.417774 | J14: 45.638541 | K14: 52.766353 | L14: =0.5*G14+0.3*J14+0.2*K14 -> 42.667919 | M14: 54.35 | N14: 150.95831
A15: IX | B15: Araucanía | C15: Prepare First | D15: Wellness & Thermal | E15: Winter & Mountain | F15: wellness, thermal and regional leisure travelers; winter-sports and mountain-adventure travelers | G15: 33.592731 | H15: 42.672929 | I15: 31.322682 | J15: 35.709395 | K15: 10.423953 | L15: =0.5*G15+0.3*J15+0.2*K15 -> 29.593975 | M15: 49.7 | N15: 143.23172
A16: XIV | B16: Los Ríos | C16: Prepare First | D16: Wellness & Thermal | E16: Nature & Adventure | F16: wellness, thermal and regional leisure travelers; eco-conscious adventure and longer-stay travelers | G16: 26.843005 | H16: 23.562633 | I16: 27.663098 | J16: 29.82618 | K16: 16.3681 | L16: =0.5*G16+0.3*J16+0.2*K16 -> 25.642977 | M16: 53.775 | N16: 133.10416
... A19: XII | B19: Magallanes y Antártica | C19: Scale Now | D19: Nature & Adventure | E19: Coastal & Cruise | F19: eco-conscious adventure and longer-stay travelers; expedition-cruise and Antarctic-gateway travelers | G19: 39.490988 | H19: 32.16918 | I19: 41.32144 | J19: 35.089993 | K19: 57.032018 | L19: =0.5*G19+0.3*J19+0.2*K19 -> 41.678896 | M19: 55.775 | N19: 135.49344

Sheet Regional_Profiles
A1: Regional Positioning and Action Logic
A2: v2: yellow cells mark revised identities (Metropolitana, Aysén, Magallanes). Rationale and data ranks in Identity_Scoring.
A3: Code | B3: Region | C3: Tier | D3: Identity 1 | E3: Identity 2 | F3: Target Traveler | G3: Top Dimensional Strengths | H3: Main Dimensional Gaps | I3: Priority Score | J3: Latest 4Q Arrivals | K3: Latest Occupancy % | L3: Latest ADR USD | M3: Recommended Action
A4: XV | B4: Arica y Parinacota | C4: Wait | D4: Community & Indigenous | E4: Culture & Heritage | F4: responsible cultural and community-based travelers; culture-led city-break and heritage travelers | G4: D8 52, D7 50 | H4: D10 6, D6 17 | I4: 31.253912 | J4: 89450 | K4: 57 | L4: 120.4725 | M4: Do not prioritize near-term promotion; validate product-market fit and close governance/service gaps first.
A5: I | B5: Tarapacá | C5: Wait | D5: Wellness & Thermal | E5: Astro & Desert | F5: wellness, thermal and regional leisure travelers; experience-seeking, astronomy and photography travelers | G5: D7 49, D8 40 | H5: D9 12, D1 15 | I5: 31.997941 | J5: 86385 | K5: 57.15 | L5: 117.5975 | M5: Do not prioritize near-term promotion; validate product-market fit and close governance/service gaps first.
A6: II | B6: Antofagasta | C6: Prepare First | D6: Astro & Desert | E6: Culture & Heritage | F6: experience-seeking, astronomy and photography travelers; culture-led city-break and heritage travelers | G6: D8 66, D7 50 | H6: D10 22, D1 24 | I6: 38.822218 | J6: 139385 | K6: 54.2 | L6: 121.5225 | M6: Fund foundational workforce, service, mobility, digital or safety gaps before broad promotion.
A7: III | B7: Atacama | C7: Prepare First | D7: Astro & Desert | E7: Coastal & Cruise | F7: experience-seeking, astronomy and photography travelers; coastal leisure, cruise and family travelers | G7: D7 53, D8 46 | H7: D1 10, D5 15 | I7: 31.482601 | J7: 110003 | K7: 57.35 | L7: 121.285 | M7: Fund foundational workforce, service, mobility, digital or safety gaps before broad promotion.
A8: IV | B8: Coquimbo | C8: Scale Now | D8: Coastal & Cruise | E8: Astro & Desert | F8: coastal leisure, cruise and family travelers; experience-seeking, astronomy and photography travelers | G8: D7 59, D10 51 | H8: D6 15, D5 18 | I8: 47.421009 | J8: 139401 | K8: 61.475 | L8: 132.575 | M8: Scale promotion and investment now, but pair growth with capacity and sustainability safeguards.
A9: V | B9: Valparaíso | C9: Scale Now | D9: Coastal & Cruise | E9: Culture & Heritage | F9: coastal leisure, cruise and family travelers; culture-led city-break and heritage travelers | G9: D7 60, D8 53 | H9: D9 30, D10 33 | I9: 56.311015 | J9: 273183 | K9: 64.325 | L9: 135.7025 | M9: Scale promotion and investment now, but pair growth with capacity and sustainability safeguards.
A10: RM | B10: Metropolitana | C10: Scale Now | D10: Culture & Heritage | E10: Winter & Mountain | F10: culture-led city-break and heritage travelers; winter-sports and mountain-adventure travelers | G10: D3 62, D4 62 | H10: D2 17, D9 33 | I10: 73.659654 | J10: 475650 | K10: 62 | L10: 177.9475 | M10: Scale promotion and investment now, but pair growth with capacity and sustainability safeguards.
A11: VI | B11: O'Higgins | C11: Prepare First | D11: Wine & Gastronomy | E11: Culture & Heritage | F11: affluent culinary and wine travelers; culture-led city-break and heritage travelers | G11: D7 64, D8 55 | H11: D5 8, D4 12 | I11: 26.70823 | J11: 80165 | K11: 58.25 | L11: 105.1225 | M11: Fund foundational workforce, service, mobility, digital or safety gaps before broad promotion.
A12: VII | B12: Maule | C12: Prepare First | D12: Wellness & Thermal | E12: Winter & Mountain | F12: wellness, thermal and regional leisure travelers; winter-sports and mountain-adventure travelers | G12: D7 61, D8 50 | H12: D4 13, D3 15 | I12: 47.295679 | J12: 108066 | K12: 62.75 | L12: 159.355 | M12: Fund foundational workforce, service, mobility, digital or safety gaps before broad promotion.
A13: VIII | B13: Biobío | C13: Prepare First | D13: Culture & Heritage | E13: Winter & Mountain | F13: culture-led city-break and heritage travelers; winter-sports and mountain-adventure travelers | G13: D10 80, D7 66 | H13: D4 17, D6 20 | I13: 42.667919 | J13: 144588 | K13: 54.35 | L13: 128.78 | M13: Fund foundational workforce, service, mobility, digital or safety gaps before broad promotion.
A14: IX | B14: Araucanía | C14: Prepare First | D14: Wellness & Thermal | E14: Winter & Mountain | F14: wellness, thermal and regional leisure travelers; winter-sports and mountain-adventure travelers | G14: D7 60, D2 56 | H14: D9 13, D3 21 | I14: 29.593975 | J14: 163446 | K14: 49.7 | L14: 109.0175 | M14: Fund foundational workforce, service, mobility, digital or safety gaps before broad promotion.
A15: XIV | B15: Los Ríos | C15: Prepare First | D15: Wellness & Thermal | E15: Nature & Adventure | F15: wellness, thermal and regional leisure travelers; eco-conscious adventure and longer-stay travelers | G15: D7 65, D8 49 | H15: D1 10, D5 12 | I15: 25.642977 | J15: 99374 | K15: 53.775 | L15: 113.37 | M15: Fund foundational workforce, service, mobility, digital or safety gaps before broad promotion.
... A18: XII | B18: Magallanes y Antártica | C18: Scale Now | D18: Nature & Adventure | E18: Coastal & Cruise | F18: eco-conscious adventure and longer-stay travelers; expedition-cruise and Antarctic-gateway travelers | G18: D7 66, D8 53 | H18: D10 10, D1 13 | I18: 41.678896 | J18: 100571 | K18: 55.775 | L18: 197.9675 | M18: Scale promotion and investment now, but pair growth with capacity and sustainability safeguards.

Sheet Dimension_Scores
A1: Normalized Dimension Scores (0-100)
A3: Code | B3: Region | C3: D1 | D3: D2 | E3: D3 | F3: D4 | G3: D5 | H3: D6 | I3: D7 | J3: D8 | K3: D9 | L3: D10 | M3: Overall | N3: Asset (D1–D2) | O3: Enabler (D3–D10) | P3: Tier | R3: D1 | S3: Cultural Heritage & Events
A4: XV | B4: Arica y Parinacota | C4: 22.283865 | D4: 33.593383 | E4: 32.395896 | F4: 25.927985 | G4: 28.553771 | H4: 17.363602 | I4: 50.22718 | J4: 51.94078 | K4: 23.896516 | L4: 5.9725558 | M4: =AVERAGE(C4:L4) -> 29.215553 | N4: =AVERAGE(C4:D4) -> 27.938624 | O4: =AVERAGE(E4:L4) -> 29.534786 | P4: Wait | R4: D2 | S4: Natural Resources & Sustainability
A5: I | B5: Tarapacá | C5: 15.145645 | D5: 27.691743 | E5: 30.134838 | F5: 29.378623 | G5: 24.008176 | H5: 21.227666 | I5: 49.05692 | J5: 39.837634 | K5: 12.154815 | L5: 17.61969 | M5: =AVERAGE(C5:L5) -> 26.625575 | N5: =AVERAGE(C5:D5) -> 21.418694 | O5: =AVERAGE(E5:L5) -> 27.927295 | P5: Wait | R5: D3 | S5: Human Resources & Workforce
A6: II | B6: Antofagasta | C6: 23.78597 | D6: 41.415802 | E6: 28.045293 | F6: 28.104243 | G6: 33.120996 | H6: 31.326621 | I6: 50.147795 | J6: 66.281922 | K6: 37.550834 | L6: 21.854979 | M6: =AVERAGE(C6:L6) -> 36.163446 | N6: =AVERAGE(C6:D6) -> 32.600886 | O6: =AVERAGE(E6:L6) -> 37.054085 | P6: Prepare First | R6: D4 | S6: Tourism Infrastructure
A7: III | B7: Atacama | C7: 9.5479185 | D7: 34.411246 | E7: 22.018434 | F7: 19.567644 | G7: 14.693321 | H7: 23.134549 | I7: 53.191973 | J7: 46.438893 | K7: 21.54423 | L7: 18.284654 | M7: =AVERAGE(C7:L7) -> 26.283286 | N7: =AVERAGE(C7:D7) -> 21.979582 | O7: =AVERAGE(E7:L7) -> 27.359212 | P7: Prepare First | R7: D5 | S7: Mobility & Transportation
A8: IV | B8: Coquimbo | C8: 19.62268 | D8: 40.073464 | E8: 25.401077 | F8: 42.140811 | G8: 18.002593 | H8: 15.471814 | I8: 59.20911 | J8: 46.334826 | K8: 26.447633 | L8: 51.157512 | M8: =AVERAGE(C8:L8) -> 34.386152 | N8: =AVERAGE(C8:D8) -> 29.848072 | O8: =AVERAGE(E8:L8) -> 35.520672 | P8: Scale Now | R8: D6 | S8: Tourism-Related Services
A9: V | B9: Valparaíso | C9: 49.152672 | D9: 42.862662 | E9: 35.132094 | F9: 44.698128 | G9: 34.921937 | H9: 43.075146 | I9: 59.759528 | J9: 52.722766 | K9: 29.696202 | L9: 32.951729 | M9: =AVERAGE(C9:L9) -> 42.497286 | N9: =AVERAGE(C9:D9) -> 46.007667 | O9: =AVERAGE(E9:L9) -> 41.619691 | P9: Scale Now | R9: D7 | S9: Security & Safety
A10: RM | B10: Metropolitana | C10: 52.04743 | D10: 16.941943 | E10: 61.707192 | F10: 61.701864 | G10: 57.908505 | H10: 54.879212 | I10: 56.901021 | J10: 54.099651 | K10: 33.333333 | L10: 60.753915 | M10: =AVERAGE(C10:L10) -> 51.027407 | N10: =AVERAGE(C10:D10) -> 34.494686 | O10: =AVERAGE(E10:L10) -> 55.160587 | P10: Scale Now | R10: D8 | S10: Economic Performance
A11: VI | B11: O'Higgins | C11: 31.870607 | D11: 27.604044 | E11: 20.709534 | F11: 12.34056 | G11: 7.6977449 | H11: 24.840676 | I11: 63.960311 | J11: 55.401254 | K11: 15.779573 | L11: 16.699545 | M11: =AVERAGE(C11:L11) -> 27.690385 | N11: =AVERAGE(C11:D11) -> 29.737326 | O11: =AVERAGE(E11:L11) -> 27.17865 | P11: Prepare First | R11: D9 | S11: Tourism Promotion
A12: VII | B12: Maule | C12: 20.217145 | D12: 37.229514 | E12: 15.325348 | F12: 12.565201 | G12: 16.997188 | H12: 18.186511 | I12: 60.900703 | J12: 49.52087 | K12: 15.602437 | L12: 34.627124 | M12: =AVERAGE(C12:L12) -> 28.117204 | N12: =AVERAGE(C12:D12) -> 28.723329 | O12: =AVERAGE(E12:L12) -> 27.965673 | P12: Prepare First | R12: D10 | S12: Governmental Involvement & Efficiency
A13: VIII | B13: Biobío | C13: 21.060624 | D13: 32.058918 | E13: 25.827107 | F13: 16.647261 | G13: 27.946126 | H13: 19.696254 | I13: 66.454617 | J13: 46.949347 | K13: 31.552845 | L13: 80.268633 | M13: =AVERAGE(C13:L13) -> 36.846173 | N13: =AVERAGE(C13:D13) -> 26.559771 | O13: =AVERAGE(E13:L13) -> 39.417774 | P13: Prepare First
A14: IX | B14: Araucanía | C14: 29.59021 | D14: 55.755648 | E14: 20.514875 | F14: 28.479407 | G14: 27.685449 | H14: 31.024615 | I14: 59.918547 | J14: 35.097898 | K14: 13.081496 | L14: 34.779168 | M14: =AVERAGE(C14:L14) -> 33.592731 | N14: =AVERAGE(C14:D14) -> 42.672929 | O14: =AVERAGE(E14:L14) -> 31.322682 | P14: Prepare First
A15: XIV | B15: Los Ríos | C15: 10.029857 | D15: 37.095409 | E15: 13.450882 | F15: 18.800846 | G15: 12.062514 | H15: 24.201186 | I15: 65.054051 | J15: 49.323312 | K15: 21.844652 | L15: 16.567345 | M15: =AVERAGE(C15:L15) -> 26.843005 | N15: =AVERAGE(C15:D15) -> 23.562633 | O15: =AVERAGE(E15:L15) -> 27.663098 | P15: Prepare First
A16: X | B16: Los Lagos | C16: 19.91888 | D16: 57.620097 | E16: 27.465591 | F16: 34.780082 | G16: 53.150092 | H16: 28.104657 | I16: 64.690324 | J16: 70.101033 | K16: 31.392222 | L16: 55.723977 | M16: =AVERAGE(C16:L16) -> 44.294696 | N16: =AVERAGE(C16:D16) -> 38.769488 | O16: =AVERAGE(E16:L16) -> 45.675997 | P16: Scale Now
A17: XI | B17: Aysén | C17: 6.3100783 | D17: 57.599532 | E17: 35.126914 | F17: 13.726549 | G17: 16.704865 | H17: 35.477878 | I17: 49.139991 | J17: 64.88177 | K17: 38.478971 | L17: 22.463047 | M17: =AVERAGE(C17:L17) -> 33.99096 | N17: =AVERAGE(C17:D17) -> 31.954805 | O17: =AVERAGE(E17:L17) -> 34.499998 | P17: Prepare First
A18: XII | B18: Magallanes y Antártica | C18: 13.39979 | D18: 50.938571 | E18: 44.880707 | F18: 33.284446 | G18: 32.649898 | H18: 43.239919 | I18: 65.922953 | J18: 52.948105 | K18: 47.66839 | L18: 9.9771008 | M18: =AVERAGE(C18:L18) -> 39.490988 | N18: =AVERAGE(C18:D18) -> 32.16918 | O18: =AVERAGE(E18:L18) -> 41.32144 | P18: Scale Now

Sheet Identity_Scoring
A1: Tourism Identity Scoring: Indicator Evidence per Region (0–100)
A2: Each identity score = mean of min–max-normalised DB1/DB2 indicators mapped to that identity (mapping below). Final calls apply documented judgment where indicators are ambiguous.
A3: Code | B3: Region | C3: Nature & Adventure | D3: Culture & Heritage | E3: Wine & Gastronomy | F3: Wellness & Thermal | G3: Astro & Desert | H3: Winter & Mountain | I3: Coastal & Cruise | J3: Community & Indigenous
A4: XV | B4: Arica y Parinacota | C4: 23 | D4: 17.6 | E4: 21.3 | F4: 24.6 | G4: 5.1 | H4: 15.4 | I4: 12 | J4: 50.5
A5: I | B5: Tarapacá | C5: 4.9 | D5: 16.6 | E5: 17.9 | F5: 26.5 | G5: 23.7 | H5: 2.6 | I5: 12.8 | J5: 19.7
A6: II | B6: Antofagasta | C6: 24.4 | D6: 28.8 | E6: 28.2 | F6: 15.4 | G6: 56.6 | H6: 34.8 | I6: 24.7 | J6: 13.1
A7: III | B7: Atacama | C7: 14.3 | D7: 10.2 | E7: 22.7 | F7: 13.1 | G7: 45.8 | H7: 17.9 | I7: 22.6 | J7: 13.2
A8: IV | B8: Coquimbo | C8: 9.9 | D8: 10.1 | E8: 36.9 | F8: 14 | G8: 37.5 | H8: 0 | I8: 51.7 | J8: 40.3
A9: V | B9: Valparaíso | C9: 32.7 | D9: 54.2 | E9: 77.1 | F9: 26.6 | G9: 21.6 | H9: 17.7 | I9: 73.3 | J9: 36.8
A10: RM | B10: Metropolitana | C10: 8 | D10: 59.1 | E10: 14.7 | F10: 18.1 | G10: 14.3 | H10: 48.3 | I10: 0 | J10: 32.3
A11: VI | B11: O'Higgins | C11: 14.2 | D11: 29.9 | E11: 52.9 | F11: 9 | G11: 23.6 | H11: 24.5 | I11: 6.6 | J11: 31.2
A12: VII | B12: Maule | C12: 23.4 | D12: 18.5 | E12: 27.1 | F12: 39.6 | G12: 7.7 | H12: 39.5 | I12: 10.9 | J12: 35
A13: VIII | B13: Biobío | C13: 13 | D13: 22.5 | E13: 3 | F13: 14.5 | G13: 33.3 | H13: 18.7 | I13: 12.9 | J13: 20.2
A14: IX | B14: Araucanía | C14: 59.7 | D14: 17.1 | E14: 14.2 | F14: 100 | G14: 12.5 | H14: 62.5 | I14: 12 | J14: 59.3
A15: XIV | B15: Los Ríos | C15: 21.1 | D15: 7.8 | E15: 16.1 | F15: 61.1 | G15: 8.9 | H15: 14.4 | I15: 14.9 | J15: 20.3
... A18: XII | B18: Magallanes y Antártica | C18: 55.4 | D18: 14.1 | E18: 54.2 | F18: 0 | G18: 4.2 | H18: 61.3 | I18: 34.5 | J18: 19
A20: Code | B20: Region | C20: Tier | D20: Data rank 1 | E20: Score | F20: Data rank 2 | G20: Score | H20: Data rank 3 | I20: Score | J20: Final primary | K20: Final secondary | L20: Changed vs v1 | M20: Rationale | N20: Target traveler
A21: XV | B21: Arica y Parinacota | C21: Wait | D21: Community & Indigenous | E21: 50.5 | F21: Wellness & Thermal | G21: 24.6 | H21: Nature & Adventure | I21: 23 | J21: Community & Indigenous | K21: Culture & Heritage | L21: No | M21: Highest data rank; 25% of population identifies as indigenous and 30 archaeological sites (most in Chile) justify a heritage secondary. | N21: responsible cultural and community-based travelers; culture-led city-break and heritage travelers
A22: I | B22: Tarapacá | C22: Wait | D22: Wellness & Thermal | E22: 26.5 | F22: Astro & Desert | G22: 23.7 | H22: Community & Indigenous | I22: 19.7 | J22: Wellness & Thermal | K22: Astro & Desert | L22: No | M22: Follows data rank (thermal 26.5, astro 23.7); both niches are thin in absolute terms, consistent with the Wait tier. | N22: wellness, thermal and regional leisure travelers; experience-seeking, astronomy and photography travelers
A23: II | B23: Antofagasta | C23: Prepare First | D23: Astro & Desert | E23: 56.6 | F23: Winter & Mountain | G23: 34.8 | H23: Culture & Heritage | I23: 28.8 | J23: Astro & Desert | K23: Culture & Heritage | L23: No | M23: Primary follows data (56.6). Secondary overrides 'Winter & Mountain' (volcano count) in favour of 37 historical sites and 16 museums. | N23: experience-seeking, astronomy and photography travelers; culture-led city-break and heritage travelers
A24: III | B24: Atacama | C24: Prepare First | D24: Astro & Desert | E24: 45.8 | F24: Wine & Gastronomy | G24: 22.7 | H24: Coastal & Cruise | I24: 22.6 | J24: Astro & Desert | K24: Coastal & Cruise | L24: No | M24: Primary follows data (45.8). Coastal (22.6) and wine (22.7) tie; 17 beaches and 10 piers make coastal the credible product. | N24: experience-seeking, astronomy and photography travelers; coastal leisure, cruise and family travelers
A25: IV | B25: Coquimbo | C25: Scale Now | D25: Coastal & Cruise | E25: 51.7 | F25: Community & Indigenous | G25: 40.3 | H25: Astro & Desert | I25: 37.5 | J25: Coastal & Cruise | K25: Astro & Desert | L25: No | M25: Primary follows data (51.7). Secondary overrides 'Community' in favour of astro: 7 observatory-type sites, the most in Chile. | N25: coastal leisure, cruise and family travelers; experience-seeking, astronomy and photography travelers
A26: V | B26: Valparaíso | C26: Scale Now | D26: Wine & Gastronomy | E26: 77.1 | F26: Coastal & Cruise | G26: 73.3 | H26: Culture & Heritage | I26: 54.2 | J26: Coastal & Cruise | K26: Culture & Heritage | L26: No | M26: Wine & Gastronomy ranks first (77) on restaurant density; we keep coastal/cruise (31 cruise calls, 59 beaches) and heritage (161 monuments, 2 WHS) and treat wine as a third pillar. | N26: coastal leisure, cruise and family travelers; culture-led city-break and heritage travelers
A27: RM | B27: Metropolitana | C27: Scale Now | D27: Culture & Heritage | E27: 59.1 | F27: Winter & Mountain | G27: 48.3 | H27: Community & Indigenous | I27: 32.3 | J27: Culture & Heritage | K27: Winter & Mountain | L27: Yes | M27: REVISED: data rank Culture 59 vs Winter 48 (35 museums, 404 monuments). Winter stays secondary: 5 ski resorts, the most in Chile. | N27: culture-led city-break and heritage travelers; winter-sports and mountain-adventure travelers
A28: VI | B28: O'Higgins | C28: Prepare First | D28: Wine & Gastronomy | E28: 52.9 | F28: Community & Indigenous | G28: 31.2 | H28: Culture & Heritage | I28: 29.9 | J28: Wine & Gastronomy | K28: Culture & Heritage | L28: No | M28: Primary follows data (52.9); Community (31.2) and Culture (29.9) tie, heritage chosen for the Sewell/Colchagua museum cluster. | N28: affluent culinary and wine travelers; culture-led city-break and heritage travelers
A29: VII | B29: Maule | C29: Prepare First | D29: Wellness & Thermal | E29: 39.6 | F29: Winter & Mountain | G29: 39.5 | H29: Community & Indigenous | I29: 35 | J29: Wellness & Thermal | K29: Winter & Mountain | L29: No | M29: Follows data rank (39.6 vs 39.5). Wine (27) is under-recorded in DB2 (2 vineyards) and should be validated as a third pillar. | N29: wellness, thermal and regional leisure travelers; winter-sports and mountain-adventure travelers
A30: VIII | B30: Biobío | C30: Prepare First | D30: Astro & Desert | E30: 33.3 | F30: Culture & Heritage | G30: 22.5 | H30: Community & Indigenous | I30: 20.2 | J30: Culture & Heritage | K30: Winter & Mountain | L30: No | M30: Data rank 'Astro & Desert' (33) is an artefact of the paleontology indicator; 20 museums and 23 historical sites support heritage. | N30: culture-led city-break and heritage travelers; winter-sports and mountain-adventure travelers
A31: IX | B31: Araucanía | C31: Prepare First | D31: Wellness & Thermal | E31: 100 | F31: Winter & Mountain | G31: 62.5 | H31: Nature & Adventure | I31: 59.7 | J31: Wellness & Thermal | K31: Winter & Mountain | L31: No | M31: Follows data rank (100 / 62.5); nature (60) and Mapuche community tourism (59) are strong third options. | N31: wellness, thermal and regional leisure travelers; winter-sports and mountain-adventure travelers
A32: XIV | B32: Los Ríos | C32: Prepare First | D32: Wellness & Thermal | E32: 61.1 | F32: Nature & Adventure | G32: 21.1 | H32: Community & Indigenous | I32: 20.3 | J32: Wellness & Thermal | K32: Nature & Adventure | L32: No | M32: Follows data rank (61.1 / 21.1). | N32: wellness, thermal and regional leisure travelers; eco-conscious adventure and longer-stay travelers
... A35: XII | B35: Magallanes y Antártica | C35: Scale Now | D35: Winter & Mountain | E35: 61.3 | F35: Nature & Adventure | G35: 55.4 | H35: Wine & Gastronomy | I35: 54.2 | J35: Nature & Adventure | K35: Coastal & Cruise | L35: Yes | M35: REVISED: 57% protected land (highest) and 284k protected-area visitors; 18 cruise calls (Antarctic gateway). Winter score (61) is inflated by 20 glacier sites; one ski resort. | N35: eco-conscious adventure and longer-stay travelers; expedition-cruise and Antarctic-gateway travelers
A37: Identity | B37: DB1/DB2 indicators used (equal weights within identity)
A38: Nature & Adventure | B38: National protected sites (%); hiking trails; visitors to protected sites; rivers, lakes & waterfalls; natural protected sites L2/L3; biosphere reserves; % forest land; glaciers & winter locations; mountains & volcanoes; preserved sites
A39: Culture & Heritage | B39: World cultural heritage sites; museums; national monuments; historical sites; archaeological sites; cultural centers; theaters; theater plays; galleries; exhibits; artistic events; cultural sites L2/L3; heritage architectural houses; artwork sites; % population attending museums
A40: Wine & Gastronomy | B40: Number of vineyards; valleys; density of restaurants; restaurant employment per 10,000
A41: Wellness & Thermal | B41: Thermal centers (DB2); geysers & thermal centers (DB1); spas
A42: Astro & Desert | B42: Observatories/zoos/aquaria/botanical gardens; deserts & dunes; paleontology sites
A43: Winter & Mountain | B43: Ski resorts; mountains & volcanoes; glaciers & winter locations
A44: Coastal & Cruise | B44: Beaches & beach resorts; piers & seashores; cruise arrivals per year; islands & peninsulas; seashore protected sites
A45: Community & Indigenous | B45: % population associated to an indigenous group; local markets; cultural sites L1 (local); popular architecture sites; cultural events scheduled through the year
A47: Known ambiguity: 'Glaciers and winter vacation locations' mixes a nature asset (glaciers) with a winter-sports asset; it is counted in both identities, which is why Aysén and Magallanes score high on Winter & Mountain although each has a single ski resort. Missing indicator values are median-imputed before normalisation.

Sheet Descriptive_Stats
A1: Descriptive Statistics: Demand Panel (DB3), Dimension Scores and Digital Readiness (DB5)
A2: All cells are live formulas on Tableau_TimeSeries (cleaned DB3), Dimension_Scores and Tableau_DigitalReadiness. Latest 4Q = 2024-Q4 to 2025-Q3.
A3: Period | B3: International arrivals | C3: National arrivals | D3: Total arrivals | E3: Avg occupancy % | F3: Avg daily rate USD | G3: Avg length of stay | H3: Intl vs 2019 (%) | I3: National vs 2019 (%)
A4: 2019 | B4: =SUMIFS(Tableau_TimeSeries!$F:$F,Tableau_TimeSeries!$C:$C,2019) -> 500737 | C4: =SUMIFS(Tableau_TimeSeries!$G:$G,Tableau_TimeSeries!$C:$C,2019) -> 1219152 | D4: =B4+C4 -> 1719889 | E4: =AVERAGEIFS(Tableau_TimeSeries!$I:$I,Tableau_TimeSeries!$C:$C,2019) -> 56.69322 | F4: =AVERAGEIFS(Tableau_TimeSeries!$H:$H,Tableau_TimeSeries!$C:$C,2019) -> 107.80983 | G4: =AVERAGEIFS(Tableau_TimeSeries!$J:$J,Tableau_TimeSeries!$C:$C,2019) -> 2.5753333 | H4: =B4/$B$4*100 -> 100 | I4: =C4/$C$4*100 -> 100
A5: 2020 | B5: =SUMIFS(Tableau_TimeSeries!$F:$F,Tableau_TimeSeries!$C:$C,2020) -> 113608 | C5: =SUMIFS(Tableau_TimeSeries!$G:$G,Tableau_TimeSeries!$C:$C,2020) -> 631158 | D5: =B5+C5 -> 744766 | E5: =AVERAGEIFS(Tableau_TimeSeries!$I:$I,Tableau_TimeSeries!$C:$C,2020) -> 35.744068 | F5: =AVERAGEIFS(Tableau_TimeSeries!$H:$H,Tableau_TimeSeries!$C:$C,2020) -> 88.047797 | G5: =AVERAGEIFS(Tableau_TimeSeries!$J:$J,Tableau_TimeSeries!$C:$C,2020) -> 2.5598333 | H5: =B5/$B$4*100 -> 22.688158 | I5: =C5/$C$4*100 -> 51.770247
A6: 2021 | B6: =SUMIFS(Tableau_TimeSeries!$F:$F,Tableau_TimeSeries!$C:$C,2021) -> 119446 | C6: =SUMIFS(Tableau_TimeSeries!$G:$G,Tableau_TimeSeries!$C:$C,2021) -> 638159 | D6: =B6+C6 -> 757605 | E6: =AVERAGEIFS(Tableau_TimeSeries!$I:$I,Tableau_TimeSeries!$C:$C,2021) -> 35.876271 | F6: =AVERAGEIFS(Tableau_TimeSeries!$H:$H,Tableau_TimeSeries!$C:$C,2021) -> 92.5625 | G6: =AVERAGEIFS(Tableau_TimeSeries!$J:$J,Tableau_TimeSeries!$C:$C,2021) -> 2.6036667 | H6: =B6/$B$4*100 -> 23.854039 | I6: =C6/$C$4*100 -> 52.344498
A7: 2022 | B7: =SUMIFS(Tableau_TimeSeries!$F:$F,Tableau_TimeSeries!$C:$C,2022) -> 469817 | C7: =SUMIFS(Tableau_TimeSeries!$G:$G,Tableau_TimeSeries!$C:$C,2022) -> 1176744 | D7: =B7+C7 -> 1646561 | E7: =AVERAGEIFS(Tableau_TimeSeries!$I:$I,Tableau_TimeSeries!$C:$C,2022) -> 50.349153 | F7: =AVERAGEIFS(Tableau_TimeSeries!$H:$H,Tableau_TimeSeries!$C:$C,2022) -> 114.19117 | G7: =AVERAGEIFS(Tableau_TimeSeries!$J:$J,Tableau_TimeSeries!$C:$C,2022) -> 2.6026667 | H7: =B7/$B$4*100 -> 93.825102 | I7: =C7/$C$4*100 -> 96.521517
A8: 2023 | B8: =SUMIFS(Tableau_TimeSeries!$F:$F,Tableau_TimeSeries!$C:$C,2023) -> 639918 | C8: =SUMIFS(Tableau_TimeSeries!$G:$G,Tableau_TimeSeries!$C:$C,2023) -> 1425773 | D8: =B8+C8 -> 2065691 | E8: =AVERAGEIFS(Tableau_TimeSeries!$I:$I,Tableau_TimeSeries!$C:$C,2023) -> 57.383333 | F8: =AVERAGEIFS(Tableau_TimeSeries!$H:$H,Tableau_TimeSeries!$C:$C,2023) -> 125.34593 | G8: =AVERAGEIFS(Tableau_TimeSeries!$J:$J,Tableau_TimeSeries!$C:$C,2023) -> 2.5738333 | H8: =B8/$B$4*100 -> 127.79523 | I8: =C8/$C$4*100 -> 116.94793
A9: 2024 | B9: =SUMIFS(Tableau_TimeSeries!$F:$F,Tableau_TimeSeries!$C:$C,2024) -> 713076 | C9: =SUMIFS(Tableau_TimeSeries!$G:$G,Tableau_TimeSeries!$C:$C,2024) -> 1489548 | D9: =B9+C9 -> 2202624 | E9: =AVERAGEIFS(Tableau_TimeSeries!$I:$I,Tableau_TimeSeries!$C:$C,2024) -> 57.405 | F9: =AVERAGEIFS(Tableau_TimeSeries!$H:$H,Tableau_TimeSeries!$C:$C,2024) -> 131.73328 | G9: =AVERAGEIFS(Tableau_TimeSeries!$J:$J,Tableau_TimeSeries!$C:$C,2024) -> 2.6031667 | H9: =B9/$B$4*100 -> 142.40529 | I9: =C9/$C$4*100 -> 122.17902
A10: Latest 4Q (2024-Q4–2025-Q3) | B10: =SUMIFS(Tableau_TimeSeries!$F:$F,Tableau_TimeSeries!$C:$C,2024,Tableau_TimeSeries!$D:$D,"Q4")+SUMIFS(Tableau_TimeSeries!$F:$F,Tableau_TimeSeries!$C:$C,2025) -> 733718 | C10: =SUMIFS(Tableau_TimeSeries!$G:$G,Tableau_TimeSeries!$C:$C,2024,Tableau_TimeSeries!$D:$D,"Q4")+SUMIFS(Tableau_TimeSeries!$G:$G,Tableau_TimeSeries!$C:$C,2025) -> 1551568 | D10: =B10+C10 -> 2285286 | E10: =(SUMIFS(Tableau_TimeSeries!$I:$I,Tableau_TimeSeries!$C:$C,2024,Tableau_TimeSeries!$D:$D,"Q4")+SUMIFS(Tableau_TimeSeries!$I:$I,Tableau_TimeSeries!$C:$C,2025))/(COUNTIFS(Tableau_TimeSeries!$I:$I,"<>",Tableau_TimeSeries!$C:$C,2024,Tableau_TimeSeries!$D:$D,"Q4")+COUNTIFS(Tableau_TimeSeries!$I:$I,"<>",Tableau_TimeSeries!$C:$C,2025)) -> 57.262069 | F10: =(SUMIFS(Tableau_TimeSeries!$H:$H,Tableau_TimeSeries!$C:$C,2024,Tableau_TimeSeries!$D:$D,"Q4")+SUMIFS(Tableau_TimeSeries!$H:$H,Tableau_TimeSeries!$C:$C,2025))/(COUNTIFS(Tableau_TimeSeries!$H:$H,"<>",Tableau_TimeSeries!$C:$C,2024,Tableau_TimeSeries!$D:$D,"Q4")+COUNTIFS(Tableau_TimeSeries!$H:$H,"<>",Tableau_TimeSeries!$C:$C,2025)) -> 136.0145 | G10: =(SUMIFS(Tableau_TimeSeries!$J:$J,Tableau_TimeSeries!$C:$C,2024,Tableau_TimeSeries!$D:$D,"Q4")+SUMIFS(Tableau_TimeSeries!$J:$J,Tableau_TimeSeries!$C:$C,2025))/(COUNTIFS(Tableau_TimeSeries!$J:$J,"<>",Tableau_TimeSeries!$C:$C,2024,Tableau_TimeSeries!$D:$D,"Q4")+COUNTIFS(Tableau_TimeSeries!$J:$J,"<>",Tableau_TimeSeries!$C:$C,2025)) -> 2.601 | H10: =B10/$B$4*100 -> 146.52762 | I10: =C10/$C$4*100 -> 127.26617
A11: 2025 covers Q1–Q3 only (27-quarter panel). Occupancy and ADR averages skip missing cells and the invalid Araucanía 2022-Q4 occupancy (104.5%, set to missing).
A13: Code | B13: Region | C13: Tier | D13: Intl arrivals latest 4Q | E13: National arrivals latest 4Q | F13: Avg occupancy % latest 4Q | G13: Avg daily rate USD latest 4Q | H13: Intl arrivals 2019 | I13: Intl recovery % (latest 4Q / 2019) | J13: National recovery % | K13: International share %
A14: XV | B14: Arica y Parinacota | C14: Wait | D14: =SUMIFS(Tableau_TimeSeries!$F:$F,Tableau_TimeSeries!$A:$A,"XV",Tableau_TimeSeries!$C:$C,2024,Tableau_TimeSeries!$D:$D,"Q4")+SUMIFS(Tableau_TimeSeries!$F:$F,Tableau_TimeSeries!$A:$A,"XV",Tableau_TimeSeries!$C:$C,2025) -> 27443 | E14: =SUMIFS(Tableau_TimeSeries!$G:$G,Tableau_TimeSeries!$A:$A,"XV",Tableau_TimeSeries!$C:$C,2024,Tableau_TimeSeries!$D:$D,"Q4")+SUMIFS(Tableau_TimeSeries!$G:$G,Tableau_TimeSeries!$A:$A,"XV",Tableau_TimeSeries!$C:$C,2025) -> 62007 | F14: =(SUMIFS(Tableau_TimeSeries!$I:$I,Tableau_TimeSeries!$A:$A,"XV",Tableau_TimeSeries!$C:$C,2024,Tableau_TimeSeries!$D:$D,"Q4")+SUMIFS(Tableau_TimeSeries!$I:$I,Tableau_TimeSeries!$A:$A,"XV",Tableau_TimeSeries!$C:$C,2025))/(COUNTIFS(Tableau_TimeSeries!$I:$I,"<>",Tableau_TimeSeries!$A:$A,"XV",Tableau_TimeSeries!$C:$C,2024,Tableau_TimeSeries!$D:$D,"Q4")+COUNTIFS(Tableau_TimeSeries!$I:$I,"<>",Tableau_TimeSeries!$A:$A,"XV",Tableau_TimeSeries!$C:$C,2025)) -> 57 | G14: =(SUMIFS(Tableau_TimeSeries!$H:$H,Tableau_TimeSeries!$A:$A,"XV",Tableau_TimeSeries!$C:$C,2024,Tableau_TimeSeries!$D:$D,"Q4")+SUMIFS(Tableau_TimeSeries!$H:$H,Tableau_TimeSeries!$A:$A,"XV",Tableau_TimeSeries!$C:$C,2025))/(COUNTIFS(Tableau_TimeSeries!$H:$H,"<>",Tableau_TimeSeries!$A:$A,"XV",Tableau_TimeSeries!$C:$C,2024,Tableau_TimeSeries!$D:$D,"Q4")+COUNTIFS(Tableau_TimeSeries!$H:$H,"<>",Tableau_TimeSeries!$A:$A,"XV",Tableau_TimeSeries!$C:$C,2025)) -> 120.4725 | H14: =SUMIFS(Tableau_TimeSeries!$F:$F,Tableau_TimeSeries!$A:$A,"XV",Tableau_TimeSeries!$C:$C,2019) -> 19830 | I14: =D14/H14*100 -> 138.39133 | J14: =E14/SUMIFS(Tableau_TimeSeries!$G:$G,Tableau_TimeSeries!$A:$A,"XV",Tableau_TimeSeries!$C:$C,2019)*100 -> 132.66651 | K14: =D14/(D14+E14)*100 -> 30.679709
A15: I | B15: Tarapacá | C15: Wait | D15: =SUMIFS(Tableau_TimeSeries!$F:$F,Tableau_TimeSeries!$A:$A,"I",Tableau_TimeSeries!$C:$C,2024,Tableau_TimeSeries!$D:$D,"Q4")+SUMIFS(Tableau_TimeSeries!$F:$F,Tableau_TimeSeries!$A:$A,"I",Tableau_TimeSeries!$C:$C,2025) -> 28257 | E15: =SUMIFS(Tableau_TimeSeries!$G:$G,Tableau_TimeSeries!$A:$A,"I",Tableau_TimeSeries!$C:$C,2024,Tableau_TimeSeries!$D:$D,"Q4")+SUMIFS(Tableau_TimeSeries!$G:$G,Tableau_TimeSeries!$A:$A,"I",Tableau_TimeSeries!$C:$C,2025) -> 58128 | F15: =(SUMIFS(Tableau_TimeSeries!$I:$I,Tableau_TimeSeries!$A:$A,"I",Tableau_TimeSeries!$C:$C,2024,Tableau_TimeSeries!$D:$D,"Q4")+SUMIFS(Tableau_TimeSeries!$I:$I,Tableau_TimeSeries!$A:$A,"I",Tableau_TimeSeries!$C:$C,2025))/(COUNTIFS(Tableau_TimeSeries!$I:$I,"<>",Tableau_TimeSeries!$A:$A,"I",Tableau_TimeSeries!$C:$C,2024,Tableau_TimeSeries!$D:$D,"Q4")+COUNTIFS(Tableau_TimeSeries!$I:$I,"<>",Tableau_TimeSeries!$A:$A,"I",Tableau_TimeSeries!$C:$C,2025)) -> 57.15 | G15: =(SUMIFS(Tableau_TimeSeries!$H:$H,Tableau_TimeSeries!$A:$A,"I",Tableau_TimeSeries!$C:$C,2024,Tableau_TimeSeries!$D:$D,"Q4")+SUMIFS(Tableau_TimeSeries!$H:$H,Tableau_TimeSeries!$A:$A,"I",Tableau_TimeSeries!$C:$C,2025))/(COUNTIFS(Tableau_TimeSeries!$H:$H,"<>",Tableau_TimeSeries!$A:$A,"I",Tableau_TimeSeries!$C:$C,2024,Tableau_TimeSeries!$D:$D,"Q4")+COUNTIFS(Tableau_TimeSeries!$H:$H,"<>",Tableau_TimeSeries!$A:$A,"I",Tableau_TimeSeries!$C:$C,2025)) -> 117.5975 | H15: =SUMIFS(Tableau_TimeSeries!$F:$F,Tableau_TimeSeries!$A:$A,"I",Tableau_TimeSeries!$C:$C,2019) -> 19089 | I15: =D15/H15*100 -> 148.02766 | J15: =E15/SUMIFS(Tableau_TimeSeries!$G:$G,Tableau_TimeSeries!$A:$A,"I",Tableau_TimeSeries!$C:$C,2019)*100 -> 114.37566 | K15: =D15/(D15+E15)*100 -> 32.71054
A16: II | B16: Antofagasta | C16: Prepare First | D16: =SUMIFS(Tableau_TimeSeries!$F:$F,Tableau_TimeSeries!$A:$A,"II",Tableau_TimeSeries!$C:$C,2024,Tableau_TimeSeries!$D:$D,"Q4")+SUMIFS(Tableau_TimeSeries!$F:$F,Tableau_TimeSeries!$A:$A,"II",Tableau_TimeSeries!$C:$C,2025) -> 42832 | E16: =SUMIFS(Tableau_TimeSeries!$G:$G,Tableau_TimeSeries!$A:$A,"II",Tableau_TimeSeries!$C:$C,2024,Tableau_TimeSeries!$D:$D,"Q4")+SUMIFS(Tableau_TimeSeries!$G:$G,Tableau_TimeSeries!$A:$A,"II",Tableau_TimeSeries!$C:$C,2025) -> 96553 | F16: =(SUMIFS(Tableau_TimeSeries!$I:$I,Tableau_TimeSeries!$A:$A,"II",Tableau_TimeSeries!$C:$C,2024,Tableau_TimeSeries!$D:$D,"Q4")+SUMIFS(Tableau_TimeSeries!$I:$I,Tableau_TimeSeries!$A:$A,"II",Tableau_TimeSeries!$C:$C,2025))/(COUNTIFS(Tableau_TimeSeries!$I:$I,"<>",Tableau_TimeSeries!$A:$A,"II",Tableau_TimeSeries!$C:$C,2024,Tableau_TimeSeries!$D:$D,"Q4")+COUNTIFS(Tableau_TimeSeries!$I:$I,"<>",Tableau_TimeSeries!$A:$A,"II",Tableau_TimeSeries!$C:$C,2025)) -> 54.2 | G16: =(SUMIFS(Tableau_TimeSeries!$H:$H,Tableau_TimeSeries!$A:$A,"II",Tableau_TimeSeries!$C:$C,2024,Tableau_TimeSeries!$D:$D,"Q4")+SUMIFS(Tableau_TimeSeries!$H:$H,Tableau_TimeSeries!$A:$A,"II",Tableau_TimeSeries!$C:$C,2025))/(COUNTIFS(Tableau_TimeSeries!$H:$H,"<>",Tableau_TimeSeries!$A:$A,"II",Tableau_TimeSeries!$C:$C,2024,Tableau_TimeSeries!$D:$D,"Q4")+COUNTIFS(Tableau_TimeSeries!$H:$H,"<>",Tableau_TimeSeries!$A:$A,"II",Tableau_TimeSeries!$C:$C,2025)) -> 121.5225 | H16: =SUMIFS(Tableau_TimeSeries!$F:$F,Tableau_TimeSeries!$A:$A,"II",Tableau_TimeSeries!$C:$C,2019) -> 33755 | I16: =D16/H16*100 -> 126.89083 | J16: =E16/SUMIFS(Tableau_TimeSeries!$G:$G,Tableau_TimeSeries!$A:$A,"II",Tableau_TimeSeries!$C:$C,2019)*100 -> 120.36176 | K16: =D16/(D16+E16)*100 -> 30.729275
A17: III | B17: Atacama | C17: Prepare First | D17: =SUMIFS(Tableau_TimeSeries!$F:$F,Tableau_TimeSeries!$A:$A,"III",Tableau_TimeSeries!$C:$C,2024,Tableau_TimeSeries!$D:$D,"Q4")+SUMIFS(Tableau_TimeSeries!$F:$F,Tableau_TimeSeries!$A:$A,"III",Tableau_TimeSeries!$C:$C,2025) -> 34383 | E17: =SUMIFS(Tableau_TimeSeries!$G:$G,Tableau_TimeSeries!$A:$A,"III",Tableau_TimeSeries!$C:$C,2024,Tableau_TimeSeries!$D:$D,"Q4")+SUMIFS(Tableau_TimeSeries!$G:$G,Tableau_TimeSeries!$A:$A,"III",Tableau_TimeSeries!$C:$C,2025) -> 75620 | F17: =(SUMIFS(Tableau_TimeSeries!$I:$I,Tableau_TimeSeries!$A:$A,"III",Tableau_TimeSeries!$C:$C,2024,Tableau_TimeSeries!$D:$D,"Q4")+SUMIFS(Tableau_TimeSeries!$I:$I,Tableau_TimeSeries!$A:$A,"III",Tableau_TimeSeries!$C:$C,2025))/(COUNTIFS(Tableau_TimeSeries!$I:$I,"<>",Tableau_TimeSeries!$A:$A,"III",Tableau_TimeSeries!$C:$C,2024,Tableau_TimeSeries!$D:$D,"Q4")+COUNTIFS(Tableau_TimeSeries!$I:$I,"<>",Tableau_TimeSeries!$A:$A,"III",Tableau_TimeSeries!$C:$C,2025)) -> 57.35 | G17: =(SUMIFS(Tableau_TimeSeries!$H:$H,Tableau_TimeSeries!$A:$A,"III",Tableau_TimeSeries!$C:$C,2024,Tableau_TimeSeries!$D:$D,"Q4")+SUMIFS(Tableau_TimeSeries!$H:$H,Tableau_TimeSeries!$A:$A,"III",Tableau_TimeSeries!$C:$C,2025))/(COUNTIFS(Tableau_TimeSeries!$H:$H,"<>",Tableau_TimeSeries!$A:$A,"III",Tableau_TimeSeries!$C:$C,2024,Tableau_TimeSeries!$D:$D,"Q4")+COUNTIFS(Tableau_TimeSeries!$H:$H,"<>",Tableau_TimeSeries!$A:$A,"III",Tableau_TimeSeries!$C:$C,2025)) -> 121.285 | H17: =SUMIFS(Tableau_TimeSeries!$F:$F,Tableau_TimeSeries!$A:$A,"III",Tableau_TimeSeries!$C:$C,2019) -> 24877 | I17: =D17/H17*100 -> 138.212 | J17: =E17/SUMIFS(Tableau_TimeSeries!$G:$G,Tableau_TimeSeries!$A:$A,"III",Tableau_TimeSeries!$C:$C,2019)*100 -> 117.87629 | K17: =D17/(D17+E17)*100 -> 31.25642
A18: IV | B18: Coquimbo | C18: Scale Now | D18: =SUMIFS(Tableau_TimeSeries!$F:$F,Tableau_TimeSeries!$A:$A,"IV",Tableau_TimeSeries!$C:$C,2024,Tableau_TimeSeries!$D:$D,"Q4")+SUMIFS(Tableau_TimeSeries!$F:$F,Tableau_TimeSeries!$A:$A,"IV",Tableau_TimeSeries!$C:$C,2025) -> 46864 | E18: =SUMIFS(Tableau_TimeSeries!$G:$G,Tableau_TimeSeries!$A:$A,"IV",Tableau_TimeSeries!$C:$C,2024,Tableau_TimeSeries!$D:$D,"Q4")+SUMIFS(Tableau_TimeSeries!$G:$G,Tableau_TimeSeries!$A:$A,"IV",Tableau_TimeSeries!$C:$C,2025) -> 92537 | F18: =(SUMIFS(Tableau_TimeSeries!$I:$I,Tableau_TimeSeries!$A:$A,"IV",Tableau_TimeSeries!$C:$C,2024,Tableau_TimeSeries!$D:$D,"Q4")+SUMIFS(Tableau_TimeSeries!$I:$I,Tableau_TimeSeries!$A:$A,"IV",Tableau_TimeSeries!$C:$C,2025))/(COUNTIFS(Tableau_TimeSeries!$I:$I,"<>",Tableau_TimeSeries!$A:$A,"IV",Tableau_TimeSeries!$C:$C,2024,Tableau_TimeSeries!$D:$D,"Q4")+COUNTIFS(Tableau_TimeSeries!$I:$I,"<>",Tableau_TimeSeries!$A:$A,"IV",Tableau_TimeSeries!$C:$C,2025)) -> 61.475 | G18: =(SUMIFS(Tableau_TimeSeries!$H:$H,Tableau_TimeSeries!$A:$A,"IV",Tableau_TimeSeries!$C:$C,2024,Tableau_TimeSeries!$D:$D,"Q4")+SUMIFS(Tableau_TimeSeries!$H:$H,Tableau_TimeSeries!$A:$A,"IV",Tableau_TimeSeries!$C:$C,2025))/(COUNTIFS(Tableau_TimeSeries!$H:$H,"<>",Tableau_TimeSeries!$A:$A,"IV",Tableau_TimeSeries!$C:$C,2024,Tableau_TimeSeries!$D:$D,"Q4")+COUNTIFS(Tableau_TimeSeries!$H:$H,"<>",Tableau_TimeSeries!$A:$A,"IV",Tableau_TimeSeries!$C:$C,2025)) -> 132.575 | H18: =SUMIFS(Tableau_TimeSeries!$F:$F,Tableau_TimeSeries!$A:$A,"IV",Tableau_TimeSeries!$C:$C,2019) -> 29596 | I18: =D18/H18*100 -> 158.34572 | J18: =E18/SUMIFS(Tableau_TimeSeries!$G:$G,Tableau_TimeSeries!$A:$A,"IV",Tableau_TimeSeries!$C:$C,2019)*100 -> 125.12778 | K18: =D18/(D18+E18)*100 -> 33.618123
A19: V | B19: Valparaíso | C19: Scale Now | D19: =SUMIFS(Tableau_TimeSeries!$F:$F,Tableau_TimeSeries!$A:$A,"V",Tableau_TimeSeries!$C:$C,2024,Tableau_TimeSeries!$D:$D,"Q4")+SUMIFS(Tableau_TimeSeries!$F:$F,Tableau_TimeSeries!$A:$A,"V",Tableau_TimeSeries!$C:$C,2025) -> 83544 | E19: =SUMIFS(Tableau_TimeSeries!$G:$G,Tableau_TimeSeries!$A:$A,"V",Tableau_TimeSeries!$C:$C,2024,Tableau_TimeSeries!$D:$D,"Q4")+SUMIFS(Tableau_TimeSeries!$G:$G,Tableau_TimeSeries!$A:$A,"V",Tableau_TimeSeries!$C:$C,2025) -> 189639 | F19: =(SUMIFS(Tableau_TimeSeries!$I:$I,Tableau_TimeSeries!$A:$A,"V",Tableau_TimeSeries!$C:$C,2024,Tableau_TimeSeries!$D:$D,"Q4")+SUMIFS(Tableau_TimeSeries!$I:$I,Tableau_TimeSeries!$A:$A,"V",Tableau_TimeSeries!$C:$C,2025))/(COUNTIFS(Tableau_TimeSeries!$I:$I,"<>",Tableau_TimeSeries!$A:$A,"V",Tableau_TimeSeries!$C:$C,2024,Tableau_TimeSeries!$D:$D,"Q4")+COUNTIFS(Tableau_TimeSeries!$I:$I,"<>",Tableau_TimeSeries!$A:$A,"V",Tableau_TimeSeries!$C:$C,2025)) -> 64.325 | G19: =(SUMIFS(Tableau_TimeSeries!$H:$H,Tableau_TimeSeries!$A:$A,"V",Tableau_TimeSeries!$C:$C,2024,Tableau_TimeSeries!$D:$D,"Q4")+SUMIFS(Tableau_TimeSeries!$H:$H,Tableau_TimeSeries!$A:$A,"V",Tableau_TimeSeries!$C:$C,2025))/(COUNTIFS(Tableau_TimeSeries!$H:$H,"<>",Tableau_TimeSeries!$A:$A,"V",Tableau_TimeSeries!$C:$C,2024,Tableau_TimeSeries!$D:$D,"Q4")+COUNTIFS(Tableau_TimeSeries!$H:$H,"<>",Tableau_TimeSeries!$A:$A,"V",Tableau_TimeSeries!$C:$C,2025)) -> 135.7025 | H19: =SUMIFS(Tableau_TimeSeries!$F:$F,Tableau_TimeSeries!$A:$A,"V",Tableau_TimeSeries!$C:$C,2019) -> 64881 | I19: =D19/H19*100 -> 128.76497 | J19: =E19/SUMIFS(Tableau_TimeSeries!$G:$G,Tableau_TimeSeries!$A:$A,"V",Tableau_TimeSeries!$C:$C,2019)*100 -> 122.92031 | K19: =D19/(D19+E19)*100 -> 30.581698
A20: RM | B20: Metropolitana | C20: Scale Now | D20: =SUMIFS(Tableau_TimeSeries!$F:$F,Tableau_TimeSeries!$A:$A,"RM",Tableau_TimeSeries!$C:$C,2024,Tableau_TimeSeries!$D:$D,"Q4")+SUMIFS(Tableau_TimeSeries!$F:$F,Tableau_TimeSeries!$A:$A,"RM",Tableau_TimeSeries!$C:$C,2025) -> 165173 | E20: =SUMIFS(Tableau_TimeSeries!$G:$G,Tableau_TimeSeries!$A:$A,"RM",Tableau_TimeSeries!$C:$C,2024,Tableau_TimeSeries!$D:$D,"Q4")+SUMIFS(Tableau_TimeSeries!$G:$G,Tableau_TimeSeries!$A:$A,"RM",Tableau_TimeSeries!$C:$C,2025) -> 310477 | F20: =(SUMIFS(Tableau_TimeSeries!$I:$I,Tableau_TimeSeries!$A:$A,"RM",Tableau_TimeSeries!$C:$C,2024,Tableau_TimeSeries!$D:$D,"Q4")+SUMIFS(Tableau_TimeSeries!$I:$I,Tableau_TimeSeries!$A:$A,"RM",Tableau_TimeSeries!$C:$C,2025))/(COUNTIFS(Tableau_TimeSeries!$I:$I,"<>",Tableau_TimeSeries!$A:$A,"RM",Tableau_TimeSeries!$C:$C,2024,Tableau_TimeSeries!$D:$D,"Q4")+COUNTIFS(Tableau_TimeSeries!$I:$I,"<>",Tableau_TimeSeries!$A:$A,"RM",Tableau_TimeSeries!$C:$C,2025)) -> 62 | G20: =(SUMIFS(Tableau_TimeSeries!$H:$H,Tableau_TimeSeries!$A:$A,"RM",Tableau_TimeSeries!$C:$C,2024,Tableau_TimeSeries!$D:$D,"Q4")+SUMIFS(Tableau_TimeSeries!$H:$H,Tableau_TimeSeries!$A:$A,"RM",Tableau_TimeSeries!$C:$C,2025))/(COUNTIFS(Tableau_TimeSeries!$H:$H,"<>",Tableau_TimeSeries!$A:$A,"RM",Tableau_TimeSeries!$C:$C,2024,Tableau_TimeSeries!$D:$D,"Q4")+COUNTIFS(Tableau_TimeSeries!$H:$H,"<>",Tableau_TimeSeries!$A:$A,"RM",Tableau_TimeSeries!$C:$C,2025)) -> 177.9475 | H20: =SUMIFS(Tableau_TimeSeries!$F:$F,Tableau_TimeSeries!$A:$A,"RM",Tableau_TimeSeries!$C:$C,2019) -> 94539 | I20: =D20/H20*100 -> 174.71414 | J20: =E20/SUMIFS(Tableau_TimeSeries!$G:$G,Tableau_TimeSeries!$A:$A,"RM",Tableau_TimeSeries!$C:$C,2019)*100 -> 134.59383 | K20: =D20/(D20+E20)*100 -> 34.725744
A21: VI | B21: O'Higgins | C21: Prepare First | D21: =SUMIFS(Tableau_TimeSeries!$F:$F,Tableau_TimeSeries!$A:$A,"VI",Tableau_TimeSeries!$C:$C,2024,Tableau_TimeSeries!$D:$D,"Q4")+SUMIFS(Tableau_TimeSeries!$F:$F,Tableau_TimeSeries!$A:$A,"VI",Tableau_TimeSeries!$C:$C,2025) -> 25232 | E21: =SUMIFS(Tableau_TimeSeries!$G:$G,Tableau_TimeSeries!$A:$A,"VI",Tableau_TimeSeries!$C:$C,2024,Tableau_TimeSeries!$D:$D,"Q4")+SUMIFS(Tableau_TimeSeries!$G:$G,Tableau_TimeSeries!$A:$A,"VI",Tableau_TimeSeries!$C:$C,2025) -> 54933 | F21: =(SUMIFS(Tableau_TimeSeries!$I:$I,Tableau_TimeSeries!$A:$A,"VI",Tableau_TimeSeries!$C:$C,2024,Tableau_TimeSeries!$D:$D,"Q4")+SUMIFS(Tableau_TimeSeries!$I:$I,Tableau_TimeSeries!$A:$A,"VI",Tableau_TimeSeries!$C:$C,2025))/(COUNTIFS(Tableau_TimeSeries!$I:$I,"<>",Tableau_TimeSeries!$A:$A,"VI",Tableau_TimeSeries!$C:$C,2024,Tableau_TimeSeries!$D:$D,"Q4")+COUNTIFS(Tableau_TimeSeries!$I:$I,"<>",Tableau_TimeSeries!$A:$A,"VI",Tableau_TimeSeries!$C:$C,2025)) -> 58.25 | G21: =(SUMIFS(Tableau_TimeSeries!$H:$H,Tableau_TimeSeries!$A:$A,"VI",Tableau_TimeSeries!$C:$C,2024,Tableau_TimeSeries!$D:$D,"Q4")+SUMIFS(Tableau_TimeSeries!$H:$H,Tableau_TimeSeries!$A:$A,"VI",Tableau_TimeSeries!$C:$C,2025))/(COUNTIFS(Tableau_TimeSeries!$H:$H,"<>",Tableau_TimeSeries!$A:$A,"VI",Tableau_TimeSeries!$C:$C,2024,Tableau_TimeSeries!$D:$D,"Q4")+COUNTIFS(Tableau_TimeSeries!$H:$H,"<>",Tableau_TimeSeries!$A:$A,"VI",Tableau_TimeSeries!$C:$C,2025)) -> 105.1225 | H21: =SUMIFS(Tableau_TimeSeries!$F:$F,Tableau_TimeSeries!$A:$A,"VI",Tableau_TimeSeries!$C:$C,2019) -> 20633 | I21: =D21/H21*100 -> 122.28954 | J21: =E21/SUMIFS(Tableau_TimeSeries!$G:$G,Tableau_TimeSeries!$A:$A,"VI",Tableau_TimeSeries!$C:$C,2019)*100 -> 114.1892 | K21: =D21/(D21+E21)*100 -> 31.475083
A22: VII | B22: Maule | C22: Prepare First | D22: =SUMIFS(Tableau_TimeSeries!$F:$F,Tableau_TimeSeries!$A:$A,"VII",Tableau_TimeSeries!$C:$C,2024,Tableau_TimeSeries!$D:$D,"Q4")+SUMIFS(Tableau_TimeSeries!$F:$F,Tableau_TimeSeries!$A:$A,"VII",Tableau_TimeSeries!$C:$C,2025) -> 34396 | E22: =SUMIFS(Tableau_TimeSeries!$G:$G,Tableau_TimeSeries!$A:$A,"VII",Tableau_TimeSeries!$C:$C,2024,Tableau_TimeSeries!$D:$D,"Q4")+SUMIFS(Tableau_TimeSeries!$G:$G,Tableau_TimeSeries!$A:$A,"VII",Tableau_TimeSeries!$C:$C,2025) -> 73670 | F22: =(SUMIFS(Tableau_TimeSeries!$I:$I,Tableau_TimeSeries!$A:$A,"VII",Tableau_TimeSeries!$C:$C,2024,Tableau_TimeSeries!$D:$D,"Q4")+SUMIFS(Tableau_TimeSeries!$I:$I,Tableau_TimeSeries!$A:$A,"VII",Tableau_TimeSeries!$C:$C,2025))/(COUNTIFS(Tableau_TimeSeries!$I:$I,"<>",Tableau_TimeSeries!$A:$A,"VII",Tableau_TimeSeries!$C:$C,2024,Tableau_TimeSeries!$D:$D,"Q4")+COUNTIFS(Tableau_TimeSeries!$I:$I,"<>",Tableau_TimeSeries!$A:$A,"VII",Tableau_TimeSeries!$C:$C,2025)) -> 62.75 | G22: =(SUMIFS(Tableau_TimeSeries!$H:$H,Tableau_TimeSeries!$A:$A,"VII",Tableau_TimeSeries!$C:$C,2024,Tableau_TimeSeries!$D:$D,"Q4")+SUMIFS(Tableau_TimeSeries!$H:$H,Tableau_TimeSeries!$A:$A,"VII",Tableau_TimeSeries!$C:$C,2025))/(COUNTIFS(Tableau_TimeSeries!$H:$H,"<>",Tableau_TimeSeries!$A:$A,"VII",Tableau_TimeSeries!$C:$C,2024,Tableau_TimeSeries!$D:$D,"Q4")+COUNTIFS(Tableau_TimeSeries!$H:$H,"<>",Tableau_TimeSeries!$A:$A,"VII",Tableau_TimeSeries!$C:$C,2025)) -> 159.355 | H22: =SUMIFS(Tableau_TimeSeries!$F:$F,Tableau_TimeSeries!$A:$A,"VII",Tableau_TimeSeries!$C:$C,2019) -> 21817 | I22: =D22/H22*100 -> 157.65687 | J22: =E22/SUMIFS(Tableau_TimeSeries!$G:$G,Tableau_TimeSeries!$A:$A,"VII",Tableau_TimeSeries!$C:$C,2019)*100 -> 133.16102 | K22: =D22/(D22+E22)*100 -> 31.828697
A23: VIII | B23: Biobío | C23: Prepare First | D23: =SUMIFS(Tableau_TimeSeries!$F:$F,Tableau_TimeSeries!$A:$A,"VIII",Tableau_TimeSeries!$C:$C,2024,Tableau_TimeSeries!$D:$D,"Q4")+SUMIFS(Tableau_TimeSeries!$F:$F,Tableau_TimeSeries!$A:$A,"VIII",Tableau_TimeSeries!$C:$C,2025) -> 46785 | E23: =SUMIFS(Tableau_TimeSeries!$G:$G,Tableau_TimeSeries!$A:$A,"VIII",Tableau_TimeSeries!$C:$C,2024,Tableau_TimeSeries!$D:$D,"Q4")+SUMIFS(Tableau_TimeSeries!$G:$G,Tableau_TimeSeries!$A:$A,"VIII",Tableau_TimeSeries!$C:$C,2025) -> 97803 | F23: =(SUMIFS(Tableau_TimeSeries!$I:$I,Tableau_TimeSeries!$A:$A,"VIII",Tableau_TimeSeries!$C:$C,2024,Tableau_TimeSeries!$D:$D,"Q4")+SUMIFS(Tableau_TimeSeries!$I:$I,Tableau_TimeSeries!$A:$A,"VIII",Tableau_TimeSeries!$C:$C,2025))/(COUNTIFS(Tableau_TimeSeries!$I:$I,"<>",Tableau_TimeSeries!$A:$A,"VIII",Tableau_TimeSeries!$C:$C,2024,Tableau_TimeSeries!$D:$D,"Q4")+COUNTIFS(Tableau_TimeSeries!$I:$I,"<>",Tableau_TimeSeries!$A:$A,"VIII",Tableau_TimeSeries!$C:$C,2025)) -> 54.35 | G23: =(SUMIFS(Tableau_TimeSeries!$H:$H,Tableau_TimeSeries!$A:$A,"VIII",Tableau_TimeSeries!$C:$C,2024,Tableau_TimeSeries!$D:$D,"Q4")+SUMIFS(Tableau_TimeSeries!$H:$H,Tableau_TimeSeries!$A:$A,"VIII",Tableau_TimeSeries!$C:$C,2025))/(COUNTIFS(Tableau_TimeSeries!$H:$H,"<>",Tableau_TimeSeries!$A:$A,"VIII",Tableau_TimeSeries!$C:$C,2024,Tableau_TimeSeries!$D:$D,"Q4")+COUNTIFS(Tableau_TimeSeries!$H:$H,"<>",Tableau_TimeSeries!$A:$A,"VIII",Tableau_TimeSeries!$C:$C,2025)) -> 128.78 | H23: =SUMIFS(Tableau_TimeSeries!$F:$F,Tableau_TimeSeries!$A:$A,"VIII",Tableau_TimeSeries!$C:$C,2019) -> 30992 | I23: =D23/H23*100 -> 150.95831 | J23: =E23/SUMIFS(Tableau_TimeSeries!$G:$G,Tableau_TimeSeries!$A:$A,"VIII",Tableau_TimeSeries!$C:$C,2019)*100 -> 127.02843 | K23: =D23/(D23+E23)*100 -> 32.357457
A24: IX | B24: Araucanía | C24: Prepare First | D24: =SUMIFS(Tableau_TimeSeries!$F:$F,Tableau_TimeSeries!$A:$A,"IX",Tableau_TimeSeries!$C:$C,2024,Tableau_TimeSeries!$D:$D,"Q4")+SUMIFS(Tableau_TimeSeries!$F:$F,Tableau_TimeSeries!$A:$A,"IX",Tableau_TimeSeries!$C:$C,2025) -> 52059 | E24: =SUMIFS(Tableau_TimeSeries!$G:$G,Tableau_TimeSeries!$A:$A,"IX",Tableau_TimeSeries!$C:$C,2024,Tableau_TimeSeries!$D:$D,"Q4")+SUMIFS(Tableau_TimeSeries!$G:$G,Tableau_TimeSeries!$A:$A,"IX",Tableau_TimeSeries!$C:$C,2025) -> 111387 | F24: =(SUMIFS(Tableau_TimeSeries!$I:$I,Tableau_TimeSeries!$A:$A,"IX",Tableau_TimeSeries!$C:$C,2024,Tableau_TimeSeries!$D:$D,"Q4")+SUMIFS(Tableau_TimeSeries!$I:$I,Tableau_TimeSeries!$A:$A,"IX",Tableau_TimeSeries!$C:$C,2025))/(COUNTIFS(Tableau_TimeSeries!$I:$I,"<>",Tableau_TimeSeries!$A:$A,"IX",Tableau_TimeSeries!$C:$C,2024,Tableau_TimeSeries!$D:$D,"Q4")+COUNTIFS(Tableau_TimeSeries!$I:$I,"<>",Tableau_TimeSeries!$A:$A,"IX",Tableau_TimeSeries!$C:$C,2025)) -> 49.7 | G24: =(SUMIFS(Tableau_TimeSeries!$H:$H,Tableau_TimeSeries!$A:$A,"IX",Tableau_TimeSeries!$C:$C,2024,Tableau_TimeSeries!$D:$D,"Q4")+SUMIFS(Tableau_TimeSeries!$H:$H,Tableau_TimeSeries!$A:$A,"IX",Tableau_TimeSeries!$C:$C,2025))/(COUNTIFS(Tableau_TimeSeries!$H:$H,"<>",Tableau_TimeSeries!$A:$A,"IX",Tableau_TimeSeries!$C:$C,2024,Tableau_TimeSeries!$D:$D,"Q4")+COUNTIFS(Tableau_TimeSeries!$H:$H,"<>",Tableau_TimeSeries!$A:$A,"IX",Tableau_TimeSeries!$C:$C,2025)) -> 109.0175 | H24: =SUMIFS(Tableau_TimeSeries!$F:$F,Tableau_TimeSeries!$A:$A,"IX",Tableau_TimeSeries!$C:$C,2019) -> 36346 | I24: =D24/H24*100 -> 143.23172 | J24: =E24/SUMIFS(Tableau_TimeSeries!$G:$G,Tableau_TimeSeries!$A:$A,"IX",Tableau_TimeSeries!$C:$C,2019)*100 -> 126.45399 | K24: =D24/(D24+E24)*100 -> 31.850887
A25: XIV | B25: Los Ríos | C25: Prepare First | D25: =SUMIFS(Tableau_TimeSeries!$F:$F,Tableau_TimeSeries!$A:$A,"XIV",Tableau_TimeSeries!$C:$C,2024,Tableau_TimeSeries!$D:$D,"Q4")+SUMIFS(Tableau_TimeSeries!$F:$F,Tableau_TimeSeries!$A:$A,"XIV",Tableau_TimeSeries!$C:$C,2025) -> 29814 | E25: =SUMIFS(Tableau_TimeSeries!$G:$G,Tableau_TimeSeries!$A:$A,"XIV",Tableau_TimeSeries!$C:$C,2024,Tableau_TimeSeries!$D:$D,"Q4")+SUMIFS(Tableau_TimeSeries!$G:$G,Tableau_TimeSeries!$A:$A,"XIV",Tableau_TimeSeries!$C:$C,2025) -> 69560 | F25: =(SUMIFS(Tableau_TimeSeries!$I:$I,Tableau_TimeSeries!$A:$A,"XIV",Tableau_TimeSeries!$C:$C,2024,Tableau_TimeSeries!$D:$D,"Q4")+SUMIFS(Tableau_TimeSeries!$I:$I,Tableau_TimeSeries!$A:$A,"XIV",Tableau_TimeSeries!$C:$C,2025))/(COUNTIFS(Tableau_TimeSeries!$I:$I,"<>",Tableau_TimeSeries!$A:$A,"XIV",Tableau_TimeSeries!$C:$C,2024,Tableau_TimeSeries!$D:$D,"Q4")+COUNTIFS(Tableau_TimeSeries!$I:$I,"<>",Tableau_TimeSeries!$A:$A,"XIV",Tableau_TimeSeries!$C:$C,2025)) -> 53.775 | G25: =(SUMIFS(Tableau_TimeSeries!$H:$H,Tableau_TimeSeries!$A:$A,"XIV",Tableau_TimeSeries!$C:$C,2024,Tableau_TimeSeries!$D:$D,"Q4")+SUMIFS(Tableau_TimeSeries!$H:$H,Tableau_TimeSeries!$A:$A,"XIV",Tableau_TimeSeries!$C:$C,2025))/(COUNTIFS(Tableau_TimeSeries!$H:$H,"<>",Tableau_TimeSeries!$A:$A,"XIV",Tableau_TimeSeries!$C:$C,2024,Tableau_TimeSeries!$D:$D,"Q4")+COUNTIFS(Tableau_TimeSeries!$H:$H,"<>",Tableau_TimeSeries!$A:$A,"XIV",Tableau_TimeSeries!$C:$C,2025)) -> 113.37 | H25: =SUMIFS(Tableau_TimeSeries!$F:$F,Tableau_TimeSeries!$A:$A,"XIV",Tableau_TimeSeries!$C:$C,2019) -> 22399 | I25: =D25/H25*100 -> 133.10416 | J25: =E25/SUMIFS(Tableau_TimeSeries!$G:$G,Tableau_TimeSeries!$A:$A,"XIV",Tableau_TimeSeries!$C:$C,2019)*100 -> 121.21001 | K25: =D25/(D25+E25)*100 -> 30.001811
A26: X | B26: Los Lagos | C26: Scale Now | D26: =SUMIFS(Tableau_TimeSeries!$F:$F,Tableau_TimeSeries!$A:$A,"X",Tableau_TimeSeries!$C:$C,2024,Tableau_TimeSeries!$D:$D,"Q4")+SUMIFS(Tableau_TimeSeries!$F:$F,Tableau_TimeSeries!$A:$A,"X",Tableau_TimeSeries!$C:$C,2025) -> 72505 | E26: =SUMIFS(Tableau_TimeSeries!$G:$G,Tableau_TimeSeries!$A:$A,"X",Tableau_TimeSeries!$C:$C,2024,Tableau_TimeSeries!$D:$D,"Q4")+SUMIFS(Tableau_TimeSeries!$G:$G,Tableau_TimeSeries!$A:$A,"X",Tableau_TimeSeries!$C:$C,2025) -> 159844 | F26: =(SUMIFS(Tableau_TimeSeries!$I:$I,Tableau_TimeSeries!$A:$A,"X",Tableau_TimeSeries!$C:$C,2024,Tableau_TimeSeries!$D:$D,"Q4")+SUMIFS(Tableau_TimeSeries!$I:$I,Tableau_TimeSeries!$A:$A,"X",Tableau_TimeSeries!$C:$C,2025))/(COUNTIFS(Tableau_TimeSeries!$I:$I,"<>",Tableau_TimeSeries!$A:$A,"X",Tableau_TimeSeries!$C:$C,2024,Tableau_TimeSeries!$D:$D,"Q4")+COUNTIFS(Tableau_TimeSeries!$I:$I,"<>",Tableau_TimeSeries!$A:$A,"X",Tableau_TimeSeries!$C:$C,2025)) -> 53.425 | G26: =(SUMIFS(Tableau_TimeSeries!$H:$H,Tableau_TimeSeries!$A:$A,"X",Tableau_TimeSeries!$C:$C,2024,Tableau_TimeSeries!$D:$D,"Q4")+SUMIFS(Tableau_TimeSeries!$H:$H,Tableau_TimeSeries!$A:$A,"X",Tableau_TimeSeries!$C:$C,2025))/(COUNTIFS(Tableau_TimeSeries!$H:$H,"<>",Tableau_TimeSeries!$A:$A,"X",Tableau_TimeSeries!$C:$C,2024,Tableau_TimeSeries!$D:$D,"Q4")+COUNTIFS(Tableau_TimeSeries!$H:$H,"<>",Tableau_TimeSeries!$A:$A,"X",Tableau_TimeSeries!$C:$C,2025)) -> 132.5525 | H26: =SUMIFS(Tableau_TimeSeries!$F:$F,Tableau_TimeSeries!$A:$A,"X",Tableau_TimeSeries!$C:$C,2019) -> 48256 | I26: =D26/H26*100 -> 150.25075 | J26: =E26/SUMIFS(Tableau_TimeSeries!$G:$G,Tableau_TimeSeries!$A:$A,"X",Tableau_TimeSeries!$C:$C,2019)*100 -> 141.30606 | K26: =D26/(D26+E26)*100 -> 31.205213
A27: XI | B27: Aysén | C27: Prepare First | D27: =SUMIFS(Tableau_TimeSeries!$F:$F,Tableau_TimeSeries!$A:$A,"XI",Tableau_TimeSeries!$C:$C,2024,Tableau_TimeSeries!$D:$D,"Q4")+SUMIFS(Tableau_TimeSeries!$F:$F,Tableau_TimeSeries!$A:$A,"XI",Tableau_TimeSeries!$C:$C,2025) -> 12922 | E27: =SUMIFS(Tableau_TimeSeries!$G:$G,Tableau_TimeSeries!$A:$A,"XI",Tableau_TimeSeries!$C:$C,2024,Tableau_TimeSeries!$D:$D,"Q4")+SUMIFS(Tableau_TimeSeries!$G:$G,Tableau_TimeSeries!$A:$A,"XI",Tableau_TimeSeries!$C:$C,2025) -> 30348 | F27: =(SUMIFS(Tableau_TimeSeries!$I:$I,Tableau_TimeSeries!$A:$A,"XI",Tableau_TimeSeries!$C:$C,2024,Tableau_TimeSeries!$D:$D,"Q4")+SUMIFS(Tableau_TimeSeries!$I:$I,Tableau_TimeSeries!$A:$A,"XI",Tableau_TimeSeries!$C:$C,2025))/(COUNTIFS(Tableau_TimeSeries!$I:$I,"<>",Tableau_TimeSeries!$A:$A,"XI",Tableau_TimeSeries!$C:$C,2024,Tableau_TimeSeries!$D:$D,"Q4")+COUNTIFS(Tableau_TimeSeries!$I:$I,"<>",Tableau_TimeSeries!$A:$A,"XI",Tableau_TimeSeries!$C:$C,2025)) -> 54.933333 | G27: =(SUMIFS(Tableau_TimeSeries!$H:$H,Tableau_TimeSeries!$A:$A,"XI",Tableau_TimeSeries!$C:$C,2024,Tableau_TimeSeries!$D:$D,"Q4")+SUMIFS(Tableau_TimeSeries!$H:$H,Tableau_TimeSeries!$A:$A,"XI",Tableau_TimeSeries!$C:$C,2025))/(COUNTIFS(Tableau_TimeSeries!$H:$H,"<>",Tableau_TimeSeries!$A:$A,"XI",Tableau_TimeSeries!$C:$C,2024,Tableau_TimeSeries!$D:$D,"Q4")+COUNTIFS(Tableau_TimeSeries!$H:$H,"<>",Tableau_TimeSeries!$A:$A,"XI",Tableau_TimeSeries!$C:$C,2025)) -> 166.95 | H27: =SUMIFS(Tableau_TimeSeries!$F:$F,Tableau_TimeSeries!$A:$A,"XI",Tableau_TimeSeries!$C:$C,2019) -> 10472 | I27: =D27/H27*100 -> 123.39572 | J27: =E27/SUMIFS(Tableau_TimeSeries!$G:$G,Tableau_TimeSeries!$A:$A,"XI",Tableau_TimeSeries!$C:$C,2019)*100 -> 120.61044 | K27: =D27/(D27+E27)*100 -> 29.863647
A28: XII | B28: Magallanes y Antártica | C28: Scale Now | D28: =SUMIFS(Tableau_TimeSeries!$F:$F,Tableau_TimeSeries!$A:$A,"XII",Tableau_TimeSeries!$C:$C,2024,Tableau_TimeSeries!$D:$D,"Q4")+SUMIFS(Tableau_TimeSeries!$F:$F,Tableau_TimeSeries!$A:$A,"XII",Tableau_TimeSeries!$C:$C,2025) -> 31509 | E28: =SUMIFS(Tableau_TimeSeries!$G:$G,Tableau_TimeSeries!$A:$A,"XII",Tableau_TimeSeries!$C:$C,2024,Tableau_TimeSeries!$D:$D,"Q4")+SUMIFS(Tableau_TimeSeries!$G:$G,Tableau_TimeSeries!$A:$A,"XII",Tableau_TimeSeries!$C:$C,2025) -> 69062 | F28: =(SUMIFS(Tableau_TimeSeries!$I:$I,Tableau_TimeSeries!$A:$A,"XII",Tableau_TimeSeries!$C:$C,2024,Tableau_TimeSeries!$D:$D,"Q4")+SUMIFS(Tableau_TimeSeries!$I:$I,Tableau_TimeSeries!$A:$A,"XII",Tableau_TimeSeries!$C:$C,2025))/(COUNTIFS(Tableau_TimeSeries!$I:$I,"<>",Tableau_TimeSeries!$A:$A,"XII",Tableau_TimeSeries!$C:$C,2024,Tableau_TimeSeries!$D:$D,"Q4")+COUNTIFS(Tableau_TimeSeries!$I:$I,"<>",Tableau_TimeSeries!$A:$A,"XII",Tableau_TimeSeries!$C:$C,2025)) -> 55.775 | G28: =(SUMIFS(Tableau_TimeSeries!$H:$H,Tableau_TimeSeries!$A:$A,"XII",Tableau_TimeSeries!$C:$C,2024,Tableau_TimeSeries!$D:$D,"Q4")+SUMIFS(Tableau_TimeSeries!$H:$H,Tableau_TimeSeries!$A:$A,"XII",Tableau_TimeSeries!$C:$C,2025))/(COUNTIFS(Tableau_TimeSeries!$H:$H,"<>",Tableau_TimeSeries!$A:$A,"XII",Tableau_TimeSeries!$C:$C,2024,Tableau_TimeSeries!$D:$D,"Q4")+COUNTIFS(Tableau_TimeSeries!$H:$H,"<>",Tableau_TimeSeries!$A:$A,"XII",Tableau_TimeSeries!$C:$C,2025)) -> 197.9675 | H28: =SUMIFS(Tableau_TimeSeries!$F:$F,Tableau_TimeSeries!$A:$A,"XII",Tableau_TimeSeries!$C:$C,2019) -> 23255 | I28: =D28/H28*100 -> 135.49344 | J28: =E28/SUMIFS(Tableau_TimeSeries!$G:$G,Tableau_TimeSeries!$A:$A,"XII",Tableau_TimeSeries!$C:$C,2019)*100 -> 127.57837 | K28: =D28/(D28+E28)*100 -> 31.330105
A30: Dimension | B30: Mean | C30: Std dev | D30: Min | E30: Max | F30: Coefficient of variation | G30: Top region | H30: Bottom region
A31: D1 Cultural Heritage & Events | B31: =AVERAGE(Dimension_Scores!$C$4:$C$18) -> 22.932225 | C31: =STDEV(Dimension_Scores!$C$4:$C$18) -> 13.268901 | D31: =MIN(Dimension_Scores!$C$4:$C$18) -> 6.3100783 | E31: =MAX(Dimension_Scores!$C$4:$C$18) -> 52.04743 | F31: =C31/B31 -> 0.57861377 | G31: =INDEX(Dimension_Scores!$B$4:$B$18,MATCH(MAX(Dimension_Scores!$C$4:$C$18),Dimension_Scores!$C$4:$C$18,0)) -> Metropolitana | H31: =INDEX(Dimension_Scores!$B$4:$B$18,MATCH(MIN(Dimension_Scores!$C$4:$C$18),Dimension_Scores!$C$4:$C$18,0)) -> Aysén
A32: D2 Natural Resources & Sustainability | B32: =AVERAGE(Dimension_Scores!$D$4:$D$18) -> 39.526132 | C32: =STDEV(Dimension_Scores!$D$4:$D$18) -> 11.902039 | D32: =MIN(Dimension_Scores!$D$4:$D$18) -> 16.941943 | E32: =MAX(Dimension_Scores!$D$4:$D$18) -> 57.620097 | F32: =C32/B32 -> 0.30111823 | G32: =INDEX(Dimension_Scores!$B$4:$B$18,MATCH(MAX(Dimension_Scores!$D$4:$D$18),Dimension_Scores!$D$4:$D$18,0)) -> Los Lagos | H32: =INDEX(Dimension_Scores!$B$4:$B$18,MATCH(MIN(Dimension_Scores!$D$4:$D$18),Dimension_Scores!$D$4:$D$18,0)) -> Metropolitana
A33: D3 Human Resources & Workforce | B33: =AVERAGE(Dimension_Scores!$E$4:$E$18) -> 29.209052 | C33: =STDEV(Dimension_Scores!$E$4:$E$18) -> 12.111952 | D33: =MIN(Dimension_Scores!$E$4:$E$18) -> 13.450882 | E33: =MAX(Dimension_Scores!$E$4:$E$18) -> 61.707192 | F33: =C33/B33 -> 0.41466433 | G33: =INDEX(Dimension_Scores!$B$4:$B$18,MATCH(MAX(Dimension_Scores!$E$4:$E$18),Dimension_Scores!$E$4:$E$18,0)) -> Metropolitana | H33: =INDEX(Dimension_Scores!$B$4:$B$18,MATCH(MIN(Dimension_Scores!$E$4:$E$18),Dimension_Scores!$E$4:$E$18,0)) -> Los Ríos
A34: D4 Tourism Infrastructure | B34: =AVERAGE(Dimension_Scores!$F$4:$F$18) -> 28.14291 | C34: =STDEV(Dimension_Scores!$F$4:$F$18) -> 13.800686 | D34: =MIN(Dimension_Scores!$F$4:$F$18) -> 12.34056 | E34: =MAX(Dimension_Scores!$F$4:$F$18) -> 61.701864 | F34: =C34/B34 -> 0.49037877 | G34: =INDEX(Dimension_Scores!$B$4:$B$18,MATCH(MAX(Dimension_Scores!$F$4:$F$18),Dimension_Scores!$F$4:$F$18,0)) -> Metropolitana | H34: =INDEX(Dimension_Scores!$B$4:$B$18,MATCH(MIN(Dimension_Scores!$F$4:$F$18),Dimension_Scores!$F$4:$F$18,0)) -> O'Higgins
A35: D5 Mobility & Transportation | B35: =AVERAGE(Dimension_Scores!$G$4:$G$18) -> 27.073545 | C35: =STDEV(Dimension_Scores!$G$4:$G$18) -> 14.187813 | D35: =MIN(Dimension_Scores!$G$4:$G$18) -> 7.6977449 | E35: =MAX(Dimension_Scores!$G$4:$G$18) -> 57.908505 | F35: =C35/B35 -> 0.5240471 | G35: =INDEX(Dimension_Scores!$B$4:$B$18,MATCH(MAX(Dimension_Scores!$G$4:$G$18),Dimension_Scores!$G$4:$G$18,0)) -> Metropolitana | H35: =INDEX(Dimension_Scores!$B$4:$B$18,MATCH(MIN(Dimension_Scores!$G$4:$G$18),Dimension_Scores!$G$4:$G$18,0)) -> O'Higgins
A36: D6 Tourism-Related Services | B36: =AVERAGE(Dimension_Scores!$H$4:$H$18) -> 28.750021 | C36: =STDEV(Dimension_Scores!$H$4:$H$18) -> 11.272622 | D36: =MIN(Dimension_Scores!$H$4:$H$18) -> 15.471814 | E36: =MAX(Dimension_Scores!$H$4:$H$18) -> 54.879212 | F36: =C36/B36 -> 0.39209093 | G36: =INDEX(Dimension_Scores!$B$4:$B$18,MATCH(MAX(Dimension_Scores!$H$4:$H$18),Dimension_Scores!$H$4:$H$18,0)) -> Metropolitana | H36: =INDEX(Dimension_Scores!$B$4:$B$18,MATCH(MIN(Dimension_Scores!$H$4:$H$18),Dimension_Scores!$H$4:$H$18,0)) -> Coquimbo
A37: D7 Security & Safety | B37: =AVERAGE(Dimension_Scores!$I$4:$I$18) -> 58.302335 | C37: =STDEV(Dimension_Scores!$I$4:$I$18) -> 6.4611915 | D37: =MIN(Dimension_Scores!$I$4:$I$18) -> 49.05692 | E37: =MAX(Dimension_Scores!$I$4:$I$18) -> 66.454617 | F37: =C37/B37 -> 0.11082217 | G37: =INDEX(Dimension_Scores!$B$4:$B$18,MATCH(MAX(Dimension_Scores!$I$4:$I$18),Dimension_Scores!$I$4:$I$18,0)) -> Biobío | H37: =INDEX(Dimension_Scores!$B$4:$B$18,MATCH(MIN(Dimension_Scores!$I$4:$I$18),Dimension_Scores!$I$4:$I$18,0)) -> Tarapacá
A38: D8 Economic Performance | B38: =AVERAGE(Dimension_Scores!$J$4:$J$18) -> 52.125337 | C38: =STDEV(Dimension_Scores!$J$4:$J$18) -> 9.4497583 | D38: =MIN(Dimension_Scores!$J$4:$J$18) -> 35.097898 | E38: =MAX(Dimension_Scores!$J$4:$J$18) -> 70.101033 | F38: =C38/B38 -> 0.18128915 | G38: =INDEX(Dimension_Scores!$B$4:$B$18,MATCH(MAX(Dimension_Scores!$J$4:$J$18),Dimension_Scores!$J$4:$J$18,0)) -> Los Lagos | H38: =INDEX(Dimension_Scores!$B$4:$B$18,MATCH(MIN(Dimension_Scores!$J$4:$J$18),Dimension_Scores!$J$4:$J$18,0)) -> Araucanía
A39: D9 Tourism Promotion | B39: =AVERAGE(Dimension_Scores!$K$4:$K$18) -> 26.668277 | C39: =STDEV(Dimension_Scores!$K$4:$K$18) -> 10.324055 | D39: =MIN(Dimension_Scores!$K$4:$K$18) -> 12.154815 | E39: =MAX(Dimension_Scores!$K$4:$K$18) -> 47.66839 | F39: =C39/B39 -> 0.38712871 | G39: =INDEX(Dimension_Scores!$B$4:$B$18,MATCH(MAX(Dimension_Scores!$K$4:$K$18),Dimension_Scores!$K$4:$K$18,0)) -> Magallanes y Antártica | H39: =INDEX(Dimension_Scores!$B$4:$B$18,MATCH(MIN(Dimension_Scores!$K$4:$K$18),Dimension_Scores!$K$4:$K$18,0)) -> Tarapacá
A40: D10 Governmental Involvement & Efficiency | B40: =AVERAGE(Dimension_Scores!$L$4:$L$18) -> 31.980065 | C40: =STDEV(Dimension_Scores!$L$4:$L$18) -> 21.256087 | D40: =MIN(Dimension_Scores!$L$4:$L$18) -> 5.9725558 | E40: =MAX(Dimension_Scores!$L$4:$L$18) -> 80.268633 | F40: =C40/B40 -> 0.66466677 | G40: =INDEX(Dimension_Scores!$B$4:$B$18,MATCH(MAX(Dimension_Scores!$L$4:$L$18),Dimension_Scores!$L$4:$L$18,0)) -> Biobío | H40: =INDEX(Dimension_Scores!$B$4:$B$18,MATCH(MIN(Dimension_Scores!$L$4:$L$18),Dimension_Scores!$L$4:$L$18,0)) -> Arica y Parinacota
A41: Reading: Security & Safety (D7) barely differentiates regions (CV ≈ 0.11) while Governmental Involvement (D10) differentiates most (CV ≈ 0.66); Metropolitana tops five of ten dimensions but is last on Natural Resources (D2).
A43: DB3 metric (405 region-quarters) | B43: Count | C43: Mean | D43: Std dev | E43: Min | F43: Median | G43: Max
A44: International arrivals | B44: =COUNT(Tableau_TimeSeries!$F$2:$F$406) -> 404 | C44: =AVERAGE(Tableau_TimeSeries!$F$2:$F$406) -> 7672.8218 | D44: =STDEV(Tableau_TimeSeries!$F$2:$F$406) -> 7798.0352 | E44: =MIN(Tableau_TimeSeries!$F$2:$F$406) -> 50 | F44: =MEDIAN(Tableau_TimeSeries!$F$2:$F$406) -> 6109 | G44: =MAX(Tableau_TimeSeries!$F$2:$F$406) -> 55042
A45: National arrivals | B45: =COUNT(Tableau_TimeSeries!$G$2:$G$406) -> 405 | C45: =AVERAGE(Tableau_TimeSeries!$G$2:$G$406) -> 19047.817 | D45: =STDEV(Tableau_TimeSeries!$G$2:$G$406) -> 15134.099 | E45: =MIN(Tableau_TimeSeries!$G$2:$G$406) -> 702 | F45: =MEDIAN(Tableau_TimeSeries!$G$2:$G$406) -> 15356 | G45: =MAX(Tableau_TimeSeries!$G$2:$G$406) -> 101196
A46: Average daily rate (USD) | B46: =COUNT(Tableau_TimeSeries!$H$2:$H$406) -> 400 | C46: =AVERAGE(Tableau_TimeSeries!$H$2:$H$406) -> 112.84035 | D46: =STDEV(Tableau_TimeSeries!$H$2:$H$406) -> 29.852954 | E46: =MIN(Tableau_TimeSeries!$H$2:$H$406) -> 61.32 | F46: =MEDIAN(Tableau_TimeSeries!$H$2:$H$406) -> 108.885 | G46: =MAX(Tableau_TimeSeries!$H$2:$H$406) -> 230.86
A47: Occupancy rate (%) | B47: =COUNT(Tableau_TimeSeries!$I$2:$I$406) -> 399 | C47: =AVERAGE(Tableau_TimeSeries!$I$2:$I$406) -> 49.736341 | D47: =STDEV(Tableau_TimeSeries!$I$2:$I$406) -> 12.732306 | E47: =MIN(Tableau_TimeSeries!$I$2:$I$406) -> 25.8 | F47: =MEDIAN(Tableau_TimeSeries!$I$2:$I$406) -> 50.5 | G47: =MAX(Tableau_TimeSeries!$I$2:$I$406) -> 88.7
A48: Length of stay (nights) | B48: =COUNT(Tableau_TimeSeries!$J$2:$J$406) -> 405 | C48: =AVERAGE(Tableau_TimeSeries!$J$2:$J$406) -> 2.5860988 | D48: =STDEV(Tableau_TimeSeries!$J$2:$J$406) -> 0.53013457 | E48: =MIN(Tableau_TimeSeries!$J$2:$J$406) -> 2.02 | F48: =MEDIAN(Tableau_TimeSeries!$J$2:$J$406) -> 2.43 | G48: =MAX(Tableau_TimeSeries!$J$2:$J$406) -> 4.71
A50: DB5 metric (15 regions, 2025) | B50: Count | C50: Mean | D50: Std dev | E50: Min | F50: Median | G50: Max
A51: Fixed broadband penetration % | B51: =COUNT(Tableau_DigitalReadiness!$D$2:$D$16) -> 15 | C51: =AVERAGE(Tableau_DigitalReadiness!$D$2:$D$16) -> 56.093333 | D51: =STDEV(Tableau_DigitalReadiness!$D$2:$D$16) -> 10.451416 | E51: =MIN(Tableau_DigitalReadiness!$D$2:$D$16) -> 37.3 | F51: =MEDIAN(Tableau_DigitalReadiness!$D$2:$D$16) -> 57.7 | G51: =MAX(Tableau_DigitalReadiness!$D$2:$D$16) -> 73.9
A52: Mobile 4G/5G coverage % | B52: =COUNT(Tableau_DigitalReadiness!$E$2:$E$16) -> 15 | C52: =AVERAGE(Tableau_DigitalReadiness!$E$2:$E$16) -> 69.813333 | D52: =STDEV(Tableau_DigitalReadiness!$E$2:$E$16) -> 6.5315571 | E52: =MIN(Tableau_DigitalReadiness!$E$2:$E$16) -> 61 | F52: =MEDIAN(Tableau_DigitalReadiness!$E$2:$E$16) -> 69.3 | G52: =MAX(Tableau_DigitalReadiness!$E$2:$E$16) -> 82.3
A53: E-commerce adoption % SMEs | B53: =COUNT(Tableau_DigitalReadiness!$F$2:$F$16) -> 15 | C53: =AVERAGE(Tableau_DigitalReadiness!$F$2:$F$16) -> 40.326667 | D53: =STDEV(Tableau_DigitalReadiness!$F$2:$F$16) -> 8.6930569 | E53: =MIN(Tableau_DigitalReadiness!$F$2:$F$16) -> 25.3 | F53: =MEDIAN(Tableau_DigitalReadiness!$F$2:$F$16) -> 42.4 | G53: =MAX(Tableau_DigitalReadiness!$F$2:$F$16) -> 56.2
A54: Digital payments adoption % | B54: =COUNT(Tableau_DigitalReadiness!$G$2:$G$16) -> 15 | C54: =AVERAGE(Tableau_DigitalReadiness!$G$2:$G$16) -> 48.286667 | D54: =STDEV(Tableau_DigitalReadiness!$G$2:$G$16) -> 10.306785 | E54: =MIN(Tableau_DigitalReadiness!$G$2:$G$16) -> 30.8 | F54: =MEDIAN(Tableau_DigitalReadiness!$G$2:$G$16) -> 48.5 | G54: =MAX(Tableau_DigitalReadiness!$G$2:$G$16) -> 72.1
A55: AI/analytics maturity (1–5) | B55: =COUNT(Tableau_DigitalReadiness!$H$2:$H$16) -> 15 | C55: =AVERAGE(Tableau_DigitalReadiness!$H$2:$H$16) -> 2.3686667 | D55: =STDEV(Tableau_DigitalReadiness!$H$2:$H$16) -> 0.74769041 | E55: =MIN(Tableau_DigitalReadiness!$H$2:$H$16) -> 1.01 | F55: =MEDIAN(Tableau_DigitalReadiness!$H$2:$H$16) -> 2.67 | G55: =MAX(Tableau_DigitalReadiness!$H$2:$H$16) -> 3.58
A56: Tourism-tech startups | B56: =COUNT(Tableau_DigitalReadiness!$I$2:$I$16) -> 15 | C56: =AVERAGE(Tableau_DigitalReadiness!$I$2:$I$16) -> 16.733333 | D56: =STDEV(Tableau_DigitalReadiness!$I$2:$I$16) -> 6.1233355 | E56: =MIN(Tableau_DigitalReadiness!$I$2:$I$16) -> 9 | F56: =MEDIAN(Tableau_DigitalReadiness!$I$2:$I$16) -> 16 | G56: =MAX(Tableau_DigitalReadiness!$I$2:$I$16) -> 30
A57: R&D investment (USD M) | B57: =COUNT(Tableau_DigitalReadiness!$J$2:$J$16) -> 15 | C57: =AVERAGE(Tableau_DigitalReadiness!$J$2:$J$16) -> 3.3466667 | D57: =STDEV(Tableau_DigitalReadiness!$J$2:$J$16) -> 1.537515 | E57: =MIN(Tableau_DigitalReadiness!$J$2:$J$16) -> 0.67 | F57: =MEDIAN(Tableau_DigitalReadiness!$J$2:$J$16) -> 3.11 | G57: =MAX(Tableau_DigitalReadiness!$J$2:$J$16) -> 6.74
A58: Digital tourism platforms listed | B58: =COUNT(Tableau_DigitalReadiness!$K$2:$K$16) -> 15 | C58: =AVERAGE(Tableau_DigitalReadiness!$K$2:$K$16) -> 12.066667 | D58: =STDEV(Tableau_DigitalReadiness!$K$2:$K$16) -> 4.317186 | E58: =MIN(Tableau_DigitalReadiness!$K$2:$K$16) -> 6 | F58: =MEDIAN(Tableau_DigitalReadiness!$K$2:$K$16) -> 12 | G58: =MAX(Tableau_DigitalReadiness!$K$2:$K$16) -> 20
A59: AI workforce % of tourism workforce | B59: =COUNT(Tableau_DigitalReadiness!$L$2:$L$16) -> 15 | C59: =AVERAGE(Tableau_DigitalReadiness!$L$2:$L$16) -> 5.1133333 | D59: =STDEV(Tableau_DigitalReadiness!$L$2:$L$16) -> 1.3752229 | E59: =MIN(Tableau_DigitalReadiness!$L$2:$L$16) -> 3.4 | F59: =MEDIAN(Tableau_DigitalReadiness!$L$2:$L$16) -> 4.8 | G59: =MAX(Tableau_DigitalReadiness!$L$2:$L$16) -> 7.7

Sheet Correlation_Regression
A1: Cross-Regional Correlation and Regression Diagnostics
A3: Metric | B3: Historical Composite | C3: Asset Score | D3: Enabler Score | E3: Recent Demand Score | F3: Digital Readiness Score | G3: Priority Score | H3: Latest Occupancy % | I3: Intl Recovery %
A4: Historical Composite | B4: 1 | C4: 0.66124375 | D4: 0.9867954 | E4: 0.62858212 | F4: 0.65302381 | G4: 0.80551126 | H4: 0.17050919 | I4: 0.38495757
A5: Asset Score | B5: 0.66124375 | C5: 1 | D5: 0.53100579 | E5: 0.32260857 | F5: 0.22665302 | G5: 0.41417161 | H5: 0.043525976 | I5: -0.04845234
A6: Enabler Score | B6: 0.9867954 | C6: 0.53100579 | D6: 1 | E6: 0.64036994 | F6: 0.68869651 | G6: 0.82045352 | H6: 0.18320365 | I6: 0.44529668
A7: Recent Demand Score | B7: 0.62858212 | C7: 0.32260857 | D7: 0.64036994 | E7: 1 | F7: 0.84610025 | G7: 0.94306833 | H7: 0.67225375 | I7: 0.75039765
A8: Digital Readiness Score | B8: 0.65302381 | C8: 0.22665302 | D8: 0.68869651 | E8: 0.84610025 | F8: 1 | G8: 0.93701709 | H8: 0.69675434 | I8: 0.63003795
A9: Priority Score | B9: 0.80551126 | C9: 0.41417161 | D9: 0.82045352 | E9: 0.94306833 | F9: 0.93701709 | G9: 1 | H9: 0.61159909 | I9: 0.68181836
A10: Latest Occupancy % | B10: 0.17050919 | C10: 0.043525976 | D10: 0.18320365 | E10: 0.67225375 | F10: 0.69675434 | G10: 0.61159909 | H10: 1 | I10: 0.30980426
A11: Intl Recovery % | B11: 0.38495757 | C11: -0.04845234 | D11: 0.44529668 | E11: 0.75039765 | F11: 0.63003795 | G11: 0.68181836 | H11: 0.30980426 | I11: 1
A14: Regression | B14: Coefficient | C14: Interpretation | D14: Caution
A15: Intercept | B15: 3.0229749 | C15: Baseline term | D15: n=15; descriptive association only
A16: Asset Score | B16: 0.37653134 | C16: Marginal association with Recent Demand Score | D16: Not causal
A17: Enabler Score | B17: 0.038951287 | C17: Marginal association with Recent Demand Score | D17: Not causal
A18: Digital Readiness | B18: 0.65747206 | C18: Marginal association with Recent Demand Score | D18: Not causal
A19: R-squared | B19: 0.73402501 | C19: Share of cross-sectional variation explained in-sample | D19: High overfit risk with small sample
A21: OLS inference (Recent Demand ~ Asset + Enabler + Digital) | B21: Coefficient | C21: Std. error | D21: t | E21: p-value | F21: Reading
A22: const | B22: 3.0229749 | C22: 16.326316 | D22: 0.18515964 | E22: 0.85647366 | F22: Intercept
A23: Asset Score | B23: 0.37653134 | C23: 0.53866896 | D23: 0.69900322 | E23: 0.49906326 | F23: Not significant (p ≈ 0.50): endowment alone does not predict current demand
A24: Enabler Score | B24: 0.038951287 | C24: 0.62494391 | D24: 0.062327653 | E24: 0.95142002 | F24: Not significant when digital readiness is included (p ≈ 0.95)
A25: Digital Readiness | B25: 0.65747206 | C25: 0.17974024 | D25: 3.6579014 | E25: 0.0037683726 | F25: Only significant predictor (p ≈ 0.004); +0.66 demand points per readiness point
A26: Model fit | B26: R² = 0.734 | C26: Adj. R² = 0.661 | D26: n = 15 | E26: F-test p = 0.0017 | F26: Cross-sectional association only; n = 15 gives 11 residual degrees of freedom, treat as directional, not causal.
A27: Bivariate check: Latest Occupancy % ~ Digital Readiness | B27: 0.114 | E27: 0.004 | F27: R² = 0.485: each readiness point associates with +0.11 occupancy points.
A28: Correlation and inference computed in Python (numpy/scipy OLS, classical standard errors) from the values in Executive_Summary; Priority Score is a weighted combination of three inputs, so its correlations are mechanical and not evidence.

Sheet Weight_Sensitivity
A1: Priority-Score Weighting Sensitivity Check
A2: Base case (used throughout RfP 1/2): Priority = 0.50 x Historical Composite + 0.30 x Recent Demand + 0.20 x Digital Readiness. This sheet re-ranks all 15 regions under three alternative weight schemes to test how much the specific 50/30/20 choice drives the tier calls. All priority and rank columns are live formulas on Executive_Summary; nothing here is hand-typed.
A4: Code | B4: Region | C4: Current Tier | D4: Historical | E4: Demand | F4: Digital | G4: Priority 50/30/20 (base) | H4: Rank (base) | I4: Priority 40/40/20 | J4: Rank (40/40/20) | K4: Priority 33/33/34 (equal) | L4: Rank (equal) | M4: Priority 60/20/20 (history-heavy) | N4: Rank (history-heavy) | O4: Rank range (max-min) | P4: Boundary-sensitive?
A5: =Executive_Summary!A5 -> XV | B5: =Executive_Summary!B5 -> Arica y Parinacota | C5: =Executive_Summary!C5 -> Wait | D5: =Executive_Summary!G5 -> 29.215553 | E5: =Executive_Summary!J5 -> 36.264197 | F5: =Executive_Summary!K5 -> 28.834379 | G5: =0.5*D5+0.3*E5+0.2*F5 -> 31.253912 | H5: =RANK(G5,$G$5:$G$19,0) -> 11 | I5: =0.4*D5+0.4*E5+0.2*F5 -> 31.958776 | J5: =RANK(I5,$I$5:$I$19,0) -> 11 | K5: =0.33*D5+0.33*E5+0.34*F5 -> 31.412007 | L5: =RANK(K5,$K$5:$K$19,0) -> 11 | M5: =0.6*D5+0.2*E5+0.2*F5 -> 30.549047 | N5: =RANK(M5,$M$5:$M$19,0) -> 10 | O5: =MAX(H5,J5,L5,N5)-MIN(H5,J5,L5,N5) -> 1 | P5: =IF(OR(AND(H5<=5,MAX(H5,J5,L5,N5)>5),AND(H5>5,MIN(H5,J5,L5,N5)<=5),AND(H5<=13,MAX(H5,J5,L5,N5)>13),AND(H5>13,MIN(H5,J5,L5,N5)<=13)),"Yes - crosses a tier cut line under an alternate weighting","No") -> No
A6: =Executive_Summary!A6 -> I | B6: =Executive_Summary!B6 -> Tarapacá | C6: =Executive_Summary!C6 -> Wait | D6: =Executive_Summary!G6 -> 26.625575 | E6: =Executive_Summary!J6 -> 39.520943 | F6: =Executive_Summary!K6 -> 34.144353 | G6: =0.5*D6+0.3*E6+0.2*F6 -> 31.997941 | H6: =RANK(G6,$G$5:$G$19,0) -> 9 | I6: =0.4*D6+0.4*E6+0.2*F6 -> 33.287478 | J6: =RANK(I6,$I$5:$I$19,0) -> 9 | K6: =0.33*D6+0.33*E6+0.34*F6 -> 33.437431 | L6: =RANK(K6,$K$5:$K$19,0) -> 9 | M6: =0.6*D6+0.2*E6+0.2*F6 -> 30.708404 | N6: =RANK(M6,$M$5:$M$19,0) -> 9 | O6: =MAX(H6,J6,L6,N6)-MIN(H6,J6,L6,N6) -> 0 | P6: =IF(OR(AND(H6<=5,MAX(H6,J6,L6,N6)>5),AND(H6>5,MIN(H6,J6,L6,N6)<=5),AND(H6<=13,MAX(H6,J6,L6,N6)>13),AND(H6>13,MIN(H6,J6,L6,N6)<=13)),"Yes - crosses a tier cut line under an alternate weighting","No") -> No
A7: =Executive_Summary!A7 -> II | B7: =Executive_Summary!B7 -> Antofagasta | C7: =Executive_Summary!C7 -> Prepare First | D7: =Executive_Summary!G7 -> 36.163446 | E7: =Executive_Summary!J7 -> 35.384703 | F7: =Executive_Summary!K7 -> 50.625421 | G7: =0.5*D7+0.3*E7+0.2*F7 -> 38.822218 | H7: =RANK(G7,$G$5:$G$19,0) -> 8 | I7: =0.4*D7+0.4*E7+0.2*F7 -> 38.744344 | J7: =RANK(I7,$I$5:$I$19,0) -> 8 | K7: =0.33*D7+0.33*E7+0.34*F7 -> 40.823532 | L7: =RANK(K7,$K$5:$K$19,0) -> 8 | M7: =0.6*D7+0.2*E7+0.2*F7 -> 38.900092 | N7: =RANK(M7,$M$5:$M$19,0) -> 8 | O7: =MAX(H7,J7,L7,N7)-MIN(H7,J7,L7,N7) -> 0 | P7: =IF(OR(AND(H7<=5,MAX(H7,J7,L7,N7)>5),AND(H7>5,MIN(H7,J7,L7,N7)<=5),AND(H7<=13,MAX(H7,J7,L7,N7)>13),AND(H7>13,MIN(H7,J7,L7,N7)<=13)),"Yes - crosses a tier cut line under an alternate weighting","No") -> No
A8: =Executive_Summary!A8 -> III | B8: =Executive_Summary!B8 -> Atacama | C8: =Executive_Summary!C8 -> Prepare First | D8: =Executive_Summary!G8 -> 26.283286 | E8: =Executive_Summary!J8 -> 41.227633 | F8: =Executive_Summary!K8 -> 29.863337 | G8: =0.5*D8+0.3*E8+0.2*F8 -> 31.482601 | H8: =RANK(G8,$G$5:$G$19,0) -> 10 | I8: =0.4*D8+0.4*E8+0.2*F8 -> 32.977035 | J8: =RANK(I8,$I$5:$I$19,0) -> 10 | K8: =0.33*D8+0.33*E8+0.34*F8 -> 32.432138 | L8: =RANK(K8,$K$5:$K$19,0) -> 10 | M8: =0.6*D8+0.2*E8+0.2*F8 -> 29.988166 | N8: =RANK(M8,$M$5:$M$19,0) -> 11 | O8: =MAX(H8,J8,L8,N8)-MIN(H8,J8,L8,N8) -> 1 | P8: =IF(OR(AND(H8<=5,MAX(H8,J8,L8,N8)>5),AND(H8>5,MIN(H8,J8,L8,N8)<=5),AND(H8<=13,MAX(H8,J8,L8,N8)>13),AND(H8>13,MIN(H8,J8,L8,N8)<=13)),"Yes - crosses a tier cut line under an alternate weighting","No") -> No
A9: =Executive_Summary!A9 -> IV | B9: =Executive_Summary!B9 -> Coquimbo | C9: =Executive_Summary!C9 -> Scale Now | D9: =Executive_Summary!G9 -> 34.386152 | E9: =Executive_Summary!J9 -> 62.310224 | F9: =Executive_Summary!K9 -> 57.674328 | G9: =0.5*D9+0.3*E9+0.2*F9 -> 47.421009 | H9: =RANK(G9,$G$5:$G$19,0) -> 3 | I9: =0.4*D9+0.4*E9+0.2*F9 -> 50.213416 | J9: =RANK(I9,$I$5:$I$19,0) -> 4 | K9: =0.33*D9+0.33*E9+0.34*F9 -> 51.519075 | L9: =RANK(K9,$K$5:$K$19,0) -> 4 | M9: =0.6*D9+0.2*E9+0.2*F9 -> 44.628601 | N9: =RANK(M9,$M$5:$M$19,0) -> 4 | O9: =MAX(H9,J9,L9,N9)-MIN(H9,J9,L9,N9) -> 1 | P9: =IF(OR(AND(H9<=5,MAX(H9,J9,L9,N9)>5),AND(H9>5,MIN(H9,J9,L9,N9)<=5),AND(H9<=13,MAX(H9,J9,L9,N9)>13),AND(H9>13,MIN(H9,J9,L9,N9)<=13)),"Yes - crosses a tier cut line under an alternate weighting","No") -> No
A10: =Executive_Summary!A10 -> V | B10: =Executive_Summary!B10 -> Valparaíso | C10: =Executive_Summary!C10 -> Scale Now | D10: =Executive_Summary!G10 -> 42.497286 | E10: =Executive_Summary!J10 -> 70.904002 | F10: =Executive_Summary!K10 -> 68.955855 | G10: =0.5*D10+0.3*E10+0.2*F10 -> 56.311015 | H10: =RANK(G10,$G$5:$G$19,0) -> 2 | I10: =0.4*D10+0.4*E10+0.2*F10 -> 59.151686 | J10: =RANK(I10,$I$5:$I$19,0) -> 2 | K10: =0.33*D10+0.33*E10+0.34*F10 -> 60.867416 | L10: =RANK(K10,$K$5:$K$19,0) -> 2 | M10: =0.6*D10+0.2*E10+0.2*F10 -> 53.470343 | N10: =RANK(M10,$M$5:$M$19,0) -> 2 | O10: =MAX(H10,J10,L10,N10)-MIN(H10,J10,L10,N10) -> 0 | P10: =IF(OR(AND(H10<=5,MAX(H10,J10,L10,N10)>5),AND(H10>5,MIN(H10,J10,L10,N10)<=5),AND(H10<=13,MAX(H10,J10,L10,N10)>13),AND(H10>13,MIN(H10,J10,L10,N10)<=13)),"Yes - crosses a tier cut line under an alternate weighting","No") -> No
A11: =Executive_Summary!A11 -> RM | B11: =Executive_Summary!B11 -> Metropolitana | C11: =Executive_Summary!C11 -> Scale Now | D11: =Executive_Summary!G11 -> 51.027407 | E11: =Executive_Summary!J11 -> 95.230769 | F11: =Executive_Summary!K11 -> 97.883598 | G11: =0.5*D11+0.3*E11+0.2*F11 -> 73.659654 | H11: =RANK(G11,$G$5:$G$19,0) -> 1 | I11: =0.4*D11+0.4*E11+0.2*F11 -> 78.07999 | J11: =RANK(I11,$I$5:$I$19,0) -> 1 | K11: =0.33*D11+0.33*E11+0.34*F11 -> 81.545621 | L11: =RANK(K11,$K$5:$K$19,0) -> 1 | M11: =0.6*D11+0.2*E11+0.2*F11 -> 69.239317 | N11: =RANK(M11,$M$5:$M$19,0) -> 1 | O11: =MAX(H11,J11,L11,N11)-MIN(H11,J11,L11,N11) -> 0 | P11: =IF(OR(AND(H11<=5,MAX(H11,J11,L11,N11)>5),AND(H11>5,MIN(H11,J11,L11,N11)<=5),AND(H11<=13,MAX(H11,J11,L11,N11)>13),AND(H11>13,MIN(H11,J11,L11,N11)<=13)),"Yes - crosses a tier cut line under an alternate weighting","No") -> No
A12: =Executive_Summary!A12 -> VI | B12: =Executive_Summary!B12 -> O'Higgins | C12: =Executive_Summary!C12 -> Prepare First | D12: =Executive_Summary!G12 -> 27.690385 | E12: =Executive_Summary!J12 -> 30.399641 | F12: =Executive_Summary!K12 -> 18.715728 | G12: =0.5*D12+0.3*E12+0.2*F12 -> 26.70823 | H12: =RANK(G12,$G$5:$G$19,0) -> 13 | I12: =0.4*D12+0.4*E12+0.2*F12 -> 26.979156 | J12: =RANK(I12,$I$5:$I$19,0) -> 13 | K12: =0.33*D12+0.33*E12+0.34*F12 -> 25.533056 | L12: =RANK(K12,$K$5:$K$19,0) -> 13 | M12: =0.6*D12+0.2*E12+0.2*F12 -> 26.437305 | N12: =RANK(M12,$M$5:$M$19,0) -> 14 | O12: =MAX(H12,J12,L12,N12)-MIN(H12,J12,L12,N12) -> 1 | P12: =IF(OR(AND(H12<=5,MAX(H12,J12,L12,N12)>5),AND(H12>5,MIN(H12,J12,L12,N12)<=5),AND(H12<=13,MAX(H12,J12,L12,N12)>13),AND(H12>13,MIN(H12,J12,L12,N12)<=13)),"Yes - crosses a tier cut line under an alternate weighting","No") -> Yes - crosses a tier cut line under an alternate weighting
A13: =Executive_Summary!A13 -> VII | B13: =Executive_Summary!B13 -> Maule | C13: =Executive_Summary!C13 -> Prepare First | D13: =Executive_Summary!G13 -> 28.117204 | E13: =Executive_Summary!J13 -> 59.352236 | F13: =Executive_Summary!K13 -> 77.15703 | G13: =0.5*D13+0.3*E13+0.2*F13 -> 47.295679 | H13: =RANK(G13,$G$5:$G$19,0) -> 4 | I13: =0.4*D13+0.4*E13+0.2*F13 -> 50.419182 | J13: =RANK(I13,$I$5:$I$19,0) -> 3 | K13: =0.33*D13+0.33*E13+0.34*F13 -> 55.098305 | L13: =RANK(K13,$K$5:$K$19,0) -> 3 | M13: =0.6*D13+0.2*E13+0.2*F13 -> 44.172176 | N13: =RANK(M13,$M$5:$M$19,0) -> 5 | O13: =MAX(H13,J13,L13,N13)-MIN(H13,J13,L13,N13) -> 2 | P13: =IF(OR(AND(H13<=5,MAX(H13,J13,L13,N13)>5),AND(H13>5,MIN(H13,J13,L13,N13)<=5),AND(H13<=13,MAX(H13,J13,L13,N13)>13),AND(H13>13,MIN(H13,J13,L13,N13)<=13)),"Yes - crosses a tier cut line under an alternate weighting","No") -> No
A14: =Executive_Summary!A14 -> VIII | B14: =Executive_Summary!B14 -> Biobío | C14: =Executive_Summary!C14 -> Prepare First | D14: =Executive_Summary!G14 -> 36.846173 | E14: =Executive_Summary!J14 -> 45.638541 | F14: =Executive_Summary!K14 -> 52.766353 | G14: =0.5*D14+0.3*E14+0.2*F14 -> 42.667919 | H14: =RANK(G14,$G$5:$G$19,0) -> 6 | I14: =0.4*D14+0.4*E14+0.2*F14 -> 43.547156 | J14: =RANK(I14,$I$5:$I$19,0) -> 6 | K14: =0.33*D14+0.33*E14+0.34*F14 -> 45.160516 | L14: =RANK(K14,$K$5:$K$19,0) -> 6 | M14: =0.6*D14+0.2*E14+0.2*F14 -> 41.788683 | N14: =RANK(M14,$M$5:$M$19,0) -> 7 | O14: =MAX(H14,J14,L14,N14)-MIN(H14,J14,L14,N14) -> 1 | P14: =IF(OR(AND(H14<=5,MAX(H14,J14,L14,N14)>5),AND(H14>5,MIN(H14,J14,L14,N14)<=5),AND(H14<=13,MAX(H14,J14,L14,N14)>13),AND(H14>13,MIN(H14,J14,L14,N14)<=13)),"Yes - crosses a tier cut line under an alternate weighting","No") -> No
A15: =Executive_Summary!A15 -> IX | B15: =Executive_Summary!B15 -> Araucanía | C15: =Executive_Summary!C15 -> Prepare First | D15: =Executive_Summary!G15 -> 33.592731 | E15: =Executive_Summary!J15 -> 35.709395 | F15: =Executive_Summary!K15 -> 10.423953 | G15: =0.5*D15+0.3*E15+0.2*F15 -> 29.593975 | H15: =RANK(G15,$G$5:$G$19,0) -> 12 | I15: =0.4*D15+0.4*E15+0.2*F15 -> 29.805641 | J15: =RANK(I15,$I$5:$I$19,0) -> 12 | K15: =0.33*D15+0.33*E15+0.34*F15 -> 26.413846 | L15: =RANK(K15,$K$5:$K$19,0) -> 12 | M15: =0.6*D15+0.2*E15+0.2*F15 -> 29.382308 | N15: =RANK(M15,$M$5:$M$19,0) -> 12 | O15: =MAX(H15,J15,L15,N15)-MIN(H15,J15,L15,N15) -> 0 | P15: =IF(OR(AND(H15<=5,MAX(H15,J15,L15,N15)>5),AND(H15>5,MIN(H15,J15,L15,N15)<=5),AND(H15<=13,MAX(H15,J15,L15,N15)>13),AND(H15>13,MIN(H15,J15,L15,N15)<=13)),"Yes - crosses a tier cut line under an alternate weighting","No") -> No
A16: =Executive_Summary!A16 -> XIV | B16: =Executive_Summary!B16 -> Los Ríos | C16: =Executive_Summary!C16 -> Prepare First | D16: =Executive_Summary!G16 -> 26.843005 | E16: =Executive_Summary!J16 -> 29.82618 | F16: =Executive_Summary!K16 -> 16.3681 | G16: =0.5*D16+0.3*E16+0.2*F16 -> 25.642977 | H16: =RANK(G16,$G$5:$G$19,0) -> 14 | I16: =0.4*D16+0.4*E16+0.2*F16 -> 25.941294 | J16: =RANK(I16,$I$5:$I$19,0) -> 14 | K16: =0.33*D16+0.33*E16+0.34*F16 -> 24.265985 | L16: =RANK(K16,$K$5:$K$19,0) -> 14 | M16: =0.6*D16+0.2*E16+0.2*F16 -> 25.344659 | N16: =RANK(M16,$M$5:$M$19,0) -> 15 | O16: =MAX(H16,J16,L16,N16)-MIN(H16,J16,L16,N16) -> 1 | P16: =IF(OR(AND(H16<=5,MAX(H16,J16,L16,N16)>5),AND(H16>5,MIN(H16,J16,L16,N16)<=5),AND(H16<=13,MAX(H16,J16,L16,N16)>13),AND(H16>13,MIN(H16,J16,L16,N16)<=13)),"Yes - crosses a tier cut line under an alternate weighting","No") -> No
... A19: =Executive_Summary!A19 -> XII | B19: =Executive_Summary!B19 -> Magallanes y Antártica | C19: =Executive_Summary!C19 -> Scale Now | D19: =Executive_Summary!G19 -> 39.490988 | E19: =Executive_Summary!J19 -> 35.089993 | F19: =Executive_Summary!K19 -> 57.032018 | G19: =0.5*D19+0.3*E19+0.2*F19 -> 41.678896 | H19: =RANK(G19,$G$5:$G$19,0) -> 7 | I19: =0.4*D19+0.4*E19+0.2*F19 -> 41.238796 | J19: =RANK(I19,$I$5:$I$19,0) -> 7 | K19: =0.33*D19+0.33*E19+0.34*F19 -> 44.00261 | L19: =RANK(K19,$K$5:$K$19,0) -> 7 | M19: =0.6*D19+0.2*E19+0.2*F19 -> 42.118995 | N19: =RANK(M19,$M$5:$M$19,0) -> 6 | O19: =MAX(H19,J19,L19,N19)-MIN(H19,J19,L19,N19) -> 1 | P19: =IF(OR(AND(H19<=5,MAX(H19,J19,L19,N19)>5),AND(H19>5,MIN(H19,J19,L19,N19)<=5),AND(H19<=13,MAX(H19,J19,L19,N19)>13),AND(H19>13,MIN(H19,J19,L19,N19)<=13)),"Yes - crosses a tier cut line under an alternate weighting","No") -> No
A21: Reading the check
A22: - Base weights (50/30/20) are chosen because the historical composite is the only source covering all 131 structural indicators, while Recent Demand and Digital Readiness are single-year signals that can move sharply on short-run noise; 50% keeps structure dominant without ignoring current conditions.
A23: - Result: rank order is materially stable in the middle of the distribution and at the very top and bottom, but three regions sit close enough to a tier cut line to be weight-sensitive - flagged 'Yes' below.
A24: - This does not change the recommended tiers; it tells the Ministry which calls are robust (act with confidence) and which are closer judgment calls worth a second look before locking budget (see flagged rows).

Sheet Forecast_Evaluation
A1: Out-of-Sample Forecast Evaluation (4-quarter holdout)
A3: Code | B3: Region | C3: Metric | D3: Period | E3: Actual | F3: Seasonal Regression | G3: Seasonal Naive | H3: Squared Error Model | I3: Squared Error Baseline | J3: Model Wins?
A4: IV | B4: Coquimbo | C4: international_arrivals | D4: 2024-Q4 | E4: 12639 | F4: 12614.098 | G4: 10140 | H4: =(F4-E4)^2 -> 620.1335 | I4: =(G4-E4)^2 -> 6245001 | J4: =IF(H4<I4,"Yes","No") -> Yes
A5: IV | B5: Coquimbo | C5: international_arrivals | D5: 2025-Q1 | E5: 16060 | F5: 16777.011 | G5: 13653 | H5: =(F5-E5)^2 -> 514104.24 | I5: =(G5-E5)^2 -> 5793649 | J5: =IF(H5<I5,"Yes","No") -> Yes
A6: IV | B6: Coquimbo | C6: international_arrivals | D6: 2025-Q2 | E6: 11184 | F6: 11309.006 | G6: 8328 | H6: =(F6-E6)^2 -> 15626.377 | I6: =(G6-E6)^2 -> 8156736 | J6: =IF(H6<I6,"Yes","No") -> Yes
A7: IV | B7: Coquimbo | C7: international_arrivals | D7: 2025-Q3 | E7: 6981 | F7: 9903.8523 | G7: 7437 | H7: =(F7-E7)^2 -> 8543065.4 | I7: =(G7-E7)^2 -> 207936 | J7: =IF(H7<I7,"Yes","No") -> No
A8: V | B8: Valparaíso | C8: occupancy_rate_pct | D8: 2024-Q4 | E8: 62.8 | F8: 62.246154 | G8: 57.7 | H8: =(F8-E8)^2 -> 0.30674556 | I8: =(G8-E8)^2 -> 26.01 | J8: =IF(H8<I8,"Yes","No") -> Yes
A9: V | B9: Valparaíso | C9: occupancy_rate_pct | D9: 2025-Q1 | E9: 86.2 | F9: 65.228205 | G9: 59.5 | H9: =(F9-E9)^2 -> 439.81618 | I9: =(G9-E9)^2 -> 712.89 | J9: =IF(H9<I9,"Yes","No") -> Yes
A10: V | B10: Valparaíso | C10: occupancy_rate_pct | D10: 2025-Q2 | E10: 56.7 | F10: 60.794872 | G10: 59.7 | H10: =(F10-E10)^2 -> 16.767975 | I10: =(G10-E10)^2 -> 9 | J10: =IF(H10<I10,"Yes","No") -> No
A11: V | B11: Valparaíso | C11: occupancy_rate_pct | D11: 2025-Q3 | E11: 51.6 | F11: 55.394872 | G11: 48.5 | H11: =(F11-E11)^2 -> 14.401052 | I11: =(G11-E11)^2 -> 9.61 | J11: =IF(H11<I11,"Yes","No") -> No
A14: Code | B14: Region | C14: Metric | D14: Model RMSE | E14: Baseline RMSE | F14: RMSE Reduction
A15: IV | B15: Coquimbo | C15: international_arrivals | D15: 1506.1056 | E15: 2258.5018 | F15: 0.33313953
A16: V | B16: Valparaíso | C16: occupancy_rate_pct | D16: 10.85463 | E16: 13.76145 | F16: 0.2112292
A18: Sensitivity | B18: Region | C18: Metric | D18: Model RMSE | E18: Baseline RMSE | F18: RMSE Reduction | G18: Note
A19: Excluding 2025-Q1 outlier (86.2%) | B19: Valparaíso | C19: occupancy_rate_pct | D19: =SQRT(AVERAGE(H8,H10,H11)) -> 3.239124 | E19: =SQRT(AVERAGE(I8,I10,I11)) -> 3.8565961 | F19: =1-D19/E19 -> 0.16010806 | G19: Model still beats the baseline without the outlier quarter; both errors fall to ≈3–4 points.
A20: Training window | B20: Both | C20: — | D20: 11 quarters (2022-Q1–2024-Q3) | E20: 4 holdout quarters | F20: 5 parameters | G20: Intercept + linear trend + 3 quarter dummies; arrivals modelled in logs. Residual df = 6, a deliberately simple, transparent specification.
A21: See Forecast_Generalization for the same test on all 15 regions × 3 metrics: the model beats the seasonal-naive baseline in 19 of 45 cases (5 of 15 among Scale Now regions), so it is kept as a challenger, not an automatic replacement.

Sheet Forecast_Generalization
A1: Forecast Generalisation: Seasonal-Trend Regression vs Seasonal-Naive Baseline, 45 Region × Metric Tests
A2: Same protocol for every series: train 2022-Q1–2024-Q3 (11 quarters), test 2024-Q4–2025-Q3 (4 quarters), RMSE on the holdout. Reduction = 1 − model RMSE / naive RMSE (positive = model better).
A3: Code | B3: Region | C3: Tier | D3: Metric | E3: Model RMSE | F3: Naive RMSE | G3: RMSE reduction | H3: Model wins? | I3: Train quarters | J3: Test quarters
A4: XV | B4: Arica y Parinacota | C4: Wait | D4: international_arrivals | E4: 2247.1674 | F4: 1071.5089 | G4: =1-E4/F4 -> -1.0971991 | H4: =IF(E4<F4,"Yes","No") -> No | I4: 11 | J4: 4
A5: XV | B5: Arica y Parinacota | C5: Wait | D5: occupancy_rate_pct | E5: 8.3244775 | F5: 4.8566964 | G5: =1-E5/F5 -> -0.71402057 | H5: =IF(E5<F5,"Yes","No") -> No | I5: 11 | J5: 4
A6: XV | B6: Arica y Parinacota | C6: Wait | D6: avg_daily_rate_usd | E6: 13.233806 | F6: 14.286564 | G6: =1-E6/F6 -> 0.073688636 | H6: =IF(E6<F6,"Yes","No") -> Yes | I6: 11 | J6: 4
A7: I | B7: Tarapacá | C7: Wait | D7: international_arrivals | E7: 1252.2758 | F7: 750.87432 | G7: =1-E7/F7 -> -0.66775681 | H7: =IF(E7<F7,"Yes","No") -> No | I7: 11 | J7: 4
A8: I | B8: Tarapacá | C8: Wait | D8: occupancy_rate_pct | E8: 2.5156992 | F8: 4.1994047 | G8: =1-E8/F8 -> 0.40093909 | H8: =IF(E8<F8,"Yes","No") -> Yes | I8: 11 | J8: 4
A9: I | B9: Tarapacá | C9: Wait | D9: avg_daily_rate_usd | E9: 9.4315037 | F9: 14.29096 | G9: =1-E9/F9 -> 0.34003706 | H9: =IF(E9<F9,"Yes","No") -> Yes | I9: 11 | J9: 4
A10: II | B10: Antofagasta | C10: Prepare First | D10: international_arrivals | E10: 2008.0725 | F10: 1416.7903 | G10: =1-E10/F10 -> -0.41733926 | H10: =IF(E10<F10,"Yes","No") -> No | I10: 11 | J10: 4
A11: II | B11: Antofagasta | C11: Prepare First | D11: occupancy_rate_pct | E11: 15.900162 | F11: 10.866807 | G11: =1-E11/F11 -> -0.46318612 | H11: =IF(E11<F11,"Yes","No") -> No | I11: 11 | J11: 4
A12: II | B12: Antofagasta | C12: Prepare First | D12: avg_daily_rate_usd | E12: 15.600439 | F12: 12.874646 | G12: =1-E12/F12 -> -0.21171795 | H12: =IF(E12<F12,"Yes","No") -> No | I12: 11 | J12: 4
A13: III | B13: Atacama | C13: Prepare First | D13: international_arrivals | E13: 2375.072 | F13: 970.66627 | G13: =1-E13/F13 -> -1.4468471 | H13: =IF(E13<F13,"Yes","No") -> No | I13: 11 | J13: 4
A14: III | B14: Atacama | C14: Prepare First | D14: occupancy_rate_pct | E14: 5.4626207 | F14: 2.9736341 | G14: =1-E14/F14 -> -0.83701843 | H14: =IF(E14<F14,"Yes","No") -> No | I14: 11 | J14: 4
A15: III | B15: Atacama | C15: Prepare First | D15: avg_daily_rate_usd | E15: 2.945828 | F15: 7.208306 | G15: =1-E15/F15 -> 0.59132866 | H15: =IF(E15<F15,"Yes","No") -> Yes | I15: 11 | J15: 4
... A48: XII | B48: Magallanes y Antártica | C48: Scale Now | D48: avg_daily_rate_usd | E48: 32.735859 | F48: 14.54072 | G48: =1-E48/F48 -> -1.251323 | H48: =IF(E48<F48,"Yes","No") -> No | I48: 11 | J48: 4
A50: Summary | B50: Tests | C50: Model wins | D50: Win rate | E50: Median RMSE reduction
A51: All series | B51: =COUNTA(A4:A48) -> 45 | C51: =COUNTIF(H4:H48,"Yes") -> 19 | D51: =C51/B51 -> 0.42222222 | E51: =MEDIAN(G4:G48) -> -0.41733926
A52: International arrivals | B52: =COUNTIF(D4:D48,"international_arrivals") -> 15 | C52: =COUNTIFS(D4:D48,"international_arrivals",H4:H48,"Yes") -> 2 | D52: =C52/B52 -> 0.13333333 | E52: -1.0971991
A53: Occupancy rate | B53: =COUNTIF(D4:D48,"occupancy_rate_pct") -> 15 | C53: =COUNTIFS(D4:D48,"occupancy_rate_pct",H4:H48,"Yes") -> 6 | D53: =C53/B53 -> 0.4 | E53: -0.42193717
A54: Average daily rate | B54: =COUNTIF(D4:D48,"avg_daily_rate_usd") -> 15 | C54: =COUNTIFS(D4:D48,"avg_daily_rate_usd",H4:H48,"Yes") -> 11 | D54: =C54/B54 -> 0.73333333 | E54: 0.34003706
A55: Scale Now regions only | B55: =COUNTIF(C4:C48,"Scale Now") -> 15 | C55: =COUNTIFS(C4:C48,"Scale Now",H4:H48,"Yes") -> 5 | D55: =C55/B55 -> 0.33333333 | E55: -0.67175246
A57: Headline model coefficients | B57: Series | C57: Intercept | D57: Trend per quarter | E57: Q2 effect | F57: Q3 effect | G57: Q4 effect | H57: Implied trend
A58: Holdout fit (2022-Q1–2024-Q3) | B58: Coquimbo international arrivals (log scale) | C58: 8.3655368 | D58: 0.056760338 | E58: -0.45118736 | F58: -0.64062746 | G58: -0.22844361 | H58: +5.8% per quarter
A59: Production refit (2022-Q1–2025-Q3) | B59: Coquimbo international arrivals (log scale) | C59: 8.5147219 | D59: 0.047865357 | E59: -0.43414751 | F59: -0.69934569 | G59: -0.20797028 | H59: +4.9% per quarter
A60: Holdout fit (2022-Q1–2024-Q3) | B60: Valparaíso occupancy (points) | C60: 48.84359 | D60: 0.68269231 | E60: -5.1160256 | F60: -11.198718 | G60: -2.299359 | H60: +0.68 pts per quarter
A61: Production refit (2022-Q1–2025-Q3) | B61: Valparaíso occupancy (points) | C61: 48.745588 | D61: 0.97941176 | E61: -11.679412 | F61: -17.983824 | G61: -7.6544118 | H61: +0.98 pts per quarter
A62: Reading: the model helps most for average daily rate (steady price trends) and for some occupancy series; for international arrivals it usually over-extrapolates the post-pandemic recovery slope and loses to the same-quarter-last-year rule. Coquimbo arrivals is one of only two arrivals series where it wins, the memo says so explicitly. Median values in column E are computed in Python (conditional medians).

Sheet Forecast_Data
A1: Forecast Output for Tableau
A3: Code | B3: Region | C3: Metric | D3: Period | E3: Forecast | F3: Horizon
A4: IV | B4: Coquimbo | C4: international_arrivals | D4: 2025-Q4 | E4: 14751.571 | F4: 2025-Q4 to 2027-Q3
A5: IV | B5: Coquimbo | C5: international_arrivals | D5: 2026-Q1 | E5: 19052.092 | F5: 2025-Q4 to 2027-Q3
A6: IV | B6: Coquimbo | C6: international_arrivals | D6: 2026-Q2 | E6: 12947.608 | F6: 2025-Q4 to 2027-Q3
A7: IV | B7: Coquimbo | C7: international_arrivals | D7: 2026-Q3 | E7: 10418.525 | F7: 2025-Q4 to 2027-Q3
A8: IV | B8: Coquimbo | C8: international_arrivals | D8: 2026-Q4 | E8: 17864.23 | F8: 2025-Q4 to 2027-Q3
A9: IV | B9: Coquimbo | C9: international_arrivals | D9: 2027-Q1 | E9: 23072.122 | F9: 2025-Q4 to 2027-Q3
A10: IV | B10: Coquimbo | C10: international_arrivals | D10: 2027-Q2 | E10: 15679.647 | F10: 2025-Q4 to 2027-Q3
A11: IV | B11: Coquimbo | C11: international_arrivals | D11: 2027-Q3 | E11: 12616.951 | F11: 2025-Q4 to 2027-Q3
A12: V | B12: Valparaíso | C12: occupancy_rate_pct | D12: 2025-Q4 | E12: 67.535294 | F12: 2025-Q4 to 2027-Q3
A13: V | B13: Valparaíso | C13: occupancy_rate_pct | D13: 2026-Q1 | E13: 76.169118 | F13: 2025-Q4 to 2027-Q3
A14: V | B14: Valparaíso | C14: occupancy_rate_pct | D14: 2026-Q2 | E14: 65.469118 | F14: 2025-Q4 to 2027-Q3
A15: V | B15: Valparaíso | C15: occupancy_rate_pct | D15: 2026-Q3 | E15: 60.144118 | F15: 2025-Q4 to 2027-Q3
... A19: V | B19: Valparaíso | C19: occupancy_rate_pct | D19: 2027-Q3 | E19: 64.061765 | F19: 2025-Q4 to 2027-Q3

Sheet Budget_Allocation
A1: USD 45M Regional Tourism Development Fund: Proposed Allocation
A3: Code | B3: Region | C3: Tier | D3: D1 | E3: D2 | F3: D3 | G3: D4 | H3: D5 | I3: D6 | J3: D7 | K3: D9 | L3: D10 | M3: Total USD M
A4: RM | B4: Metropolitana | C4: Scale Now | D4: 1.5 | E4: 0 | F4: 0 | G4: 1 | H4: 1 | I4: 0.5 | J4: 0.5 | K4: 1.5 | L4: 0.5 | M4: =SUM(D4:L4) -> 6.5
A5: V | B5: Valparaíso | C5: Scale Now | D5: 1 | E5: 1.5 | F5: 0 | G5: 1 | H5: 1 | I5: 0 | J5: 1 | K5: 1 | L5: 0.25 | M5: =SUM(D5:L5) -> 6.75
A6: IV | B6: Coquimbo | C6: Scale Now | D6: 0 | E6: 1 | F6: 0 | G6: 1 | H6: 1 | I6: 0.5 | J6: 0 | K6: 1.5 | L6: 0.25 | M6: =SUM(D6:L6) -> 5.25
A7: X | B7: Los Lagos | C7: Scale Now | D7: 0 | E7: 2 | F7: 1 | G7: 1 | H7: 1 | I7: 0.5 | J7: 0.5 | K7: 0 | L7: 0.25 | M7: =SUM(D7:L7) -> 6.25
A8: XII | B8: Magallanes y Antártica | C8: Scale Now | D8: 0 | E8: 2 | F8: 0.5 | G8: 1 | H8: 1 | I8: 0.5 | J8: 0.5 | K8: 0 | L8: 0 | M8: =SUM(D8:L8) -> 5.5
A9: VII | B9: Maule | C9: Prepare First | D9: 0 | E9: 0 | F9: 0.5 | G9: 0.25 | H9: 0 | I9: 0.25 | J9: 0 | K9: 0.25 | L9: 0.25 | M9: =SUM(D9:L9) -> 1.5
A10: VIII | B10: Biobío | C10: Prepare First | D10: 0 | E10: 0 | F10: 0.5 | G10: 0.5 | H10: 0.5 | I10: 0.25 | J10: 0 | K10: 0.25 | L10: 0 | M10: =SUM(D10:L10) -> 2
A11: II | B11: Antofagasta | C11: Prepare First | D11: 0 | E11: 0 | F11: 0 | G11: 0.25 | H11: 0.25 | I11: 0.25 | J11: 0.25 | K11: 0.25 | L11: 0.25 | M11: =SUM(D11:L11) -> 1.5
A12: IX | B12: Araucanía | C12: Prepare First | D12: 0 | E12: 0.5 | F12: 0.75 | G12: 0.5 | H12: 0.5 | I12: 0.25 | J12: 0 | K12: 0 | L12: 0.5 | M12: =SUM(D12:L12) -> 3
A13: III | B13: Atacama | C13: Prepare First | D13: 0 | E13: 0.25 | F13: 0.25 | G13: 0.25 | H13: 0.25 | I13: 0.25 | J13: 0 | K13: 0.25 | L13: 0 | M13: =SUM(D13:L13) -> 1.5
A14: XI | B14: Aysén | C14: Prepare First | D14: 0 | E14: 0.5 | F14: 0.25 | G14: 0.25 | H14: 0.5 | I14: 0 | J14: 0 | K14: 0 | L14: 0.25 | M14: =SUM(D14:L14) -> 1.75
A15: XIV | B15: Los Ríos | C15: Prepare First | D15: 0 | E15: 0 | F15: 0.25 | G15: 0.25 | H15: 0 | I15: 0.25 | J15: 0 | K15: 0 | L15: 0.25 | M15: =SUM(D15:L15) -> 1
A16: VI | B16: O'Higgins | C16: Prepare First | D16: 0.25 | E16: 0 | F16: 0.25 | G16: 0 | H16: 0.25 | I16: 0 | J16: 0 | K16: 0.25 | L16: 0 | M16: =SUM(D16:L16) -> 1
A17: XC | B17: Cross-cutting: national predictive-monitoring & data-governance pilot | C17: Cross-cutting | D17: 0 | E17: 0 | F17: 0 | G17: 0 | H17: 0 | I17: 0 | J17: 0 | K17: 0 | L17: 0 | M17: 1.5
A18: TOTAL | M18: =SUM(M4:M17) -> 45
A20: Subtotal by tier | B20: USD M | C20: Share of fund
A21: Scale Now | B21: =SUMIF($C$4:$C$17,"Scale Now",$M$4:$M$17) -> 30.25 | C21: =B21/$M$18 -> 0.67222222
A22: Prepare First | B22: =SUMIF($C$4:$C$17,"Prepare First",$M$4:$M$17) -> 13.25 | C22: =B22/$M$18 -> 0.29444444
A23: Cross-cutting | B23: =SUMIF($C$4:$C$17,"Cross-cutting",$M$4:$M$17) -> 1.5 | C23: =B23/$M$18 -> 0.033333333
A24: Wait | B24: 0 | C24: =B24/$M$18 -> 0
A26: Subtotal by dimension | B26: D1 | C26: D2 | D26: D3 | E26: D4 | F26: D5 | G26: D6 | H26: D7 | I26: D9 | J26: D10 | K26: Cross-cutting | L26: Check
A27: USD M | B27: =SUM(D4:D16) -> 2.75 | C27: =SUM(E4:E16) -> 7.75 | D27: =SUM(F4:F16) -> 4.25 | E27: =SUM(G4:G16) -> 7.25 | F27: =SUM(H4:H16) -> 7.25 | G27: =SUM(I4:I16) -> 3.5 | H27: =SUM(J4:J16) -> 2.75 | I27: =SUM(K4:K16) -> 5.25 | J27: =SUM(L4:L16) -> 2.75 | K27: =M17 -> 1.5 | L27: =SUM(B27:K27) -> 45
A29: Cross-cutting line: what the USD 1.5M buys | B29: USD M
A30: IoT sensor network upkeep and expansion at the 10 monitored protected areas | B30: 0.5
A31: Shared data platform, data dictionary, Tableau operations and quarterly re-estimation | B31: 0.4
A32: Privacy, aggregation-threshold and model-risk audit (including mobile-flow governance) | B32: 0.3
A33: Analytics staffing and regional data-steward training | B33: 0.3
A34: Total cross-cutting | B34: =SUM(B30:B33) -> 1.5
A35: v2 change: USD 1.5M moved from the D10 (Governmental Involvement & Efficiency) lines of Metropolitana (−0.50), Valparaíso (−0.25), Coquimbo (−0.25), Los Lagos (−0.25) and Maule (−0.25) into an explicit national predictive-monitoring and data-governance pilot, so the RfP 2 recommendation to invest in AI-enabled monitoring is funded rather than asserted. Regional totals otherwise unchanged; fund total remains USD 45.0M.

Sheet Digital_Signals_Summary
A1: DB4 Semi-Structured Signals: Decision-Relevant Findings
A2: v2: three findings added (complaint themes, sensor reliability, platform-vs-official price gap).
A3: Signal | B3: Region/Site | C3: Evidence | D3: Decision Implication | E3: Caveat
A4: Protected-area crowding | B4: Los Lagos, Parque Nacional Chiloé | C4: Trail counters avg. 749.5 visitors; max 891; 33.3% of sampled trail readings show non-open status. | D4: Scale nature tourism only with capacity management, timed entry, maintenance and dispersal. | E4: Sparse 2025 sensor readings; descriptive, not a full census.
A5: Protected-area operating pressure | B5: Valparaíso, Parque Nacional Rapa Nui | C5: Trail counters avg. 684.9; max 770; 57.1% of sampled trail readings show non-open status. | D5: Pair promotion with conservation controls and visitor-management funding. | E5: Small sample; status may reflect maintenance/weather rather than crowding alone.
A6: Positive digital sentiment | B6: Metropolitana / Magallanes | C6: 2025 weighted sentiment: +0.685 / +0.675. | D6: Supports high-intent promotion and premium experience packaging, while monitoring capacity. | E6: 2025 social feed is incomplete and synthetic.
A7: Experience friction | B7: Tarapacá / Araucanía / Maule | C7: 2025 weighted sentiment: -0.046 / -0.021 / -0.001; keywords include safety/public transport in affected regions. | D7: Fix service, mobility and trust issues before scaling paid promotion. | E7: Sentiment is noisy and platform-dependent.
A8: Interregional corridor | B8: RM → Coquimbo | C8: 2025 Q2 mobile-flow estimate: 11,675 visitors, avg stay 3.7 nights. | D8: Market Coquimbo as a Santiago-linked short-break / astro-coastal corridor. | E8: Aggregated synthetic mobile-flow estimate, not official counts.
A9: Interregional corridor | B9: Maule → Los Lagos | C9: 2025 Q2 mobile-flow estimate: 11,695 visitors, avg stay 2.9 nights. | D9: Build cross-regional nature itineraries and transport bundles. | E9: Same privacy and representativeness caveats.
A10: Complaint themes | B10: All regions, 2024–2025 flagged complaints | C10: Top themes: overcrowding at peak season (11), price transparency (11), signage clarity (10), cleanliness near terminals (10). | D10: Crowding is already a top complaint — supports capacity management before further promotion; signage/cleanliness are cheap Prepare-First fixes. | E10: 34 records carry complaint tags in 2024-2025 (the window used above); 95 records carry complaint tags across the full 2019-2025 feed.
A11: Sensor reliability | B11: 10 monitored protected areas | C11: 43 of 260 readings lack battery data; 36 report battery <20%; 28 of 80 trail-counter readings are partial closure or weather closure. | D11: Any monitoring investment must fund sensor upkeep; gaps could be misread as low visitation. | E11: Battery health added to cross-cutting pilot scope.
A12: Platform vs official prices | B12: O'Higgins, Tarapacá, Maule | C12: Booking-platform ADR runs 6–9% above DB3 ADR in 2024–25 (O'Higgins +8.6%, Tarapacá +8.6%, Maule +6.4%); near zero in Metropolitana and Coquimbo. | D12: Possible informal-supply or pricing-transparency gap in Prepare First / Wait regions; verify before setting rate benchmarks. | E12: Two platforms only; averages unweighted by listing volume.

Sheet Data_Quality
A1: Data Readiness and Trust Assessment
A2: v2: issues added after checking the original files : historical vintage 2004–2012, Araucanía 2022-Q4 occupancy 104.5%, 10 scattered missing DB3 cells, Valparaíso 2025-Q1 outlier, IoT battery gaps, buoy readings at inland sites; VA/VI/VP/VPP row read as 'Tipo de variable'.
A3: Issue | B3: Source | C3: Observed Evidence | D3: Treatment | E3: Residual Risk
A4: Legacy geography | B4: DB1–DB5 | C4: All five sources use the pre-2018 15-region frame; Ñuble is absent although Chile now has 16 regions. | D4: Keep the 15-region frame so region_code joins cleanly; disclose that no stand-alone Ñuble recommendation is possible. | E4: No Ñuble recommendation; Biobío figures include Ñuble territory.
A5: Historical vintage (NEW) | B5: DB1–DB2 | C5: DB2's own metadata rows date its 50 indicators to 2004–2012 (37 of 45 dated values are 2010–2011) and name the sources (INE, SERNATUR, DIPRES, Carabineros, SBIF, SUBDERE); DB1 carries no year or source rows. | D5: Treated the ten-dimension composite as a structural baseline from roughly a decade before DB3–DB5, weighted it at 50% and read it alongside 2019–2025 demand and 2025 digital readiness; recommend a refresh of DB1–DB2. | E5: Enabler scores that change quickly (telecoms, roads, workforce) may be stale; DB1 vintage is undocumented.
A6: Missing / dash values | B6: DB1 | C6: 10 numeric cells missing after cleaning: 9 literal dashes plus 1 blank (wildfire land 4, forest share 3, preserved sites 2, outbound travellers 1 for O'Higgins). | D6: Treat as missing; median-impute only inside composite scoring; retain a missingness flag. | E6: Dimension ranks slightly less certain where imputation occurs (D2, D5).
A7: Currency-formatted cells | B7: DB1–DB2 | C7: Income, investment and budget fields carry accounting/currency number formats (e.g., ' $ 293,648 '); values are numeric in the source files but export as text in CSV. | D7: Cast to numeric after stripping symbols and separators; verified against the originals cell by cell (0 mismatches across 131 indicators). | E7: None after conversion.
A8: Missing value | B8: DB2 | C8: 1 missing Crime Index value (Aysén, dash). | D8: Median-impute only for composite scoring. | E8: Negligible.
A9: VA/VI/VP/VPP codes | B9: DB2 header row | C9: Row is labelled 'Tipo de variable' (variable type). Within every dimension the codes run VA → VI → VP → VPP in column order and all five D10 public-policy variables are VPP, which suggests a relevance or policy grading rather than a measurement scale. | D9: Not used analytically (no weights); flagged for the Ministry to document. | E9: Possible loss of an intended weighting scheme.
A10: Trailing TOTAL row; metadata rows | B10: DB1–DB2 | C10: DB1 ends with a TOTAL row; DB2 ends with AÑO / FUENTE / LINK / file-location rows below the 15 regions. | D10: Dropped before scoring; DB2 metadata retained as a sourcing table (DB2_Indicator_Metadata). | E10: None.
A11: Duplicate record | B11: DB3 | C11: Antofagasta 2022-Q4 appears twice with identical values (406 rows in source, 405 after de-duplication). | D11: One exact duplicate dropped before modelling. | E11: None.
A12: Impossible negative value | B12: DB3 | C12: Aysén 2020-Q1 international arrivals = −3,148. | D12: Set to missing; excluded from level and model calculations. | E12: Aysén recovery ratio less reliable.
A13: Impossible value >100% (NEW) | B13: DB3 | C13: Araucanía 2022-Q4 occupancy recorded as 104.5%. | D13: Set to missing; occupancy averages for Araucanía exclude the cell. | E13: Araucanía 2022 occupancy history less reliable.
A14: Scattered missing cells (NEW) | B14: DB3 | C14: 5 missing average-daily-rate and 5 missing occupancy cells in the source (e.g., Metropolitana 2023-Q1 ADR; Araucanía 2025-Q1 occupancy; Aysén 2025-Q2 occupancy). | D14: Left missing; averages use available quarters; forecast series selected have complete holdout windows. | E14: Latest-occupancy figures for Araucanía and Aysén rest on three quarters, not four.
... A21: Region-name label inconsistency (NEW) | B21: DB3 | C21: region_name carries two spellings for the same region_code: ‘Araucanía’ and ‘Araucania’ (IX), and ‘Metropolitana’ and ‘Región Metropolitana (RM)’ (RM). | D21: All joins and scoring use region_code, never the free-text region_name column, so the label variants never entered any calculation. | E21: None for this analysis; flagged so a future refresh normalizes region_name before it is used directly.

Sheet Methodology
A1: Analytical Methodology
A3: Step | B3: Method | C3: Specification | D3: Why
A4: 1. Clean | B4: Preserve source structure; convert numeric/currency; map dash to missing; drop TOTAL/AVG; dedupe DB3. | C4: Legacy 15-region frame maintained to keep region_code joins consistent. | D4: Assignment explicitly requires transparent handling of imperfect data.
A5: 2. Normalize | B5: Each DB1–DB2 indicator min-max normalized to 0–100 across 15 regions; clearly adverse indicators reversed. | C5: Missing values median-imputed only for scoring. Variables equally weighted within each of 10 dimensions. | D5: Prevents unit scale from dominating; mirrors the spirit of WEF unweighted indicator aggregation without claiming an official TTDI score.
A6: 3. Regional scores | B6: Overall = mean(D1…D10); Asset = mean(D1,D2); Enabler = mean(D3…D10). | C6: Recent Demand = 50% log latest 4Q arrivals + 30% occupancy + 20% international-arrival recovery. Digital = mean normalized DB5 metrics. | D6: Separates tourism endowment, execution capacity, current demand and digital readiness.
A7: 4. Priority score | B7: 0.50 Historical Composite + 0.30 Recent Demand + 0.20 Digital Readiness. | C7: Decision-support ranking; final tiers also apply professional judgment on niche value and bottlenecks. | D7: Avoids treating a single composite as an automatic investment rule.
A8: 5. Forecast validation | B8: Seasonal trend regression: intercept + linear time trend + quarter dummies; arrivals estimated in log scale. | C8: Train 2022-Q1–2024-Q3; hold out 2024-Q4–2025-Q3; compare RMSE with seasonal-naive same-quarter-last-year baseline. | D8: Directly meets RfP requirement to test out-of-sample against a simple baseline.
A9: 6. Budget | B9: USD 45M distributed only to Scale Now and Prepare First regions. | C9: Scale Now receives growth/capacity funding; Prepare First receives foundational funding; Wait receives no near-term allocation. | D9: Aligns capital with readiness and makes opportunity cost explicit.
A10: 2b. Identity scoring | B10: Eight identity scores per region = mean of min–max-normalised DB1/DB2 indicators mapped to each identity (see Identity_Scoring). | C10: Final primary/secondary identity = data rank, overridden only with a written rationale (three overrides in v2: Metropolitana, Aysén, Magallanes). | D10: Makes the 'what should each region be known for' call auditable instead of intuitive.
A11: 5b. Forecast governance | B11: Same holdout protocol run on all 45 region × metric series; model kept as challenger where it loses to the seasonal-naive rule. | C11: Coquimbo arrivals and Valparaíso occupancy reported with sensitivity (outlier excluded) and a seasonal-naive planning floor for the 8-quarter outlook. | D11: Prevents cherry-picking the two series where the model happens to win.
A12: 7. Cross-cutting budget line | B12: USD 1.5M ring-fenced for predictive monitoring and data governance, funded from D10 lines of five regions. | C12: Sensor upkeep 0.5; data platform 0.4; privacy/model-risk audit 0.3; staffing/training 0.3. | D12: Aligns the RfP 2 'invest now' recommendation with the RfP 2 budget.
A13: 2c. Dimension boundaries (verified) | B13: Taken from the merged header rows of the original files: D1 24, D2 23, D3 12, D4 10, D5 12 indicators (DB1); D6 18, D7 12, D8 9, D9 6, D10 5 (DB2) = 131. | C13: Recomputing every dimension score from the original files reproduces Dimension_Scores exactly (max difference 0.000). | D13: Scores are auditable back to the Ministry files.
A14: 2d. Reversed (adverse) indicators | B14: 20 indicators scored as 100 − normalised value: D2: % land in human settlements, toxic waste, environmental complaints, environmental issues per million, land affected by wildfires; D7: crime perception, homes with a crime victim, murders, public-health complaints, Crime Index, homes reporting a crime, reported crimes, accidents, illegal commerce; D8: unemployment, poverty, IP crimes, strikes, strike length, strike cost. | C14: All other indicators treated as 'more is better', including outbound travellers (D5) and % population with primary education (D3). | D14: Makes the 'clearly adverse' rule explicit and reproducible.
A15: 1b. Source verification | B15: Cleaned values compared cell by cell with the original DB1–DB5 files: 0 mismatches across 131 × 15 DB1–DB2 cells, DB3 (after the two documented fixes), DB4 record counts by type (280/289/260/172) and DB5. | C15: DB2 metadata rows (AÑO/FUENTE/LINK) extracted to DB2_Indicator_Metadata. | D15: Demonstrates the cleaning did not alter the Ministry's numbers.

Sheet Raw_DB1_D1_D5
A1: region_code | B1: region_name | C1: CULTURAL EVENTS SCHEDULED THROUGHOUT THE YEAR | D1: NUMBER OF CULTURAL CENTERS | E1: WORLD CULTURAL HERITAGE SITES | F1: NUMBER OF ARCHEOLOGICAL SITES | G1: NATIONAL MONUMENTS | H1: MUSEUMS | I1: % OF POPULATION THAT ATTENDS MUSEUMS | J1: THEATERS | K1: NUMBER OF THEATER PLAYS PER YEAR | L1: LIBRARIES | M1: GALERIES | N1: % OF POPULATION ASSOCIATED TO AN INDIGENOUS GROUP | O1: NUMBER OF EXHIBITS | P1: ARTISTIC EVENTS (MUSIC, DANCE AND FOLKLOR, THEATRE, ETC) PER YEAR | Q1: MAJOR SPORTS EVENTS PER YEAR | R1: OBSERVATORIES, ZOOS, AQUARIUMS, BOTANICAL GARDENS | S1: ARTWORK SITES | T1: POPULAR ARCHITECTURE SITES | U1: HISTORICAL SITES | V1: LOCAL MARKETS | W1: CULTURAL SITES LEVEL III (INTERNATIONAL) | X1: CULTURA SITES LEVEL II (NATIONAL) | Y1: CULTURAL SITES LEVEL I (LOCAL) | Z1: HERITAGE ARCHITECTURAL HOUSES | AA1: % OF LAND THAT CORRESPONDS TO FORESTS | AB1: NATIONAL PROTECTED SITES (%) | AC1: % LAND THAT CORRESPONDS TO HUMAN SETTLEMENTS | AD1: TOXIC WASTE DISPOSAL (TONS/100 hab.) | AE1: NUMBER OF ENVIRONMENTAL COMPLAINTS PRESENTED | AF1: ENVIRONMENTAL ISSUES PER MILLION HABITANTS | AG1: NUMBER OF BEACHES AND BEACH RESORTS | AH1: LAND AFFECTED BY WILDFIRES | AI1: NATURAL PROTECTED SITES LEVEL III (INTERNATIONAL) | AJ1: NATURAL PROTECTED SITES LEVEL II (NATIONAL) | AK1: RIVERS, LAKES AND WATERFALLS | AL1: MOUNTAINS, VOLCANOES AND MOUNTAIN SYSTEMS | AM1: GEISERS AND THERMAL CENTERS | AN1: PIERS AND SEASHORES | AO1: GLACIERS AND WINTER VACATION LOCATIONS | AP1: VALLEYS | AQ1: DESERTS AND DUNES | AR1: ISLANDS AND PENINSULAS | AS1: PALEONTOLOGY SITES | AT1: HIKING TRAILS | AU1: PRESERVED SITES | AV1: SEASHORE PROTECTED SITES | AW1: BIOSHPERE RESERVES | AX1: % AVAILABLE WORKFORCE | AY1: % POPULATION ORIENTED TOWARDS TOURISM | AZ1: AVERAGE MONTHLY INCOME (CHILEAN PESOS) | BA1: 5 POPULATION WITH PRIMARY EDUCATION | BB1: % POPULATION WITH SECONDARY EDUCATION | BC1: AVERAGE NUMBER OF YEARS STUDYING | BD1: HIGHER EDUCATION AND TECHNICAL INSTITUTIONS | BE1: TOURISM-ORIENTED INSTITUTIONS | BF1: NUMBER OF COLLEGE STUDENTS IN TOURISM RELATED PROGRAMS | BG1: AVERAGE NUMBER OF GRADUATES IN TOURISM-RELATED PROGRAMS | BH1: DENSITY OF TOURISM GUIDES (PER 100.000 HABITANTS) | BI1: CERTIFIED WORKERS ON HIGHLY-COMPETITIVE TOURISM STANDARDS | BJ1: % OF TOURISM-RELATED ROOMS AVAILABLE THROUGHOUT THE YEAR | BK1: ROOMS PER 1000 HABITANTS | BL1: NUMBER OF BEDS AVAILABLE IN HOTELS, HOSTELS, B&B, ETC. | BM1: TOURISM-RELATED WORKFORCE (PER 10,000 EMPLOYEES) | BN1: AVERAGE % OF OCCUPANCY THROUGHOUT THE YEAR | BO1: AVERAGE NUMBER OF NIGHTS THAT TOURISTS SPEND | BP1: NUMBER OF ESTABLISHMENTS WITH A TOURIST-RELATED CERTIFICATION | BQ1: NUMBER OF CERTIFIED CONSULTANTS FOR TOURISM-RELATED CERTIFICATIONS | BR1: TOURISM-RELATED INVESTEMENTS (MILLION USD) BY CHAMBER OF COMMERCE MEMBERS | BS1: TOURISM-RELATED INFRASTRUCTURE INVESTMENT (MILLION USD/YEAR) | BT1: NATIONAL TOURISTS ARRIVALS | BU1: INTERNATIONAL TOURISTS ARRIVALS | BV1: NUMBER OF PEOPLE TRAVELING OUT OF THE COUNTRY | BW1: DENSITY OF AIRPORTS | BX1: DENSITY OF ROADS AND HIGHWAYS | BY1: % OF ROADS THAT ARE HIGHWAYS (FOUR LINES) | BZ1: NUMBER OF VEHICLES | CA1: VISITORS TO PROTECTED SITES | CB1: NUMBER OF CRUISES THAT ARRIVE PER YEAR | CC1: TOURIST'S ARRIVALS THROUGH BORDER LINES | CD1: SECONDARY ROADS (KMS) | CE1: NUMBER OF INTERNATIONAL BORDER GATES
A2: XV | B2: Arica y Parinacota | C2: 31 | D2: 2 | E2: 0 | F2: 30 | G2: 28 | H2: 4 | I2: 22.1 | J2: 2 | K2: 105 | L2: 12 | M2: 2 | N2: 25.4 | O2: 1 | P2: 0 | Q2: 0 | R2: 0 | S2: 4 | T2: 32 | U2: 4 | V2: 3 | W2: 9 | X2: 32 | Y2: 7 | Z2: 59 | AB2: 21.9 | AC2: 0.45800208 | AD2: 58.001835 | AE2: 1 | AF2: 0 | AG2: 5 | AI2: 13 | AJ2: 13 | AK2: 4 | AL2: 6 | AM2: 6 | AN2: 2 | AO2: 0 | AP2: 8 | AQ2: 2 | AR2: 0 | AS2: 0 | AT2: 2 | AV2: 0 | AW2: 1 | AX2: 42.556098 | AY2: 0.8769062 | AZ2: 293648.08 | BA2: 94.1 | BB2: 83.8 | BC2: 11.13802 | BD2: 52.730379 | BE2: 2 | BF2: 193 | BG2: 11 | BH2: 20.037544 | BI2: 356 | BJ2: 23.693333 | BK2: 18.740377 | BL2: 6544 | BM2: 33.009217 | BN2: 37 | BO2: 2.3 | BP2: 5 | BQ2: 3 | BR2: 0 | BS2: 0 | BT2: 97454 | BU2: 34186 | BV2: 1151575 | BW2: 5.2730379 | BX2: 2.1292527 | BY2: 17.35 | BZ2: 45248 | CA2: 15045 | CB2: 13 | CC2: 167211 | CD2: 4.67 | CE2: 3
A3: I | B3: Tarapacá | C3: 0 | D3: 5 | E3: 1 | F3: 13 | G3: 73 | H3: 5 | I3: 20.8 | J3: 2 | K3: 178 | L3: 12 | M3: 1 | N3: 12.6 | O3: 1 | P3: 0 | Q3: 0 | R3: 0 | S3: 0 | T3: 34 | U3: 10 | V3: 1 | W3: 6 | X3: 34 | Y3: 12 | Z3: 0 | AA3: 0.17288009 | AB3: 9.1 | AC3: 0.027991623 | AD3: 76.025528 | AE3: 1 | AF3: 0 | AG3: 16 | AI3: 2 | AJ3: 6 | AK3: 1 | AL3: 1 | AM3: 7 | AN3: 5 | AO3: 0 | AP3: 5 | AQ3: 6 | AR3: 4 | AS3: 2 | AT3: 3 | AU3: 5 | AV3: 0 | AW3: 0 | AX3: 68.563325 | AY3: 1.4542791 | AZ3: 381466.17 | BA3: 91.7 | BB3: 66.7 | BC3: 10.705366 | BD3: 41.849759 | BE3: 5 | BF3: 255 | BG3: 19 | BH3: 22.180372 | BI3: 380 | BJ3: 23.034783 | BK3: 22.172003 | BL3: 11108 | BM3: 41.431262 | BN3: 42.8 | BO3: 2.1 | BP3: 5 | BQ3: 10 | BR3: 0 | BS3: 11 | BT3: 235365 | BU3: 40919 | BV3: 19560 | BW3: 4.1849759 | BX3: 4.0213015 | BY3: 15.9 | BZ3: 81182 | CA3: 17161 | CB3: 0 | CC3: 434727 | CD3: 184.1 | CE3: 1
A4: II | B4: Antofagasta | C4: 1 | D4: 9 | E4: 0 | F4: 28 | G4: 81 | H4: 16 | I4: 27.4 | J4: 8 | K4: 203 | L4: 15 | M4: 2 | N4: 5.7 | O4: 2 | P4: 1 | Q4: 0 | R4: 3 | S4: 1 | T4: 24 | U4: 37 | V4: 0 | W4: 4 | X4: 31 | Y4: 26 | Z4: 63 | AB4: 2.8 | AC4: 0.02816418 | AD4: 39.558771 | AE4: 2 | AF4: 0 | AG4: 22 | AI4: 5 | AJ4: 28 | AK4: 8 | AL4: 13 | AM4: 3 | AN4: 14 | AO4: 1 | AP4: 6 | AQ4: 10 | AR4: 6 | AS4: 4 | AT4: 0 | AU4: 5 | AV4: 0 | AW4: 0 | AX4: 54.486398 | AY4: 1.0793872 | AZ4: 475865.94 | BA4: 91.7 | BB4: 66.7 | BC4: 10.641231 | BD4: 40.487141 | BE4: 7 | BF4: 529 | BG4: 47 | BH4: 20.446006 | BI4: 184 | BJ4: 24.550218 | BK4: 22.761871 | BL4: 19920 | BM4: 35.021377 | BN4: 44.6 | BO4: 1.8 | BP4: 2 | BQ4: 10 | BR4: 17 | BS4: 15 | BT4: 413922 | BU4: 84195 | BV4: 22898 | BW4: 2.0243571 | BX4: 3.33195 | BY4: 52.25 | BZ4: 112607 | CA4: 315888 | CB4: 0 | CC4: 115100 | CD4: 23 | CE4: 5
A5: III | B5: Atacama | C5: 8 | D5: 10 | E5: 0 | F5: 8 | G5: 35 | H5: 7 | I5: 20 | J5: 0 | K5: 144 | L5: 12 | M5: 0 | N5: 7.5 | O5: 0 | P5: 0 | Q5: 0 | R5: 0 | S5: 0 | T5: 18 | U5: 5 | V5: 0 | W5: 2 | X5: 29 | Y5: 7 | Z5: 33 | AB5: 2 | AC5: 0.018915487 | AD5: 40.763793 | AE5: 0 | AF5: 3.9318067 | AG5: 17 | AI5: 7 | AJ5: 23 | AK5: 2 | AL5: 7 | AM5: 2 | AN5: 10 | AO5: 0 | AP5: 3 | AQ5: 13 | AR5: 1 | AS5: 3 | AT5: 2 | AU5: 5 | AV5: 1 | AW5: 0 | AX5: 51.844166 | AY5: 0.9420609 | AZ5: 379971.01 | BA5: 89.1 | BB5: 73.2 | BC5: 10.326248 | BD5: 47.181681 | BE5: 1 | BF5: 108 | BG5: 16 | BH5: 18.479492 | BI5: 578 | BJ5: 19.429752 | BK5: 18.487355 | BL5: 9674 | BM5: 29.252642 | BN5: 36 | BO5: 1.9 | BP5: 1 | BQ5: 3 | BR5: 0 | BS5: 15 | BT5: 168508 | BU5: 14222 | BV5: 2416 | BW5: 0 | BX5: 3.6353485 | BY5: 24.39 | BZ5: 55812 | CA5: 24873 | CB5: 0 | CC5: 2552 | CD5: 11.33 | CE5: 2
A6: IV | B6: Coquimbo | C6: 23 | D6: 7 | E6: 0 | F6: 2 | G6: 52 | H6: 7 | I6: 18.3 | J6: 4 | K6: 80 | L6: 22 | M6: 2 | N6: 1.7 | O6: 0 | P6: 1 | Q6: 0 | R6: 7 | S6: 1 | T6: 69 | U6: 2 | V6: 1 | W6: 0 | X6: 29 | Y6: 27 | Z6: 97 | AA6: 0.77047997 | AB6: 0.4 | AC6: 0.35495191 | AD6: 25.445036 | AE6: 1 | AF6: 0 | AG6: 37 | AH6: 1.5005684 | AI6: 4 | AJ6: 16 | AK6: 7 | AL6: 0 | AM6: 1 | AN6: 21 | AO6: 0 | AP6: 18 | AQ6: 0 | AR6: 9 | AS6: 1 | AT6: 0 | AU6: 5 | AV6: 2 | AW6: 1 | AX6: 56.497804 | AY6: 0.92372474 | AZ6: 338013.99 | BA6: 92.7 | BB6: 71.2 | BC6: 9.7187602 | BD6: 43.102734 | BE6: 7 | BF6: 870 | BG6: 85 | BH6: 6.9627493 | BI6: 1074 | BJ6: 15.503289 | BK6: 15.626399 | BL6: 24346 | BM6: 12.002454 | BN6: 35.2 | BO6: 2.8 | BP6: 4 | BQ6: 9 | BR6: 383.9 | BS6: 750 | BT6: 205850 | BU6: 25803 | BV6: 2786 | BW6: 0 | BX6: 1.9123854 | BY6: 283.37 | BZ6: 116263 | CA6: 57234 | CB6: 0 | CC6: 15265 | CD6: 228.58 | CE6: 1
A7: V | B7: Valparaíso | C7: 14 | D7: 37 | E7: 2 | F7: 24 | G7: 161 | H7: 12 | I7: 25.7 | J7: 7 | K7: 322 | L7: 56 | M7: 7 | N7: 3.2 | O7: 3 | P7: 3 | Q7: 1 | R7: 4 | S7: 2 | T7: 48 | U7: 21 | V7: 4 | W7: 46 | X7: 90 | Y7: 36 | Z7: 720 | AA7: 6.4878843 | AB7: 2.7 | AC7: 2.1092909 | AD7: 38.456163 | AE7: 13 | AF7: 0 | AG7: 59 | AH7: 6.6376934 | AI7: 13 | AJ7: 71 | AK7: 3 | AL7: 0 | AM7: 3 | AN7: 14 | AO7: 3 | AP7: 22 | AQ7: 1 | AR7: 0 | AS7: 0 | AT7: 14 | AU7: 5 | AV7: 3 | AW7: 2 | AX7: 53.533753 | AY7: 0.98801703 | AZ7: 311263.79 | BA7: 92.9 | BB7: 73.5 | BC7: 10.641749 | BD7: 27.275349 | BE7: 21 | BF7: 3949 | BG7: 316 | BH7: 12.208966 | BI7: 3661 | BJ7: 17.207012 | BK7: 13.387001 | BL7: 44504 | BM7: 21.183854 | BN7: 29.7 | BO7: 2 | BP7: 14 | BQ7: 27 | BR7: 920 | BS7: 257 | BT7: 430436 | BU7: 106915 | BV7: 317309 | BW7: 0.64941306 | BX7: 0.19692354 | BY7: 280.95 | BZ7: 316618 | CA7: 146161 | CB7: 31 | CC7: 436195 | CD7: 93.86 | CE7: 1
A8: RM | B8: Metropolitana | C8: 4 | D8: 56 | E8: 0 | F8: 1 | G8: 404 | H8: 35 | I8: 22.5 | J8: 70 | K8: 6558 | L8: 127 | M8: 25 | N8: 4.1 | O8: 30 | P8: 0 | Q8: 0 | R8: 3 | S8: 2 | T8: 5 | U8: 9 | V8: 4 | W8: 4 | X8: 85 | Y8: 112 | Z8: 274 | AA8: 6.8524073 | AB8: 0.9 | AC8: 7.2465343 | AD8: 47.026844 | AE8: 16 | AF8: 0 | AG8: 0 | AH8: 0.037358066 | AI8: 3 | AJ8: 3 | AK8: 0 | AL8: 3 | AM8: 4 | AN8: 0 | AO8: 5 | AP8: 9 | AQ8: 0 | AR8: 0 | AS8: 0 | AT8: 0 | AU8: 5 | AV8: 0 | AW8: 0 | AX8: 55.901343 | AY8: 6.0600005 | AZ8: 421484.21 | BA8: 93.1 | BB8: 70.5 | BC8: 11.194223 | BD8: 18.973188 | BE8: 30 | BF8: 12881 | BG8: 1261 | BH8: 4.8340382 | BI8: 15221 | BJ8: 38.125 | BK8: 4.3275366 | BL8: 43634 | BM8: 9.3232594 | BN8: 59.8 | BO8: 2.2 | BP8: 15 | BQ8: 133 | BR8: 754.2 | BS8: 236 | BT8: 448887 | BU8: 765681 | BV8: 1091111 | BW8: 1.2810215 | BX8: 0.73063515 | BY8: 541.32 | BZ8: 1306140 | CA8: 83459 | CB8: 0 | CC8: 1147039 | CD8: 248.5 | CE8: 1
A9: VI | B9: O'Higgins | C9: 32 | D9: 13 | E9: 1 | F9: 9 | G9: 67 | H9: 6 | I9: 21.9 | J9: 13 | K9: 251 | L9: 36 | M9: 0 | N9: 1.9 | O9: 1 | P9: 7 | Q9: 2 | R9: 3 | S9: 16 | T9: 29 | U9: 3 | V9: 1 | W9: 0 | X9: 28 | Y9: 15 | Z9: 229 | AA9: 11.308537 | AB9: 2.8 | AC9: 0.92095149 | AD9: 27.151123 | AE9: 4 | AF9: 1.2810215 | AG9: 12 | AH9: 2.4746412 | AI9: 5 | AJ9: 22 | AK9: 1 | AL9: 3 | AM9: 2 | AN9: 2 | AO9: 7 | AP9: 5 | AQ9: 2 | AR9: 1 | AS9: 1 | AT9: 7 | AU9: 5 | AV9: 0 | AW9: 0 | AX9: 54.662153 | AY9: 0.62151951 | AZ9: 308068.3 | BA9: 95.5 | BB9: 65 | BC9: 9.4947191 | BD9: 23.058388 | BE9: 7 | BF9: 352 | BG9: 15 | BH9: 9.991968 | BI9: 2833 | BJ9: 17.463687 | BK9: 8.0089467 | BL9: 14526 | BM9: 6.3410566 | BN9: 15.4 | BO9: 2.2 | BP9: 2 | BQ9: 7 | BR9: 10 | BS9: 0 | BT9: 73478 | BU9: 7066 | BW9: 0 | BX9: 1.352131 | BY9: 134.5 | BZ9: 164204 | CA9: 11073 | CB9: 0 | CC9: 0 | CD9: 62.12 | CE9: 0
A10: VII | B10: Maule | C10: 29 | D10: 17 | E10: 0 | F10: 1 | G10: 54 | H10: 7 | I10: 11.1 | J10: 9 | K10: 657 | L10: 29 | M10: 1 | N10: 1.6 | O10: 1 | P10: 7 | Q10: 0 | R10: 0 | S10: 10 | T10: 27 | U10: 4 | V10: 3 | W10: 0 | X10: 37 | Y10: 28 | Z10: 19 | AA10: 12.698466 | AB10: 0.6 | AC10: 0.41169633 | AD10: 32.858164 | AE10: 5 | AF10: 0 | AG10: 18 | AH10: 0.81675425 | AI10: 0 | AJ10: 20 | AK10: 23 | AL10: 12 | AM10: 7 | AN10: 5 | AO10: 6 | AP10: 13 | AQ10: 3 | AR10: 0 | AS10: 0 | AT10: 9 | AU10: 5 | AV10: 0 | AW10: 0 | AX10: 48.163724 | AY10: 0.23850938 | AZ10: 244231.06 | BA10: 93.4 | BB10: 73.1 | BC10: 9.0458133 | BD10: 24.226487 | BE10: 4 | BF10: 364 | BG10: 37 | BH10: 8.6995112 | BI10: 2898 | BJ10: 14.492147 | BK10: 6.096265 | BL10: 12278 | BM10: 8.6664751 | BN10: 28.4 | BO10: 2 | BP10: 3 | BQ10: 14 | BR10: 0 | BS10: 0 | BT10: 167293 | BU10: 8935 | BV10: 3942 | BW10: 0 | BX10: 1.4798529 | BY10: 197.65 | BZ10: 185728 | CA10: 64500 | CB10: 0 | CC10: 853 | CD10: 232.9 | CE10: 2
A11: VIII | B11: Biobío | C11: 5 | D11: 32 | E11: 0 | F11: 0 | G11: 59 | H11: 20 | I11: 18.9 | J11: 12 | K11: 488 | L11: 63 | M11: 7 | N11: 3.9 | O11: 10 | P11: 0 | Q11: 0 | R11: 0 | S11: 4 | T11: 13 | U11: 23 | V11: 2 | W11: 0 | X11: 10 | Y11: 54 | Z11: 135 | AA11: 20.733206 | AB11: 2.8 | AC11: 0.96291069 | AD11: 31.680761 | AE11: 2 | AF11: 1.0743666 | AG11: 25 | AH11: 0.72577792 | AI11: 3 | AJ11: 7 | AK11: 19 | AL11: 3 | AM11: 2 | AN11: 4 | AO11: 3 | AP11: 2 | AQ11: 0 | AR11: 1 | AS11: 8 | AT11: 0 | AU11: 5 | AV11: 0 | AW11: 0 | AX11: 48.65076 | AY11: 1.2311178 | AZ11: 290366.99 | BA11: 92.7 | BB11: 71.1 | BC11: 9.9123949 | BD11: 23.098881 | BE11: 17 | BF11: 4023 | BG11: 320 | BH11: 1.6115499 | BI11: 2334 | BJ11: 16.038462 | BK11: 4.9281195 | BL11: 20802 | BM11: 7.8858507 | BN11: 36 | BO11: 1.9 | BP11: 5 | BQ11: 12 | BR11: 25 | BS11: 9 | BT11: 393481 | BU11: 31409 | BV11: 1546 | BW11: 0 | BX11: 1.0206859 | BY11: 400.89 | BZ11: 312085 | CA11: 49841 | CB11: 0 | CC11: 828 | CD11: 642.26 | CE11: 1
A12: IX | B12: Araucanía | C12: 18 | D12: 13 | E12: 0 | F12: 2 | G12: 96 | H12: 5 | I12: 13.2 | J12: 8 | K12: 179 | L12: 58 | M12: 4 | N12: 30.1 | O12: 0 | P12: 5 | Q12: 3 | R12: 0 | S12: 13 | T12: 16 | U12: 6 | V12: 10 | W12: 0 | X12: 12 | Y12: 31 | Z12: 20 | AA12: 29.436065 | AB12: 9.6 | AC12: 0.43052731 | AD12: 36.785178 | AE12: 6 | AF12: 0 | AG12: 25 | AH12: 0.15781708 | AI12: 22 | AJ12: 79 | AK12: 51 | AL12: 10 | AM12: 17 | AN12: 3 | AO12: 7 | AP12: 10 | AQ12: 0 | AR12: 1 | AS12: 3 | AT12: 23 | AU12: 5 | AV12: 0 | AW12: 1 | AX12: 52.281718 | AY12: 2.3036173 | AZ12: 251080.78 | BA12: 94.5 | BB12: 72 | BC12: 9.1468115 | BD12: 28.750999 | BE12: 8 | BF12: 709 | BG12: 67 | BH12: 9.0853157 | BI12: 709 | BJ12: 11.208333 | BK12: 9.899544 | BL12: 26140 | BM12: 16.089059 | BN12: 37.4 | BO12: 2.5 | BP12: 15 | BQ12: 7 | BR12: 24 | BS12: 25 | BT12: 200377 | BU12: 38524 | BV12: 130713 | BW12: 0 | BX12: 1.6152196 | BY12: 236.97 | BZ12: 124956 | CA12: 228921 | CB12: 0 | CC12: 112246 | CD12: 469.74 | CE12: 3
A13: XIV | B13: Los Ríos | C13: 3 | D13: 9 | E13: 0 | F13: 1 | G13: 33 | H13: 8 | I13: 16.2 | J13: 3 | K13: 94 | L13: 12 | M13: 2 | N13: 16.7 | O13: 2 | P13: 1 | Q13: 0 | R13: 1 | S13: 0 | T13: 10 | U13: 5 | V13: 2 | W13: 0 | X13: 10 | Y13: 19 | Z13: 55 | AA13: 46.109281 | AB13: 6.9 | AC13: 0.31222338 | AD13: 35.412014 | AE13: 0 | AF13: 0 | AG13: 10 | AH13: 0.13727845 | AI13: 2 | AJ13: 31 | AK13: 13 | AL13: 3 | AM13: 14 | AN13: 4 | AO13: 0 | AP13: 1 | AQ13: 0 | AR13: 5 | AS13: 1 | AT13: 0 | AV13: 0 | AW13: 1 | AX13: 47.217554 | AY13: 0.40726122 | AZ13: 268648.11 | BA13: 93.6 | BB13: 64.8 | BC13: 9.2606142 | BD13: 30.864544 | BE13: 4 | BF13: 444 | BG13: 58 | BH13: 8.6981897 | BI13: 868 | BJ13: 17.282051 | BK13: 18.911548 | BL13: 12846 | BM13: 11.812703 | BN13: 37.9 | BO13: 1.7 | BP13: 9 | BQ13: 1 | BR13: 54.1 | BS13: 0 | BT13: 113900 | BU13: 16070 | BV13: 11145 | BW13: 0 | BX13: 2.0185973 | BY13: 133.02 | BZ13: 51811 | CA13: 376 | CB13: 7 | CC13: 0 | CD13: 42.67 | CE13: 1
A14: X | B14: Los Lagos | C14: 1 | D14: 24 | E14: 1 | F14: 0 | G14: 64 | H14: 11 | I14: 19.8 | J14: 8 | K14: 272 | L14: 31 | M14: 1 | N14: 20.8 | O14: 2 | P14: 0 | Q14: 0 | R14: 0 | S14: 0 | T14: 38 | U14: 3 | V14: 3 | W14: 0 | X14: 57 | Y14: 30 | Z14: 94 | AA14: 56.322154 | AB14: 15.9 | AC14: 0.18116293 | AD14: 34.76677 | AE14: 1 | AF14: 0 | AG14: 18 | AH14: 0.0029314133 | AI14: 12 | AJ14: 41 | AK14: 17 | AL14: 10 | AM14: 9 | AN14: 10 | AO14: 3 | AP14: 6 | AQ14: 0 | AR14: 31 | AS14: 0 | AT14: 0 | AU14: 7 | AV14: 3 | AW14: 1 | AX14: 54.554723 | AY14: 14.971801 | AZ14: 291430.76 | BA14: 92.9 | BB14: 66.7 | BC14: 9.0612385 | BD14: 30.694576 | BE14: 10 | BF14: 856 | BG14: 72 | BH14: 20.92812 | BI14: 2672 | BJ14: 14.083607 | BK14: 23.972464 | BL14: 35548 | BM14: 23.816201 | BN14: 31.6 | BO14: 1.8 | BP14: 27 | BQ14: 13 | BR14: 54.1 | BS14: 48 | BT14: 275043 | BU14: 105048 | BV14: 259411 | BW14: 10.929917 | BX14: 1.892795 | BY14: 135.48 | BZ14: 129882 | CA14: 486725 | CB14: 28 | CC14: 192977 | CD14: 660.16 | CE14: 3
A15: XI | B15: Aysén | C15: 0 | D15: 4 | E15: 0 | F15: 2 | G15: 17 | H15: 0 | I15: 14.8 | J15: 0 | K15: 49 | L15: 12 | M15: 0 | N15: 21.8 | O15: 0 | P15: 0 | Q15: 0 | R15: 0 | S15: 0 | T15: 24 | U15: 2 | V15: 0 | W15: 1 | X15: 20 | Y15: 10 | Z15: 0 | AA15: 44.385074 | AB15: 39.4 | AC15: 0.020770817 | AD15: 43.886897 | AE15: 0 | AF15: 0 | AG15: 0 | AH15: 0.0055786655 | AI15: 21 | AJ15: 93 | AK15: 25 | AL15: 8 | AM15: 6 | AN15: 5 | AO15: 23 | AP15: 3 | AQ15: 0 | AR15: 8 | AS15: 3 | AT15: 6 | AU15: 6 | AV15: 0 | AW15: 2 | AX15: 61.015773 | AY15: 1.0495538 | AZ15: 418043.96 | BA15: 95.3 | BB15: 68.5 | BC15: 9.4511884 | BD15: 65.579504 | BE15: 3 | BF15: 64 | BG15: 6 | BH15: 67.765488 | BI15: 83 | BJ15: 6.8253968 | BK15: 37.598916 | BL15: 8020 | BM15: 23.062126 | BN15: 21.7 | BO15: 1.7 | BP15: 0 | BQ15: 1 | BR15: 0 | BS15: 19 | BT15: 28584 | BU15: 10763 | BV15: 90876 | BW15: 0 | BX15: 4.0886635 | BY15: 3.7 | BZ15: 19348 | CA15: 32030 | CB15: 0 | CC15: 56201 | CD15: 5.25 | CE15: 4
A16: XII | B16: Magallanes y Antártica | C16: 0 | D16: 3 | E16: 0 | F16: 2 | G16: 45 | H16: 6 | I16: 27.7 | J16: 2 | K16: 4 | L16: 14 | M16: 0 | N16: 22.7 | O16: 3 | P16: 0 | Q16: 0 | R16: 0 | S16: 2 | T16: 16 | U16: 16 | V16: 0 | W16: 2 | X16: 24 | Y16: 11 | Z16: 34 | AA16: 20.194798 | AB16: 57.3 | AC16: 0.035406576 | AD16: 40.575232 | AE16: 3 | AF16: 0 | AG16: 0 | AH16: 0.0074082531 | AI16: 19 | AJ16: 62 | AK16: 23 | AL16: 10 | AM16: 0 | AN16: 17 | AO16: 20 | AP16: 10 | AQ16: 0 | AR16: 0 | AS16: 1 | AT16: 1 | AU16: 5 | AV16: 1 | AW16: 1 | AX16: 51.871955 | AY16: 0.056243127 | AZ16: 572203.34 | BA16: 93.6 | BB16: 77.6 | BC16: 10.189078 | BD16: 59.671409 | BE16: 6 | BF16: 380 | BG16: 55 | BH16: 137.24424 | BI16: 222 | BJ16: 12.942149 | BK16: 41.531301 | BL16: 12436 | BM16: 67.7602 | BN16: 37.1 | BO16: 2 | BP16: 5 | BQ16: 3 | BR16: 0 | BS16: 12 | BT16: 84034 | BU16: 109092 | BV16: 262190 | BW16: 0.16498424 | BX16: 3.6321987 | BY16: 6.02 | BZ16: 46336 | CA16: 283629 | CB16: 18 | CC16: 388598 | CD16: 0 | CE16: 5

Sheet Raw_DB2_D6_D10
A1: region_code | B1: region_name | C1: Density of restaurants per 100,000 habitants | D1: People working at restaurants per 10,000 habitants | E1: Car rental agencies | F1: Hospital beds per 10,000 habitants | G1: Density of ATM machines per 100,000 habitants | H1: Spas | I1: Casinos per 100,000 habitants | J1: Golf courses | K1: Artwork Centers | L1: Density of tourist guides per 100,000 habitants | M1: Thermal centers | N1: Density of sports centers per 10,000 habitants | O1: Ski resorts | P1: Major shopping centers | Q1: Phone service penetration pero 1,000 habitants | R1: Density of service stations | S1: Number of certified tourism-operators | T1: Number of vineyards | U1: Percentage of crime perception | V1: Percentage of homes with at least one crime victim per year | W1: Density of murders per one million habitants | X1: Density of public health complaints per one million habitants | Y1: Crime index | Z1: Allocated budget for public safety (millions of chilean pesos) | AA1: Porcentage of homes that reported at least one crime | AB1: Number of reported crimes | AC1: Number of crimes investigated and resolved | AD1: Number of accidents (roads; air; water) | AE1: Illegal commerce | AF1: Number of police units | AG1: Unemployment rate | AH1: Poverty rate | AI1: Industrial and Intellectual property crimes | AJ1: Yearly strikes | AK1: Average length of strikes | AL1: Estimated daily cost per individual participating on a strike | AM1: Banks per one million habitants | AN1: Temporary residents | AO1: Exports (volume in million chilean pesos) | AP1: Density of tourism offices per one million habitants | AQ1: Number of tourism information offices | AR1: Average number of internet searches for main tourist attractions | AS1: Yearly budget for tourism promotion ($M) | AT1: Yearly budget for international tourism promotion ($M) | AU1: Governmental resources allocated to tourism promotion ($M) | AV1: Public infrastructure investments related to the tourism sector ($) | AW1: Entrepreneurial and Innovation funds allocated to tourism related projects ($) | AX1: Seed funds allocated to the tourism sector ($) | AY1: Governmental funds devoted to tourism development ($) | AZ1: Number of regional strategy plans for tourism development
A2: XV | B2: Arica y Parinacota | C2: 35.856658 | D2: 19.562971 | E2: 12 | F2: 21.619455 | G2: 43.766215 | H2: 0 | I2: 5.2730379 | J2: 1 | K2: 20 | L2: 20.037544 | M2: 5 | N2: 0 | O2: 0 | P2: 0 | Q2: 240.55 | R2: 17 | S2: 6 | T2: 0 | U2: 0.318 | V2: 0.26 | W2: 42.184303 | X2: 15.819114 | Y2: 0.513 | Z2: 11884613 | AA2: 0.426 | AB2: 26467 | AC2: 2387 | AD2: 981 | AE2: 319 | AF2: 265 | AG2: 7.3 | AH2: 8.2 | AI2: 84.368606 | AJ2: 1 | AK2: 11 | AL2: 253 | AM2: 94.914682 | AN2: 45560 | AO2: 137 | AP2: 5.2730379 | AQ2: 6517 | AR2: 1060490 | AS2: 193364 | AT2: 118413 | AU2: 92641 | AV2: 36370835 | AW2: 11757543 | AX2: 446922 | AY2: 24729573 | AZ2: 1
A3: I | B3: Tarapacá | C3: 25.946851 | D3: 26.616447 | E3: 2 | F3: 18.957941 | G3: 60.263653 | H3: 0 | I3: 4.1849759 | J3: 3 | K3: 9 | L3: 22.180372 | M3: 5 | N3: 40.133919 | O3: 0 | P3: 2 | Q3: 213.07 | R3: 28 | S3: 0 | T3: 0 | U3: 0.421 | V3: 0.468 | W3: 87.884495 | X3: 0 | Y3: 0.516 | Z3: 14740693 | AA3: 0.398 | AB3: 76896 | AC3: 1862 | AD3: 1105 | AE3: 593 | AF3: 592 | AG3: 4.8 | AH3: 13.4 | AI3: 485.45721 | AJ3: 6 | AK3: 14.9 | AL3: 59745 | AM3: 138.10421 | AN3: 83265 | AO3: 3236 | AP3: 4.1849759 | AQ3: 7600 | AR3: 1750481 | AS3: 74404 | AT3: 13600 | AU3: 0 | AV3: 42364100 | AW3: 12796789 | AX3: 355208 | AY3: 29714382 | AZ3: 2
A4: II | B4: Antofagasta | C4: 37.24817 | D4: 35.446492 | E4: 22 | F4: 29.960485 | G4: 69.233012 | H4: 3 | I4: 4.0487141 | J4: 3 | K4: 36 | L4: 20.446006 | M4: 2 | N4: 14.291961 | O4: 0 | P4: 3 | Q4: 259.23 | R4: 39 | S4: 2 | T4: 0 | U4: 0.546 | V4: 0.314 | W4: 109.31528 | X4: 0 | Y4: 0.381 | Z4: 22383612 | AA4: 0.495 | AB4: 123017 | AC4: 4228 | AD4: 2324 | AE4: 7 | AF4: 765 | AG4: 6.2 | AH4: 7.3 | AI4: 12.146142 | AJ4: 13 | AK4: 9.6 | AL4: 30220 | AM4: 178.14342 | AN4: 238010 | AO4: 16666 | AP4: 4.0487141 | AQ4: 16280 | AR4: 2846340 | AS4: 200000 | AT4: 149000 | AU4: 149744 | AV4: 38262875 | AW4: 29066423 | AX4: 192572 | AY4: 50841622 | AZ4: 1
A5: III | B5: Atacama | C5: 44.822597 | D5: 26.932876 | E5: 19 | F5: 25.478108 | G5: 56.224836 | H5: 1 | I5: 3.9318067 | J5: 1 | K5: 9 | L5: 18.479492 | M5: 3 | N5: 32.437406 | O5: 0 | P5: 0 | Q5: 184.01 | R5: 35 | S5: 1 | T5: 0 | U5: 0.39 | V5: 0.197 | W5: 66.840715 | X5: 0 | Y5: 0.488 | Z5: 17068077 | AA5: 0.533 | AB5: 21705 | AC5: 3125 | AD5: 965 | AE5: 14 | AF5: 504 | AG5: 6.4 | AH5: 10.2 | AI5: 15.727227 | AJ5: 3 | AK5: 29.3 | AL5: 17860 | AM5: 145.47685 | AN5: 53046 | AO5: 3456 | AP5: 3.9318067 | AQ5: 11614 | AR5: 556668 | AS5: 94100 | AT5: 187035 | AU5: 0 | AV5: 35948639 | AW5: 16986593 | AX5: 233225 | AY5: 30224699 | AZ5: 2
A6: IV | B6: Coquimbo | C6: 37.632002 | D6: 25.165365 | E6: 9 | F6: 17.804745 | G6: 47.744567 | H6: 3 | I6: 3.3155949 | J6: 3 | K6: 13 | L6: 6.9627493 | M6: 3 | N6: 14.091278 | O6: 0 | P6: 1 | Q6: 150.06 | R6: 72 | S6: 3 | T6: 0 | U6: 0.288 | V6: 0.218 | W6: 155.83296 | X6: 0 | Y6: 0.396 | Z6: 20225710 | AA6: 0.449 | AB6: 69974 | AC6: 4203 | AD6: 1831 | AE6: 100 | AF6: 1082 | AG6: 6 | AH6: 12.3 | AI6: 11.604582 | AJ6: 3 | AK6: 29 | AL6: 1431 | AM6: 112.73023 | AN6: 275447 | AO6: 2229 | AP6: 1.6577975 | AQ6: 11056 | AR6: 5364222 | AS6: 189900 | AT6: 72917 | AU6: 0 | AV6: 64917630 | AW6: 33222779 | AX6: 673800 | AY6: 44790979 | AZ6: 3
A7: V | B7: Valparaíso | C7: 52.407634 | D7: 47.049976 | E7: 16 | F7: 27.755914 | G7: 55.849523 | H7: 9 | I7: 1.9482392 | J7: 12 | K7: 44 | L7: 12.208966 | M7: 3 | N7: 18.70959 | O7: 2 | P7: 8 | Q7: 230.65 | R7: 179 | S7: 3 | T7: 5 | U7: 0.311 | V7: 0.291 | W7: 87.670763 | X7: 1.9482392 | Y7: 0.432 | Z7: 24137492 | AA7: 0.445 | AB7: 236177 | AC7: 19176 | AD7: 6765 | AE7: 166 | AF7: 2761 | AG7: 7.5 | AH7: 11.6 | AI7: 50.654219 | AJ7: 10 | AK7: 10.7 | AL7: 16641 | AM7: 143.52029 | AN7: 1557887 | AO7: 4287 | AP7: 1.2988261 | AQ7: 5648.5 | AR7: 3058423 | AS7: 129481 | AT7: 63996 | AU7: 1079295 | AV7: 101802434 | AW7: 24239428 | AX7: 811772 | AY7: 51647041 | AZ7: 1
A8: RM | B8: Metropolitana | C8: 9.222619 | D8: 16.914184 | E8: 47 | F8: 25.508213 | G8: 65.498743 | H8: 0 | I8: 0 | J8: 21 | K8: 42 | L8: 4.8340382 | M8: 4 | N8: 14.716594 | O8: 5 | P8: 33 | Q8: 331.61 | R8: 507 | S8: 39 | T8: 1 | U8: 0.372 | V8: 0.295 | W8: 65.333759 | X8: 0.65993696 | Y8: 0.47 | Z8: 60400444 | AA8: 0.424 | AB8: 1146510 | AC8: 53517 | AD8: 23242 | AE8: 7605 | AF8: 9385 | AG8: 7.7 | AH8: 8.8 | AI8: 39.596218 | AJ8: 102 | AK8: 12.3 | AL8: 147198 | AM8: 1295.1128 | AN8: 7307884 | AO8: 6196 | AP8: 0.32996848 | AQ8: 19352 | AR8: 13709951 | AS8: 56982 | AT8: 0 | AU8: 0 | AV8: 230562951 | AW8: 43552270 | AX8: 62052 | AY8: 90875903 | AZ8: 1
A9: VI | B9: O'Higgins | C9: 18.959119 | D9: 49.421811 | E9: 6 | F9: 19.945505 | G9: 43.42663 | H9: 0 | I9: 2.5620431 | J9: 3 | K9: 39 | L9: 9.991968 | M9: 2 | N9: 14.949521 | O9: 1 | P9: 2 | Q9: 117.3 | R9: 114 | S9: 3 | T9: 7 | U9: 0.203 | V9: 0.22 | W9: 51.240862 | X9: 0 | Y9: 0.396 | Z9: 18182163 | AA9: 0.477 | AB9: 111020 | AC9: 4894 | AD9: 2451 | AE9: 762 | AF9: 1136 | AG9: 6 | AH9: 9.9 | AI9: 11.529194 | AJ9: 7 | AK9: 10.2 | AL9: 26831 | AM9: 95.804743 | AN9: 265601 | AO9: 3056 | AP9: 1.2810215 | AQ9: 4700 | AR9: 754000 | AS9: 179000 | AT9: 6000 | AU9: 345000 | AV9: 50200910 | AW9: 17850727 | AX9: 444491 | AY9: 43045390 | AZ9: 1
A10: VII | B10: Maule | C10: 15.637096 | D10: 19.942803 | E10: 10 | F10: 23.852077 | G10: 35.899249 | H10: 9 | I10: 1.1012039 | J10: 1 | K10: 24 | L10: 8.6995112 | M10: 5 | N10: 25.382751 | O10: 0 | P10: 3 | Q10: 109.73 | R10: 130 | S10: 0 | T10: 2 | U10: 0.245 | V10: 0.227 | W10: 27.530099 | X10: 1.1012039 | Y10: 0.427 | Z10: 25936948 | AA10: 0.53 | AB10: 124820 | AC10: 6018 | AD10: 4771 | AE10: 194 | AF10: 1875 | AG10: 6.4 | AH10: 15.8 | AI10: 11.012039 | AJ10: 5 | AK10: 10.7 | AL10: 1371 | AM10: 48.346496 | AN10: 165417 | AO10: 1311 | AP10: 1.1012039 | AQ10: 7183 | AR10: 647510 | AS10: 168850 | AT10: 8000 | AU10: 218000 | AV10: 97730159 | AW10: 19292650 | AX10: 486500 | AY10: 48826193 | AZ10: 2
A11: VIII | B11: Biobío | C11: 14.127921 | D11: 14.004368 | E11: 16 | F11: 27.159987 | G11: 38.193732 | H11: 2 | I11: 1.6115499 | J11: 6 | K11: 26 | L11: 1.6115499 | M11: 3 | N11: 20.531145 | O11: 1 | P11: 3 | Q11: 162.84 | R11: 211 | S11: 1 | T11: 0 | U11: 0.36 | V11: 0.31 | W11: 63.924812 | X11: 0 | Y11: 0.42 | Z11: 41208340 | AA11: 0.41 | AB11: 292281 | AC11: 19222 | AD11: 5713 | AE11: 37 | AF11: 3193 | AG11: 7.9 | AH11: 15.8 | AI11: 12.892399 | AJ11: 12 | AK11: 11.8 | AL11: 15518 | AM11: 188.60655 | AN11: 305920 | AO11: 4475 | AP11: 1.0743666 | AQ11: 7362 | AR11: 3548528 | AS11: 317000 | AT11: 44000 | AU11: 319660 | AV11: 137998425 | AW11: 28228357 | AX11: 1646127 | AY11: 88172439 | AZ11: 3
A12: IX | B12: Araucanía | C12: 15.985555 | D12: 15.686545 | E12: 25 | F12: 25.8874 | G12: 40.826419 | H12: 23 | I12: 2.3000799 | J12: 2 | K12: 16 | L12: 9.0853157 | M12: 13 | N12: 22.73629 | O12: 4 | P12: 1 | Q12: 135.88 | R12: 118 | S12: 5 | T12: 0 | U12: 0.381 | V12: 0.288 | W12: 78.202718 | X12: 1.15004 | Y12: 0.369 | Z12: 29000528 | AA12: 0.469 | AB12: 140063 | AC12: 8685 | AD12: 3161 | AE12: 323 | AF12: 1550 | AG12: 8 | AH12: 18.1 | AI12: 20.700719 | AJ12: 4 | AK12: 30.3 | AL12: 5856 | AM12: 232.88701 | AN12: 395583 | AO12: 372 | AP12: 1.15004 | AQ12: 9488 | AR12: 1842375 | AS12: 108799 | AT12: 27507 | AU12: 0 | AV12: 67212297 | AW12: 31050589 | AX12: 0 | AY12: 54529735 | AZ12: 2
A13: XIV | B13: Los Ríos | C13: 34.512172 | D13: 26.206804 | E13: 9 | F13: 30.471722 | G13: 42.649188 | H13: 2 | I13: 2.8058676 | J13: 1 | K13: 40 | L13: 8.6981897 | M13: 12 | N13: 0 | O13: 1 | P13: 0 | Q13: 191.32 | R13: 44 | S13: 1 | T13: 0 | U13: 0.274 | V13: 0.27 | W13: 101.01123 | X13: 0 | Y13: 0.298 | Z13: 15834434 | AA13: 0.44 | AB13: 22076 | AC13: 3235 | AD13: 818 | AE13: 29 | AF13: 773 | AG13: 6.4 | AH13: 14.3 | AI13: 11.223471 | AJ13: 4 | AK13: 11.3 | AL13: 6171 | AM13: 51.622697 | AN13: 71200 | AO13: 71 | AP13: 2.8058676 | AQ13: 7109 | AR13: 1476220 | AS13: 253292 | AT13: 35000 | AU13: 13000 | AV13: 49376288 | AW13: 22065484 | AX13: 486875 | AY13: 32409855 | AZ13: 1
A14: X | B14: Los Lagos | C14: 36.414929 | D14: 27.360029 | E14: 24 | F14: 22.644226 | G14: 47.297552 | H14: 2 | I14: 4.1856241 | J14: 2 | K14: 27 | L14: 20.92812 | M14: 8 | N14: 25.727636 | O14: 2 | P14: 2 | Q14: 162.58 | R14: 86 | S14: 6 | T14: 0 | U14: 0.323 | V14: 0.201 | W14: 104.6406 | X14: 0 | Y14: 0.374 | Z14: 19901362 | AA14: 0.426 | AB14: 85949 | AC14: 8729 | AD14: 2023 | AE14: 192 | AF14: 1409 | AG14: 3.5 | AH14: 11.8 | AI14: 23.718536 | AJ14: 2 | AK14: 8 | AL14: 2160 | AM14: 994.62248 | AN14: 122157 | AO14: 2251 | AP14: 4.1856241 | AQ14: 4707.6667 | AR14: 7108761 | AS14: 264511 | AT14: 96915 | AU14: 63500 | AV14: 101170739 | AW14: 40816121 | AX14: 737875 | AY14: 62581190 | AZ14: 2
A15: XI | B15: Aysén | C15: 76.509422 | D15: 40.98719 | E15: 15 | F15: 27.543392 | G15: 43.719669 | H15: 0 | I15: 10.929917 | J15: 0 | K15: 57 | L15: 67.765488 | M15: 4 | N15: 24.264417 | O15: 1 | P15: 0 | Q15: 170.81 | R15: 20 | S15: 0 | T15: 0 | U15: 0.351 | V15: 0.256 | W15: 174.87868 | X15: 10.929917 | Z15: 15972532 | AA15: 0.445 | AB15: 14119 | AC15: 3349 | AD15: 422 | AE15: 0 | AF15: 469 | AG15: 4.4 | AH15: 5.2 | AI15: 32.789752 | AJ15: 1 | AK15: 7 | AL15: 1953 | AM15: 106.08251 | AN15: 13667 | AO15: 379 | AP15: 10.929917 | AQ15: 5660 | AR15: 200654 | AS15: 65000 | AT15: 454500 | AU15: 536488 | AV15: 32558406 | AW15: 13692259 | AX15: 794614 | AY15: 29462726 | AZ15: 2
A16: XII | B16: Magallanes y Antártica | C16: 59.008394 | D16: 59.339902 | E16: 12 | F16: 34.675719 | G16: 71.605691 | H16: 0 | I16: 13.260313 | J16: 1 | K16: 15 | L16: 137.24424 | M16: 0 | N16: 18.365534 | O16: 1 | P16: 2 | Q16: 297.25 | R16: 21 | S16: 3 | T16: 0 | U16: 0.283 | V16: 0.18 | W16: 53.041253 | X16: 6.6301566 | Y16: 0.367 | Z16: 20075842 | AA16: 0.414 | AB16: 8659 | AC16: 2527 | AD16: 660 | AE16: 0 | AF16: 216 | AG16: 5.4 | AH16: 6.1 | AI16: 86.192036 | AJ16: 1 | AK16: 22 | AL16: 616 | AM16: 5.1145114 | AN16: 322800 | AO16: 397 | AP16: 13.260313 | AQ16: 4217 | AR16: 558678 | AS16: 266000 | AT16: 525000 | AU16: 32100 | AV16: 30955753 | AW16: 18036736 | AX16: 357752 | AY16: 30288105 | AZ16: 1

Sheet DB2_Indicator_Metadata
A1: DB2 Indicator Metadata: reference year, source and type code, as recorded in the original Ministry file
A2: Copied from rows 7 and 24–26 of 'Tourism Chile D6 - D10.xlsx' (Tipo de variable / AÑO / FUENTE / LINK). DB1 carries no equivalent metadata.
A3: Dimension | B3: Indicator | C3: Type code | D3: Reference year | E3: Source (FUENTE) | F3: Link
A4: D6 | B4: Density of restaurants per 100,000 habitants | C4: VA | D4: 2010 | E4: INE - Informe anual de turismo | F4: http://www.ine.cl/canales/menu/publicaciones/calendario_de_publicaciones/pdf/18082011/Turismo_2010_18082011.pdf
A5: D6 | B5: People working at restaurants per 10,000 habitants | C5: VA | D5: 2006 | E5: SERNATUR - Turismo y empleo en Chile | F5: http://www.sernatur.cl/estudios-y-estadisticas?did=16
A6: D6 | B6: Car rental agencies | C6: VI | D6: 2011 | E6: SERNATUR - Unidad de servicios turísticos | F6: ----------------
A7: D6 | B7: Hospital beds per 10,000 habitants | C7: VI | D7: 2011 | E7: INE -“Estadísticas de salud” – “Dotación de camas hospitalarias por subsector y región | F7: http://www.ine.cl/canales/menu/publicaciones/compendio_estadistico/pdf/2011/1.6estadisticas_salud.pdf
A8: D6 | B8: Density of ATM machines per 100,000 habitants | C8: VI | D8: 2010 | E8: SBIF -"Información financiera” – Categoría “Productos” – Estadística de Cajeros automáticos | F8: http://www.sbif.cl/sbifweb/servlet/InfoFinanciera?indice=4.1&idCategoria=564&tipocont=2150
A9: D6 | B9: Spas | C9: VA | D9: 2011 | E9: Atractivos Turísticos Base SIG SERNATUR | F9: ----------------
A10: D6 | B10: Casinos per 100,000 habitants | C10: VA | D10: 2011 | E10: Superintendencia de Casinos de Juego – Estadísticas de la industria – Análisis de la industria –Casinos de juego en operación | F10: http://www.scj.cl/estadisticas/analisis_estadisticas1.html
A11: D6 | B11: Golf courses | C11: VI | D11: 2011 | E11: Federación chilena de golf – Listado de clubes | F11: http://www.chilegolf.cl/es/clubes
A12: D6 | B12: Artwork Centers | C12: VP | D12: 2011 | E12: SERNATUR - Unidad de servicios turísticos | F12: ----------------
A13: D6 | B13: Density of tourist guides per 100,000 habitants | C13: VP | D13: 2011 | E13: SERNATUR - Unidad de servicios turísticos | F13: ----------------
A14: D6 | B14: Thermal centers | C14: VP | D14: 2010 | E14: SERNATUR- Micrositio de rutas termales | F14: http://www.sernatur.cl/images/lang1/nacional/micrositios/termas/index.php?cod=12
A15: D6 | B15: Density of sports centers per 10,000 habitants | C15: VP | D15: 2004 | E15: INE-Primer Catastro Nacional de Instalaciones y Recintos deportivos | F15: http://www.ine.cl/canales/sala_prensa/archivo_documentos/enfoques/2006/pdf/deporte090506.pdf
... A20: D6 | B20: Number of certified tourism-operators | C20: VPP | D20: 2012 | E20: SERNATUR - Servicio de Angencias de Viajes y Tour Operadores Certificados | F20: www.calidadturistica.cl
A21: D6 | B21: Number of vineyards | C21: VPP | E21: SIG Sernatur/ Categoría Realizaciones Técticas Contemporáneas | F21: ----------------
A22: D7 | B22: Percentage of crime perception | C22: VA | D22: 2010 | E22: Subsecretaría de prevención del delito – encuesta ENUSC “Encuesta nacional urbana de seguridad ciudadana” | F22: http://www.seguridadpublica.gov.cl/enusc_2010.html
A23: D7 | B23: Percentage of homes with at least one crime victim per year | C23: VA | D23: 2010 | E23: INE - Encuesta de seguridad ciudadana | F23: http://www.ine.cl/canales/chile_estadistico/encuestas_seguridadciudadana/victimizacion2010.php
A24: D7 | B24: Density of murders per one million habitants | C24: VA | D24: 2010 | E24: INE – Anuario de Investigaciones | F24: http://www.ine.cl/canales/chile_estadistico/estadisticas_sociales_culturales/policiales/investigaciones/investigaciones.php
A25: D7 | B25: Density of public health complaints per one million habitants | C25: VA | D25: 2010 | E25: INE – Anuario de Investigaciones | F25: http://www.ine.cl/canales/chile_estadistico/estadisticas_sociales_culturales/policiales/investigaciones/investigaciones.php
A26: D7 | B26: Crime index | C26: VI | D26: 2010 | E26: Fundación Paz Ciudadana - Conceptos Nº 22: La medición del desempeño policial en Chile | F26: http://www.pazciudadana.cl/publs.php?&view=A
A27: D7 | B27: Allocated budget for public safety (millions of chilean pesos) | C27: VA | D27: 2010 | E27: DIPRES – instituciones – Ministerio del interior y seguridad pública – Antecedentes presupuestarios – Presupuesto Capítulos | F27: http://www.dipres.gob.cl/574/multipropertyvalues-2430-14273.html
A28: D7 | B28: Porcentage of homes that reported at least one crime | C28: VP | D28: 2010 | E28: INE - Encuesta de seguridad ciudadana | F28: http://www.ine.cl/canales/chile_estadistico/encuestas_seguridadciudadana/victimizacion2010.php
A29: D7 | B29: Number of reported crimes | C29: VP | D29: 2008 | E29: Subsecretaría de prevención del delito | F29: http://www.seguridadpublica.gov.cl/publicaciones.html
A30: D7 | B30: Number of crimes investigated and resolved | C30: VP | D30: 2010 | E30: INE – Anuario de Investigaciones | F30: http://www.ine.cl/canales/chile_estadistico/estadisticas_sociales_culturales/policiales/investigaciones/investigaciones.php
A31: D7 | B31: Number of accidents (roads; air; water) | C31: VPP | D31: 2008 | E31: INE - Carabineros Informe Anual 2008 | F31: ----------------
A32: D7 | B32: Illegal commerce | C32: VPP | D32: 2011 | E32: Carabineros de Chile - Carabineros en Cifras 2011 | F32: ----------------
A33: D7 | B33: Number of police units | C33: VPP | D33: 2011 | E33: Carabineros de Chile - Cuenta Pública | F33: http://centroestudios.carabineros.cl/#
... A45: D9 | B45: Average number of internet searches for main tourist attractions | C45: VP | D45: 2011 | E45: Google AdWords | F45: https://adwords.google.com
A46: D9 | B46: Yearly budget for tourism promotion ($M) | C46: VP | D46: 2011-2014 | E46: Plan para el Desarrollo Turístico Región Metropolitana | F46: http://www.sernatur.cl/planes-regionales-de-desarrollo-turistico
A47: D9 | B47: Yearly budget for international tourism promotion ($M) | C47: VP | D47: 2011-2014 | E47: Plan para el Desarrollo Turístico Región Metropolitana | F47: http://www.sernatur.cl/planes-regionales-de-desarrollo-turistico
A48: D9 | B48: Governmental resources allocated to tourism promotion ($M) | C48: VPP | D48: 2011 | E48: DIPRES - Informe Ejecución Programa Cuarto Trimestre | F48: http://www.dipres.gob.cl/574/propertyvalue-14273.html
A49: D10 | B49: Public infrastructure investments related to the tourism sector ($) | C49: VPP | D49: 2011 | E49: MOP - Informe de Ejecución Presupuestaria | F49: http://www.dirplan.cl/InformaciondePresupuestoMOP/informedeejecucionpresupuestaria/Paginas/default.aspx
A50: D10 | B50: Entrepreneurial and Innovation funds allocated to tourism related projects ($) | C50: VPP | D50: 2011 | E50: DIPRES - Informe Ejecución Programa Cuarto Trimestre | F50: http://www.dipres.gob.cl/574/propertyvalue-14273.html
A51: D10 | B51: Seed funds allocated to the tourism sector ($) | C51: VPP | D51: Promedio 2011-2010 | E51: DIPRES - Informe Ejecución Programa Cuarto Trimestre | F51: http://www.dipres.gob.cl/574/propertyvalue-14273.html
A52: D10 | B52: Governmental funds devoted to tourism development ($) | C52: VPP | D52: 2011 | E52: SUBDERE - Informe de Ejecución Presupuestaria Fondo Nacional Desarrollo Nacional al 31 de Diciembre del 2011 | F52: http://www.subdere.cl/documentacion/fndr-ejecuci%C3%B3n-presupuestaria-al-31-de-diciembre-de-2011
A53: D10 | B53: Number of regional strategy plans for tourism development | C53: VPP | D53: Desde 2000 hasta 2030 | E53: SUBDERE - Estrategias Regionales de Desarrollo (ERD) | F53: http://www.subdere.gov.cl/documentacion/estrategias-regionales-de-desarrollo
A55: 45 of 50 indicators carry a numeric year (2004–2012); 37 are dated 2010 or 2011. Type codes run VA → VI → VP → VPP within each dimension; all five D10 variables are VPP.

Sheet Tableau_TimeSeries
A1: region_code | B1: region_name | C1: year | D1: quarter | E1: period_label | F1: international_arrivals | G1: national_arrivals | H1: avg_daily_rate_usd | I1: occupancy_rate_pct | J1: avg_length_of_stay_nights | K1: data_quality_note
A2: III | B2: Atacama | C2: 2025 | D2: Q1 | E2: 2025-Q1 | F2: 11500 | G2: 24619 | H2: 118.44 | I2: 65.7 | J2: 2.57
A3: II | B3: Antofagasta | C3: 2019 | D3: Q3 | E3: 2019-Q3 | F3: 5554 | G3: 13956 | H3: 108.35 | I3: 48.6 | J3: 2.14
A4: II | B4: Antofagasta | C4: 2023 | D4: Q3 | E4: 2023-Q3 | F4: 6402 | G4: 15949 | H4: 124.94 | I4: 50.2 | J4: 2.36
A5: XIV | B5: Los Ríos | C5: 2023 | D5: Q4 | E5: 2023-Q4 | F5: 8485 | G5: 19134 | H5: 108.46 | I5: 53 | J5: 2.43
A6: III | B6: Atacama | C6: 2019 | D6: Q3 | E6: 2019-Q3 | F6: 3872 | G6: 11476 | H6: 107.79 | I6: 53.3 | J6: 2.09
A7: RM | B7: Metropolitana | C7: 2019 | D7: Q3 | E7: 2019-Q3 | F7: 17467 | G7: 41466 | H7: 133.11 | I7: 49.1 | J7: 2.09
A8: IV | B8: Coquimbo | C8: 2022 | D8: Q4 | E8: 2022-Q4 | F8: 7941 | G8: 21474 | H8: 120.81 | I8: 53.2 | J8: 2.41
A9: VII | B9: Maule | C9: 2024 | D9: Q4 | E9: 2024-Q4 | F9: 9730 | G9: 19697 | H9: 164.03 | I9: 61.7 | J9: 2.53
A10: XIV | B10: Los Ríos | C10: 2021 | D10: Q1 | E10: 2021-Q1 | F10: 885 | G10: 8764 | H10: 69.96 | I10: 35.4 | J10: 2.47
A11: VII | B11: Maule | C11: 2021 | D11: Q2 | E11: 2021-Q2 | F11: 617 | G11: 5522 | H11: 95.43 | I11: 33.3 | J11: 2.31
A12: XI | B12: Aysén | C12: 2022 | D12: Q3 | E12: 2022-Q3 | F12: 994 | G12: 1696 | H12: 134.01 | I12: 34 | J12: 3.27
A13: V | B13: Valparaíso | C13: 2024 | D13: Q3 | E13: 2024-Q3 | F13: 15158 | G13: 31425 | H13: 125.16 | I13: 48.5 | J13: 2.17
... A97: XIV | B97: Los Ríos | C97: 2025 | D97: Q3 | E97: 2025-Q3 | F97: 5349 | G97: 11571 | H97: 115.65 | I97: 51.9 | J97: 2.24
A98: RM | B98: Metropolitana | C98: 2023 | D98: Q1 | E98: 2023-Q1 | F98: 42001 | G98: 84230 | I98: 74.4 | J98: 2.6
A99: X | B99: Los Lagos | C99: 2022 | D99: Q1 | E99: 2022-Q1 | F99: 11298 | G99: 35163 | H99: 105.09 | I99: 52.7 | J99: 2.53
A100: XV | B100: Arica y Parinacota | C100: 2024 | D100: Q3 | E100: 2024-Q3 | F100: 4255 | G100: 10342 | H100: 123.31 | I100: 52.1 | J100: 2.21
A101: IV | B101: Coquimbo | C101: 2025 | D101: Q1 | E101: 2025-Q1 | F101: 16060 | G101: 31818 | H101: 125.01 | I101: 71.9 | J101: 2.64
A102: I | B102: Tarapacá | C102: 2025 | D102: Q3 | E102: 2025-Q3 | F102: 4861 | G102: 9388 | H102: 129.77 | I102: 53.4 | J102: 2.25
A103: I | B103: Tarapacá | C103: 2024 | D103: Q3 | E103: 2024-Q3 | F103: 4391 | G103: 9557 | H103: 106.57 | I103: 50.6 | J103: 2.41
A104: VIII | B104: Biobío | C104: 2024 | D104: Q3 | E104: 2024-Q3 | F104: 7935 | G104: 16168 | I104: 55.2 | J104: 2.35
A105: II | B105: Antofagasta | C105: 2019 | D105: Q1 | E105: 2019-Q1 | F105: 10977 | G105: 25530 | H105: 109.12 | I105: 65.2 | J105: 2.47
A106: IV | B106: Coquimbo | C106: 2020 | D106: Q4 | E106: 2020-Q4 | F106: 454 | G106: 7360 | H106: 82.27 | I106: 28.5 | J106: 2.5
A107: VII | B107: Maule | C107: 2022 | D107: Q3 | E107: 2022-Q3 | F107: 3466 | G107: 10057 | H107: 130.43 | I107: 52.3 | J107: 2.23
A108: XI | B108: Aysén | C108: 2023 | D108: Q4 | E108: 2023-Q4 | F108: 3224 | G108: 8455 | H108: 139.14 | I108: 48.7 | J108: 4.08
A109: VII | B109: Maule | C109: 2020 | D109: Q4 | E109: 2020-Q4 | F109: 354 | G109: 5785 | H109: 96.85 | I109: 33.3 | J109: 2.69
A110: I | B110: Tarapacá | C110: 2022 | D110: Q4 | E110: 2022-Q4 | F110: 5555 | G110: 14161 | H110: 91.89 | I110: 63.3 | J110: 2.34
A111: VIII | B111: Biobío | C111: 2019 | D111: Q4 | E111: 2019-Q4 | F111: 8588 | G111: 21387 | H111: 111.24 | I111: 66.3 | J111: 2.34
A112: II | B112: Antofagasta | C112: 2024 | D112: Q2 | E112: 2024-Q2 | F112: 9495 | G112: 23504 | H112: 119.28 | I112: 58.6 | J112: 2.54
A113: III | B113: Atacama | C113: 2020 | D113: Q3 | E113: 2020-Q3 | F113: 260 | G113: 4088 | H113: 79.44 | I113: 26.8 | J113: 2.18
A114: VII | B114: Maule | C114: 2024 | D114: Q2 | E114: 2024-Q2 | F114: 8047 | G114: 15596 | H114: 152.58 | I114: 58.8 | J114: 2.43
A115: IV | B115: Coquimbo | C115: 2021 | D115: Q3 | E115: 2021-Q3 | F115: 1858 | G115: 9495 | H115: 84.86 | I115: 39.2 | J115: 2.21
A116: X | B116: Los Lagos | C116: 2024 | D116: Q4 | E116: 2024-Q4 | F116: 17288 | G116: 43246 | H116: 131.53 | I116: 55.9 | J116: 2.47
... A166: RM | B166: Metropolitana | C166: 2023 | D166: Q2 | E166: 2023-Q2 | F166: 29259 | G166: 58456 | H166: 170.96 | I166: 65.9 | J166: 2.64
A167: II | B167: Antofagasta | C167: 2020 | D167: Q2 | E167: 2020-Q2 | F167: 555 | G167: 8282 | H167: 82.31 | J167: 2.33
A168: VII | B168: Maule | C168: 2022 | D168: Q4 | E168: 2022-Q4 | F168: 7403 | G168: 15788 | H168: 134.7 | I168: 59.4 | J168: 2.38
A169: I | B169: Tarapacá | C169: 2024 | D169: Q1 | E169: 2024-Q1 | F169: 9140 | G169: 18955 | H169: 109.29 | I169: 56 | J169: 2.48
A170: VI | B170: O'Higgins | C170: 2024 | D170: Q1 | E170: 2024-Q1 | F170: 9845 | G170: 18295 | H170: 90.9 | I170: 57.4 | J170: 2.39
A171: XIV | B171: Los Ríos | C171: 2020 | D171: Q4 | E171: 2020-Q4 | F171: 409 | G171: 6766 | H171: 70.07 | I171: 31 | J171: 2.44
A172: II | B172: Antofagasta | C172: 2021 | D172: Q1 | E172: 2021-Q1 | F172: 1420 | G172: 11490 | H172: 80.29 | I172: 33.8 | J172: 2.59
A173: V | B173: Valparaíso | C173: 2025 | D173: Q3 | E173: 2025-Q3 | F173: 16269 | G173: 30396 | H173: 131.52 | I173: 51.6 | J173: 2.31
A174: III | B174: Atacama | C174: 2019 | D174: Q2 | E174: 2019-Q2 | F174: 5466 | G174: 14857 | H174: 99.63 | I174: 55.7 | J174: 2.49
A175: XIV | B175: Los Ríos | C175: 2019 | D175: Q3 | E175: 2019-Q3 | F175: 3922 | G175: 9199 | H175: 86.15 | I175: 51.8 | J175: 2.51
A176: XII | B176: Magallanes y Antártica | C176: 2021 | D176: Q4 | E176: 2021-Q4 | F176: 2539 | G176: 8874 | H176: 132.75 | I176: 38 | J176: 4.11
A177: XII | B177: Magallanes y Antártica | C177: 2019 | D177: Q2 | E177: 2019-Q2 | F177: 3247 | G177: 7939 | H177: 172.24 | I177: 37.2 | J177: 3.45
A178: IX | B178: Araucania | C178: 2021 | D178: Q3 | E178: 2021-Q3 | F178: 2125 | G178: 9494 | H178: 74.29 | I178: 38.7 | J178: 2.25
A179: XIV | B179: Los Ríos | C179: 2020 | D179: Q1 | E179: 2020-Q1 | F179: 4604 | G179: 12378 | H179: 73.75 | I179: 43.6 | J179: 2.56
... A213: I | B213: Tarapacá | C213: 2019 | D213: Q4 | E213: 2019-Q4 | F213: 4486 | G213: 13057 | H213: 100.05 | I213: 56.9 | J213: 2.43
A214: III | B214: Atacama | C214: 2020 | D214: Q1 | E214: 2020-Q1 | F214: 4381 | G214: 13812 | I214: 49.7 | J214: 2.62
A215: VIII | B215: Biobío | C215: 2024 | D215: Q4 | E215: 2024-Q4 | F215: 13298 | G215: 25417 | H215: 126.98 | I215: 56.6 | J215: 2.45
A216: XI | B216: Aysén | C216: 2019 | D216: Q1 | E216: 2019-Q1 | F216: 5382 | G216: 12847 | H216: 128 | I216: 73.7 | J216: 4.26
A217: XI | B217: Aysén | C217: 2024 | D217: Q4 | E217: 2024-Q4 | F217: 3304 | G217: 8427 | H217: 158.42 | I217: 58.9 | J217: 3.51
A218: XI | B218: Aysén | C218: 2025 | D218: Q3 | E218: 2025-Q3 | F218: 1214 | G218: 2335 | H218: 176.74 | I218: 38 | J218: 3.37
A219: III | B219: Atacama | C219: 2023 | D219: Q1 | E219: 2023-Q1 | F219: 10339 | G219: 24803 | H219: 112.53 | I219: 68.5 | J219: 2.55
A220: I | B220: Tarapacá | C220: 2022 | D220: Q1 | E220: 2022-Q1 | F220: 4486 | G220: 14521 | H220: 100.6 | I220: 53.6 | J220: 2.3
A221: IV | B221: Coquimbo | C221: 2023 | D221: Q3 | E221: 2023-Q3 | F221: 5716 | G221: 15224 | H221: 127.21 | I221: 57 | J221: 2.25
A222: XI | B222: Aysén | C222: 2021 | D222: Q2 | E222: 2021-Q2 | F222: 180 | G222: 1660 | H222: 119.83 | I222: 31.1 | J222: 3.31
A223: XII | B223: Magallanes y Antártica | C223: 2019 | D223: Q4 | E223: 2019-Q4 | F223: 7742 | G223: 16233 | H223: 160.11 | I223: 61.1 | J223: 4.03
A224: RM | B224: Metropolitana | C224: 2019 | D224: Q4 | E224: 2019-Q4 | F224: 25570 | G224: 67314 | H224: 126.74 | I224: 69.6 | J224: 2.1
A225: VIII | B225: Biobío | C225: 2021 | D225: Q3 | E225: 2021-Q3 | F225: 2350 | G225: 8450 | H225: 90.21 | I225: 37.4 | J225: 2.14
A226: I | B226: Tarapacá | C226: 2019 | D226: Q1 | E226: 2019-Q1 | F226: 6681 | G226: 16504 | H226: 85.28 | I226: 61.8 | J226: 2.78
A227: XI | B227: Aysén | C227: 2025 | D227: Q2 | E227: 2025-Q2 | F227: 1812 | G227: 4247 | H227: 163.45 | J227: 3.69
A228: X | B228: Los Lagos | C228: 2022 | D228: Q2 | E228: 2022-Q2 | F228: 8957 | G228: 26370 | H228: 102.16 | I228: 46.9 | J228: 2.16
A229: I | B229: Tarapacá | C229: 2023 | D229: Q2 | E229: 2023-Q2 | F229: 5704 | G229: 12842 | H229: 121.79 | I229: 55.9 | J229: 2.39
A230: XIV | B230: Los Ríos | C230: 2024 | D230: Q1 | E230: 2024-Q1 | F230: 11214 | G230: 23287 | H230: 103.14 | I230: 63.1 | J230: 2.55
A231: XIV | B231: Los Ríos | C231: 2021 | D231: Q3 | E231: 2021-Q3 | F231: 1363 | G231: 5412 | H231: 81.55 | I231: 30.6 | J231: 2.29
A232: VII | B232: Maule | C232: 2023 | D232: Q2 | E232: 2023-Q2 | F232: 6664 | G232: 14202 | H232: 144.99 | I232: 62.4 | J232: 2.31
A233: III | B233: Atacama | C233: 2022 | D233: Q4 | E233: 2022-Q4 | F233: 6254 | G233: 18416 | H233: 123.46 | I233: 47.9 | J233: 2.33
A234: V | B234: Valparaíso | C234: 2023 | D234: Q1 | E234: 2023-Q1 | F234: 26431 | G234: 51651 | H234: 112.33 | I234: 67.5 | J234: 2.54
A235: XV | B235: Arica y Parinacota | C235: 2019 | D235: Q4 | E235: 2019-Q4 | F235: 5501 | G235: 12713 | H235: 96.47 | I235: 59.5 | J235: 2.44
A236: IX | B236: Araucania | C236: 2023 | D236: Q4 | E236: 2023-Q4 | F236: 13850 | G236: 28838 | H236: 98.38 | I236: 63.1 | J236: 2.42
A237: II | B237: Antofagasta | C237: 2022 | D237: Q2 | E237: 2022-Q2 | F237: 6444 | G237: 18147 | H237: 100.45 | I237: 43.8 | J237: 2.45
A238: XII | B238: Magallanes y Antártica | C238: 2019 | D238: Q3 | E238: 2019-Q3 | F238: 1849 | G238: 3843 | H238: 166.96 | I238: 37.1 | J238: 3.27
A239: I | B239: Tarapacá | C239: 2021 | D239: Q3 | E239: 2021-Q3 | F239: 1180 | G239: 5041 | H239: 82.99 | I239: 33.5 | J239: 2.29
... A244: V | B244: Valparaíso | C244: 2023 | D244: Q2 | E244: 2023-Q2 | F244: 14711 | G244: 41321 | H244: 124.41 | I244: 59.3 | J244: 2.21
A245: IV | B245: Coquimbo | C245: 2019 | D245: Q4 | E245: 2019-Q4 | F245: 9628 | G245: 21198 | I245: 56.3 | J245: 2.55
A246: VII | B246: Maule | C246: 2019 | D246: Q1 | E246: 2019-Q1 | F246: 6105 | G246: 16524 | H246: 113.38 | I246: 71.6 | J246: 2.68
A247: III | B247: Atacama | C247: 2024 | D247: Q3 | E247: 2024-Q3 | F247: 6270 | G247: 12058 | H247: 114.9 | I247: 47.5 | J247: 2.17
A248: RM | B248: Metropolitana | C248: 2022 | D248: Q2 | E248: 2022-Q2 | F248: 21256 | G248: 49307 | H248: 140.98 | I248: 47.1 | J248: 2.47
A249: X | B249: Los Lagos | C249: 2023 | D249: Q2 | E249: 2023-Q2 | F249: 12344 | G249: 38169 | H249: 116.55 | I249: 48.2 | J249: 2.28
A250: X | B250: Los Lagos | C250: 2023 | D250: Q4 | E250: 2023-Q4 | F250: 16811 | G250: 42630 | H250: 133.86 | I250: 61 | J250: 2.42
A251: VIII | B251: Biobío | C251: 2020 | D251: Q3 | E251: 2020-Q3 | F251: 329 | G251: 5612 | H251: 77.5 | I251: 31.7 | J251: 2.17
A252: VI | B252: O'Higgins | C252: 2024 | D252: Q3 | E252: 2024-Q3 | F252: 4321 | G252: 9960 | H252: 104.63 | I252: 48.5 | J252: 2.13
A253: RM | B253: Metropolitana | C253: 2022 | D253: Q1 | E253: 2022-Q1 | F253: 29175 | G253: 66847 | H253: 120.13 | I253: 61.8 | J253: 2.53
A254: V | B254: Valparaíso | C254: 2021 | D254: Q4 | E254: 2021-Q4 | F254: 6712 | G254: 24058 | H254: 99.62 | I254: 41.3 | J254: 2.34
A255: III | B255: Atacama | C255: 2023 | D255: Q3 | E255: 2023-Q3 | F255: 6137 | G255: 12162 | H255: 105.14 | I255: 46 | J255: 2.16
A256: XII | B256: Magallanes y Antártica | C256: 2019 | D256: Q1 | E256: 2019-Q1 | F256: 10417 | G256: 26118 | H256: 149.42 | I256: 88.7 | J256: 4.42
A257: IX | B257: Araucanía | C257: 2019 | D257: Q3 | E257: 2019-Q3 | F257: 6157 | G257: 15678 | H257: 86.25 | I257: 40.4 | J257: 2.12
... A265: IX | B265: Araucanía | C265: 2020 | D265: Q4 | E265: 2020-Q4 | F265: 658 | G265: 9021 | H265: 67.54 | I265: 29.9 | J265: 2.34
A266: IX | B266: Araucanía | C266: 2022 | D266: Q4 | E266: 2022-Q4 | F266: 10208 | G266: 24658 | H266: 89.19 | J266: 2.49 | K266: Araucanía 2022-Q4 occupancy set to missing (source value 104.5% is impossible)
A267: VII | B267: Maule | C267: 2021 | D267: Q3 | E267: 2021-Q3 | F267: 1754 | G267: 5413 | H267: 104.42 | I267: 35.1 | J267: 2.28
A268: VI | B268: O'Higgins | C268: 2025 | D268: Q2 | E268: 2025-Q2 | F268: 5479 | G268: 11519 | H268: 104.89 | I268: 52 | J268: 2.49
A269: I | B269: Tarapacá | C269: 2024 | D269: Q2 | E269: 2024-Q2 | F269: 5604 | G269: 12989 | H269: 105.86 | I269: 50.1 | J269: 2.21
A270: V | B270: Valparaíso | C270: 2022 | D270: Q3 | E270: 2022-Q3 | F270: 10603 | G270: 25989 | H270: 114.19 | I270: 50.2 | J270: 2.2
A271: VI | B271: O'Higgins | C271: 2020 | D271: Q3 | E271: 2020-Q3 | F271: 262 | G271: 3117 | H271: 70.11 | I271: 32.7 | J271: 2.36
A272: III | B272: Atacama | C272: 2021 | D272: Q1 | E272: 2021-Q1 | F272: 1078 | G272: 9718 | H272: 86.96 | I272: 36.1 | J272: 2.39
A273: XI | B273: Aysén | C273: 2019 | D273: Q4 | E273: 2019-Q4 | F273: 2745 | G273: 7067 | H273: 134.13 | I273: 50.5 | J273: 4.16
A274: VII | B274: Maule | C274: 2024 | D274: Q1 | E274: 2024-Q1 | F274: 12366 | G274: 23693 | H274: 145.61 | I274: 75 | J274: 2.63
A275: RM | B275: Metropolitana | C275: 2025 | D275: Q3 | E275: 2025-Q3 | F275: 28073 | G275: 55243 | H275: 176.81 | I275: 52.6 | J275: 2.28
A276: RM | B276: Metropolitana | C276: 2020 | D276: Q2 | E276: 2020-Q2 | F276: 1302 | G276: 19475 | H276: 111.8 | I276: 31.2 | J276: 2.31
...

Sheet Tableau_DigitalReadiness
A1: region_code | B1: region_name | C1: as_of_year | D1: fixed_broadband_penetration_pct | E1: mobile_4g5g_coverage_pct | F1: ecommerce_adoption_pct_smes | G1: digital_payments_adoption_pct | H1: ai_analytics_maturity_index_1to5 | I1: tourism_tech_startups_count | J1: rd_investment_million_usd | K1: digital_tourism_platforms_listed_count | L1: ai_workforce_pct_of_tourism_workforce
A2: XV | B2: Arica y Parinacota | C2: 2025 | D2: 46.6 | E2: 69.3 | F2: 36.3 | G2: 36.9 | H2: 2.72 | I2: 10 | J2: 1.57 | K2: 9 | L2: 5
A3: I | B3: Tarapacá | C3: 2025 | D3: 55.9 | E3: 68.1 | F3: 38.3 | G3: 42.6 | H3: 2.19 | I3: 16 | J3: 0.67 | K3: 13 | L3: 4.4
A4: II | B4: Antofagasta | C4: 2025 | D4: 59.1 | E4: 70.9 | F4: 50.4 | G4: 53.1 | H4: 2.77 | I4: 19 | J4: 3.67 | K4: 6 | L4: 5.5
A5: III | B5: Atacama | C5: 2025 | D5: 49.1 | E5: 66.5 | F5: 41.6 | G5: 48.5 | H5: 2.25 | I5: 9 | J5: 2.56 | K5: 11 | L5: 3.4
A6: IV | B6: Coquimbo | C6: 2025 | D6: 61.7 | E6: 75.7 | F6: 47.1 | G6: 47.1 | H6: 3.18 | I6: 19 | J6: 4.65 | K6: 14 | L6: 4.2
A7: V | B7: Valparaíso | C7: 2025 | D7: 69.5 | E7: 74.2 | F7: 46.8 | G7: 46.8 | H7: 2.72 | I7: 23 | J7: 3.88 | K7: 17 | L7: 7.6
A8: RM | B8: Metropolitana | C8: 2025 | D8: 73.9 | E8: 82.3 | F8: 56.2 | G8: 72.1 | H8: 3.58 | I8: 26 | J8: 6.74 | K8: 20 | L8: 7.7
A9: VI | B9: O'Higgins | C9: 2025 | D9: 42.4 | E9: 66.2 | F9: 28.5 | G9: 40.3 | H9: 1.01 | I9: 14 | J9: 3.08 | K9: 10 | L9: 3.6
A10: VII | B10: Maule | C10: 2025 | D10: 67.6 | E10: 80.9 | F10: 44.7 | G10: 56.5 | H10: 2.72 | I10: 30 | J10: 4.99 | K10: 18 | L10: 6.4
A11: VIII | B11: Biobío | C11: 2025 | D11: 61.2 | E11: 72.5 | F11: 42.4 | G11: 51.4 | H11: 2.67 | I11: 15 | J11: 4.93 | K11: 12 | L11: 5.3
A12: IX | B12: Araucanía | C12: 2025 | D12: 37.3 | E12: 61.5 | F12: 27.9 | G12: 30.8 | H12: 1.14 | I12: 13 | J12: 3.26 | K12: 6 | L12: 4.1
A13: XIV | B13: Los Ríos | C13: 2025 | D13: 53 | E13: 61.2 | F13: 25.3 | G13: 37.2 | H13: 1.29 | I13: 10 | J13: 2.62 | K13: 10 | L13: 3.9
... A16: XII | B16: Magallanes y Antártica | C16: 2025 | D16: 61.1 | E16: 69.9 | F16: 42.7 | G16: 60.5 | H16: 2.95 | I16: 19 | J16: 3.11 | K16: 12 | L16: 6.5

Sheet DB4_Booking
A1: record_type | B1: record_id | C1: region_code | D1: region_name | E1: year | F1: quarter | G1: platform | H1: avg_daily_rate_usd | I1: occupancy_pct | J1: review_score | K1: review_count
A2: online_travel_platform_snapshot | B2: 1000 | C2: XV | D2: Arica y Parinacota | E2: 2022 | F2: Q1 | G2: BookNow | H2: 87.79 | I2: 36.5 | J2: 4.16 | K2: 743
A3: online_travel_platform_snapshot | B3: 1001 | C3: XV | D3: Arica y Parinacota | E3: 2022 | F3: Q1 | G3: StaySouth | H3: 91.46 | I3: 40.6 | J3: 3.99 | K3: 251
A4: online_travel_platform_snapshot | B4: 1002 | C4: XV | D4: Arica y Parinacota | E4: 2022 | F4: Q2 | G4: StaySouth | H4: 99.84 | I4: 71 | J4: 3.87 | K4: 520
A5: online_travel_platform_snapshot | B5: 1003 | C5: XV | D5: Arica y Parinacota | E5: 2022 | F5: Q3 | G5: BookNow | H5: 105.79 | I5: 81.1 | J5: 4.46 | K5: 615
A6: online_travel_platform_snapshot | B6: 1004 | C6: XV | D6: Arica y Parinacota | E6: 2022 | F6: Q4 | G6: BookNow | H6: 89.04 | I6: 50.3 | J6: 4.73 | K6: 95
A7: online_travel_platform_snapshot | B7: 1005 | C7: XV | D7: Arica y Parinacota | E7: 2022 | F7: Q4 | G7: StaySouth | H7: 97.7 | I7: 67.8 | J7: 3.96 | K7: 423
A8: online_travel_platform_snapshot | B8: 1006 | C8: XV | D8: Arica y Parinacota | E8: 2023 | F8: Q1 | G8: BookNow | H8: 118.28 | I8: 42.7 | J8: 4.21 | K8: 146
A9: online_travel_platform_snapshot | B9: 1007 | C9: XV | D9: Arica y Parinacota | E9: 2023 | F9: Q1 | G9: StaySouth | H9: 95.16 | I9: 90.3 | J9: 4.58 | K9: 887
A10: online_travel_platform_snapshot | B10: 1008 | C10: XV | D10: Arica y Parinacota | E10: 2023 | F10: Q2 | G10: StaySouth | H10: 116.83 | I10: 73.4 | J10: 3.93 | K10: 339
A11: online_travel_platform_snapshot | B11: 1009 | C11: XV | D11: Arica y Parinacota | E11: 2023 | F11: Q3 | G11: BookNow | H11: 104.8 | I11: 50.2 | J11: 4.3 | K11: 190
A12: online_travel_platform_snapshot | B12: 1010 | C12: XV | D12: Arica y Parinacota | E12: 2023 | F12: Q4 | G12: StaySouth | H12: 125.41 | I12: 54.6 | J12: 4.45 | K12: 389
A13: online_travel_platform_snapshot | B13: 1011 | C13: XV | D13: Arica y Parinacota | E13: 2024 | F13: Q1 | G13: BookNow | H13: 107.06 | I13: 60.4 | J13: 4.37 | K13: 564
... A281: online_travel_platform_snapshot | B281: 1279 | C281: XII | D281: Magallanes y Antártica | E281: 2025 | F281: Q2 | G281: StaySouth | H281: 208.71 | I281: 52.4 | J281: 4.03 | K281: 333

Sheet DB4_Sentiment
A1: record_type | B1: record_id | C1: region_code | D1: region_name | E1: year | F1: quarter | G1: source | H1: sentiment_score | I1: mention_count | J1: top_keywords | K1: flagged_complaints
A2: social_media_sentiment | B2: 1280 | C2: XV | D2: Arica y Parinacota | E2: 2020 | F2: Q1 | G2: Instagram | H2: 0.56 | I2: 4027 | J2: [{"keyword": "indigenous culture", "count": 176}, {"keyword": "hiking trails", "count": 317}, {"keyword": "local markets", "count": 391}, {"keyword": "safety", "count": 13}]
A3: social_media_sentiment | B3: 1281 | C3: XV | D3: Arica y Parinacota | E3: 2020 | F3: Q2 | G3: X | H3: 0.12 | I3: 2413 | J3: [{"keyword": "hot springs", "count": 9}, {"keyword": "festivals", "count": 391}, {"keyword": "public transport", "count": 377}, {"keyword": "beaches", "count": 161}]
A4: social_media_sentiment | B4: 1282 | C4: XV | D4: Arica y Parinacota | E4: 2020 | F4: Q3 | G4: X | H4: 0.47 | I4: 4362 | J4: [{"keyword": "local markets", "count": 342}, {"keyword": "beaches", "count": 22}, {"keyword": "whale watching", "count": 369}]
A5: social_media_sentiment | B5: 1283 | C5: XV | D5: Arica y Parinacota | E5: 2020 | F5: Q4 | G5: Instagram | H5: 0.01 | I5: 2023 | J5: [{"keyword": "beaches", "count": 399}, {"keyword": "whale watching", "count": 127}, {"keyword": "indigenous culture", "count": 263}, {"keyword": "hot springs", "count": 247}]
A6: social_media_sentiment | B6: 1284 | C6: XV | D6: Arica y Parinacota | E6: 2021 | F6: Q2 | G6: Instagram | H6: 0.03 | I6: 4351 | J6: [{"keyword": "national parks", "count": 190}, {"keyword": "safety", "count": 30}, {"keyword": "cleanliness", "count": 187}]
A7: social_media_sentiment | B7: 1285 | C7: XV | D7: Arica y Parinacota | E7: 2021 | F7: Q4 | G7: X | H7: -0.07 | I7: 814 | J7: [{"keyword": "public transport", "count": 236}, {"keyword": "hiking trails", "count": 229}, {"keyword": "beaches", "count": 141}, {"keyword": "glaciers", "count": 302}, {"keyword": "national parks", "count": 148}]
A8: social_media_sentiment | B8: 1286 | C8: XV | D8: Arica y Parinacota | E8: 2022 | F8: Q1 | G8: X | H8: 0.01 | I8: 4245 | J8: [{"keyword": "desert stargazing", "count": 68}, {"keyword": "cleanliness", "count": 247}, {"keyword": "hiking trails", "count": 252}] | K8: ["cleanliness near terminals", "price transparency"]
A9: social_media_sentiment | B9: 1287 | C9: XV | D9: Arica y Parinacota | E9: 2022 | F9: Q2 | G9: X | H9: 0.29 | I9: 3009 | J9: [{"keyword": "volcano trekking", "count": 271}, {"keyword": "beaches", "count": 114}, {"keyword": "wine tours", "count": 211}]
A10: social_media_sentiment | B10: 1288 | C10: XV | D10: Arica y Parinacota | E10: 2023 | F10: Q1 | G10: TripAdvisor | H10: 0.2 | I10: 4843 | J10: [{"keyword": "street art", "count": 106}, {"keyword": "wine tours", "count": 198}, {"keyword": "glaciers", "count": 311}, {"keyword": "astronomy tourism", "count": 344}]
A11: social_media_sentiment | B11: 1289 | C11: XV | D11: Arica y Parinacota | E11: 2023 | F11: Q2 | G11: X | H11: 0.54 | I11: 1001 | J11: [{"keyword": "wine tours", "count": 311}, {"keyword": "local markets", "count": 42}, {"keyword": "astronomy tourism", "count": 289}, {"keyword": "beaches", "count": 206}] | K11: ["transport connections", "wifi reliability"]
A12: social_media_sentiment | B12: 1290 | C12: XV | D12: Arica y Parinacota | E12: 2023 | F12: Q3 | G12: X | H12: 0.56 | I12: 332 | J12: [{"keyword": "volcano trekking", "count": 27}, {"keyword": "desert stargazing", "count": 376}, {"keyword": "safety", "count": 315}, {"keyword": "seafood", "count": 6}]
A13: social_media_sentiment | B13: 1291 | C13: XV | D13: Arica y Parinacota | E13: 2023 | F13: Q4 | G13: X | H13: 0.63 | I13: 4127 | J13: [{"keyword": "local markets", "count": 255}, {"keyword": "wine tours", "count": 163}, {"keyword": "national parks", "count": 327}, {"keyword": "safety", "count": 30}, {"keyword": "seafood", "count": 383}] | K13: ["price transparency"]
A14: social_media_sentiment | B14: 1292 | C14: XV | D14: Arica y Parinacota | E14: 2024 | F14: Q1 | G14: Instagram | H14: 0.19 | I14: 4925 | J14: [{"keyword": "public transport", "count": 92}, {"keyword": "local markets", "count": 87}, {"keyword": "desert stargazing", "count": 246}, {"keyword": "hot springs", "count": 287}, {"keyword": "cleanliness", "count": 398}]
A15: social_media_sentiment | B15: 1293 | C15: XV | D15: Arica y Parinacota | E15: 2024 | F15: Q2 | G15: X | H15: 0.38 | I15: 1808 | J15: [{"keyword": "desert stargazing", "count": 312}, {"keyword": "whale watching", "count": 55}, {"keyword": "wine tours", "count": 337}, {"keyword": "beaches", "count": 354}]
A16: social_media_sentiment | B16: 1294 | C16: XV | D16: Arica y Parinacota | E16: 2024 | F16: Q3 | G16: X | H16: 0.42 | I16: 4902 | J16: [{"keyword": "ski resorts", "count": 355}, {"keyword": "astronomy tourism", "count": 325}, {"keyword": "street art", "count": 327}, {"keyword": "glaciers", "count": 192}, {"keyword": "safety", "count": 11}]
A17: social_media_sentiment | B17: 1295 | C17: XV | D17: Arica y Parinacota | E17: 2024 | F17: Q4 | G17: X | H17: 0.19 | I17: 666 | J17: [{"keyword": "indigenous culture", "count": 296}, {"keyword": "seafood", "count": 165}, {"keyword": "whale watching", "count": 282}, {"keyword": "hot springs", "count": 339}, {"keyword": "cleanliness", "count": 25}]
A18: social_media_sentiment | B18: 1296 | C18: XV | D18: Arica y Parinacota | E18: 2025 | F18: Q2 | G18: Instagram | H18: 0.17 | I18: 2988 | J18: [{"keyword": "beaches", "count": 224}, {"keyword": "hiking trails", "count": 392}, {"keyword": "whale watching", "count": 115}, {"keyword": "wine tours", "count": 23}, {"keyword": "festivals", "count": 379}]
A19: social_media_sentiment | B19: 1297 | C19: XV | D19: Arica y Parinacota | E19: 2025 | F19: Q3 | G19: TripAdvisor | H19: 0.26 | I19: 2001 | J19: [{"keyword": "desert stargazing", "count": 196}, {"keyword": "hot springs", "count": 213}, {"keyword": "signage", "count": 66}, {"keyword": "cleanliness", "count": 76}] | K19: ["overcrowding at peak season"]
A20: social_media_sentiment | B20: 1298 | C20: I | D20: Tarapacá | E20: 2020 | F20: Q2 | G20: X | H20: -0.06 | I20: 1827 | J20: [{"keyword": "beaches", "count": 248}, {"keyword": "local markets", "count": 15}, {"keyword": "cleanliness", "count": 315}, {"keyword": "signage", "count": 216}] | K20: ["signage clarity"]
A21: social_media_sentiment | B21: 1299 | C21: I | D21: Tarapacá | E21: 2020 | F21: Q3 | G21: TripAdvisor | H21: 0.35 | I21: 3571 | J21: [{"keyword": "signage", "count": 21}, {"keyword": "cleanliness", "count": 275}, {"keyword": "volcano trekking", "count": 213}, {"keyword": "hiking trails", "count": 389}]
A22: social_media_sentiment | B22: 1300 | C22: I | D22: Tarapacá | E22: 2020 | F22: Q4 | G22: TripAdvisor | H22: 0.29 | I22: 1380 | J22: [{"keyword": "whale watching", "count": 272}, {"keyword": "signage", "count": 127}, {"keyword": "seafood", "count": 9}] | K22: ["wifi reliability"]
A23: social_media_sentiment | B23: 1301 | C23: I | D23: Tarapacá | E23: 2021 | F23: Q4 | G23: Instagram | H23: 0.21 | I23: 2692 | J23: [{"keyword": "astronomy tourism", "count": 374}, {"keyword": "safety", "count": 132}, {"keyword": "wine tours", "count": 202}] | K23: ["wifi reliability"]
A24: social_media_sentiment | B24: 1302 | C24: I | D24: Tarapacá | E24: 2022 | F24: Q1 | G24: X | H24: 0.13 | I24: 225 | J24: [{"keyword": "whale watching", "count": 86}, {"keyword": "hot springs", "count": 170}, {"keyword": "safety", "count": 234}, {"keyword": "local markets", "count": 323}, {"keyword": "festivals", "count": 285}] | K24: ["signage clarity", "cleanliness near terminals"]
A25: social_media_sentiment | B25: 1303 | C25: I | D25: Tarapacá | E25: 2022 | F25: Q2 | G25: TripAdvisor | H25: 0.32 | I25: 3035 | J25: [{"keyword": "signage", "count": 194}, {"keyword": "volcano trekking", "count": 200}, {"keyword": "cleanliness", "count": 179}, {"keyword": "glaciers", "count": 18}, {"keyword": "whale watching", "count": 266}]
A26: social_media_sentiment | B26: 1304 | C26: I | D26: Tarapacá | E26: 2022 | F26: Q3 | G26: TripAdvisor | H26: 0.12 | I26: 2040 | J26: [{"keyword": "astronomy tourism", "count": 167}, {"keyword": "glaciers", "count": 381}, {"keyword": "hot springs", "count": 215}, {"keyword": "whale watching", "count": 116}, {"keyword": "hiking trails", "count": 22}]
A27: social_media_sentiment | B27: 1305 | C27: I | D27: Tarapacá | E27: 2022 | F27: Q4 | G27: X | H27: 0.37 | I27: 4285 | J27: [{"keyword": "seafood", "count": 236}, {"keyword": "desert stargazing", "count": 218}, {"keyword": "ski resorts", "count": 344}] | K27: ["transport connections"]
A28: social_media_sentiment | B28: 1306 | C28: I | D28: Tarapacá | E28: 2023 | F28: Q1 | G28: TripAdvisor | H28: 0.39 | I28: 2600 | J28: [{"keyword": "desert stargazing", "count": 124}, {"keyword": "hot springs", "count": 218}, {"keyword": "wine tours", "count": 369}, {"keyword": "local markets", "count": 340}, {"keyword": "indigenous culture", "count": 121}] | K28: ["transport connections"]
A29: social_media_sentiment | B29: 1307 | C29: I | D29: Tarapacá | E29: 2023 | F29: Q2 | G29: TripAdvisor | H29: 0.09 | I29: 2311 | J29: [{"keyword": "desert stargazing", "count": 94}, {"keyword": "national parks", "count": 308}, {"keyword": "cleanliness", "count": 191}]
A30: social_media_sentiment | B30: 1308 | C30: I | D30: Tarapacá | E30: 2023 | F30: Q3 | G30: X | H30: -0.53 | I30: 1047 | J30: [{"keyword": "whale watching", "count": 86}, {"keyword": "local markets", "count": 51}, {"keyword": "safety", "count": 17}, {"keyword": "national parks", "count": 246}]
A31: social_media_sentiment | B31: 1309 | C31: I | D31: Tarapacá | E31: 2023 | F31: Q4 | G31: Instagram | H31: 0 | I31: 3927 | J31: [{"keyword": "glaciers", "count": 182}, {"keyword": "seafood", "count": 393}, {"keyword": "volcano trekking", "count": 326}]
A32: social_media_sentiment | B32: 1310 | C32: I | D32: Tarapacá | E32: 2024 | F32: Q1 | G32: X | H32: 0.21 | I32: 4299 | J32: [{"keyword": "astronomy tourism", "count": 370}, {"keyword": "ski resorts", "count": 274}, {"keyword": "wine tours", "count": 221}, {"keyword": "hot springs", "count": 42}] | K32: ["price transparency"]
A33: social_media_sentiment | B33: 1311 | C33: I | D33: Tarapacá | E33: 2024 | F33: Q2 | G33: Instagram | H33: 0.37 | I33: 3742 | J33: [{"keyword": "desert stargazing", "count": 266}, {"keyword": "public transport", "count": 9}, {"keyword": "ski resorts", "count": 102}]
A34: social_media_sentiment | B34: 1312 | C34: I | D34: Tarapacá | E34: 2024 | F34: Q3 | G34: TripAdvisor | H34: 0.22 | I34: 588 | J34: [{"keyword": "desert stargazing", "count": 163}, {"keyword": "seafood", "count": 286}, {"keyword": "signage", "count": 163}, {"keyword": "national parks", "count": 271}, {"keyword": "public transport", "count": 305}] | K34: ["signage clarity", "overcrowding at peak season"]
A35: social_media_sentiment | B35: 1313 | C35: I | D35: Tarapacá | E35: 2024 | F35: Q4 | G35: Instagram | H35: 0.27 | I35: 2991 | J35: [{"keyword": "festivals", "count": 96}, {"keyword": "desert stargazing", "count": 239}, {"keyword": "ski resorts", "count": 47}]
A36: social_media_sentiment | B36: 1314 | C36: I | D36: Tarapacá | E36: 2025 | F36: Q2 | G36: X | H36: 0.16 | I36: 1329 | J36: [{"keyword": "festivals", "count": 196}, {"keyword": "wine tours", "count": 140}, {"keyword": "public transport", "count": 135}, {"keyword": "safety", "count": 294}, {"keyword": "local markets", "count": 114}]
A37: social_media_sentiment | B37: 1315 | C37: I | D37: Tarapacá | E37: 2025 | F37: Q3 | G37: X | H37: -0.19 | I37: 1909 | J37: [{"keyword": "whale watching", "count": 312}, {"keyword": "beaches", "count": 330}, {"keyword": "safety", "count": 145}, {"keyword": "cleanliness", "count": 175}]
A38: social_media_sentiment | B38: 1316 | C38: II | D38: Antofagasta | E38: 2020 | F38: Q1 | G38: X | H38: 0.54 | I38: 4450 | J38: [{"keyword": "volcano trekking", "count": 278}, {"keyword": "cleanliness", "count": 90}, {"keyword": "desert stargazing", "count": 296}, {"keyword": "public transport", "count": 366}] | K38: ["price transparency", "overcrowding at peak season"]
A39: social_media_sentiment | B39: 1317 | C39: II | D39: Antofagasta | E39: 2020 | F39: Q2 | G39: X | H39: 0.5 | I39: 2282 | J39: [{"keyword": "cleanliness", "count": 93}, {"keyword": "hot springs", "count": 157}, {"keyword": "national parks", "count": 331}, {"keyword": "volcano trekking", "count": 201}, {"keyword": "seafood", "count": 252}]
A40: social_media_sentiment | B40: 1318 | C40: II | D40: Antofagasta | E40: 2020 | F40: Q3 | G40: Instagram | H40: 0.54 | I40: 4474 | J40: [{"keyword": "local markets", "count": 380}, {"keyword": "festivals", "count": 121}, {"keyword": "volcano trekking", "count": 34}]
A41: social_media_sentiment | B41: 1319 | C41: II | D41: Antofagasta | E41: 2020 | F41: Q4 | G41: TripAdvisor | H41: 0.26 | I41: 1544 | J41: [{"keyword": "public transport", "count": 12}, {"keyword": "beaches", "count": 206}, {"keyword": "signage", "count": 83}]
A42: social_media_sentiment | B42: 1320 | C42: II | D42: Antofagasta | E42: 2021 | F42: Q1 | G42: TripAdvisor | H42: 0.28 | I42: 3538 | J42: [{"keyword": "safety", "count": 259}, {"keyword": "whale watching", "count": 77}, {"keyword": "astronomy tourism", "count": 323}, {"keyword": "festivals", "count": 256}]
A43: social_media_sentiment | B43: 1321 | C43: II | D43: Antofagasta | E43: 2021 | F43: Q2 | G43: X | H43: 0.42 | I43: 1714 | J43: [{"keyword": "volcano trekking", "count": 141}, {"keyword": "seafood", "count": 346}, {"keyword": "safety", "count": 244}, {"keyword": "wine tours", "count": 134}, {"keyword": "hiking trails", "count": 254}]
A44: social_media_sentiment | B44: 1322 | C44: II | D44: Antofagasta | E44: 2021 | F44: Q4 | G44: Instagram | H44: 0.26 | I44: 2422 | J44: [{"keyword": "wine tours", "count": 201}, {"keyword": "beaches", "count": 108}, {"keyword": "cleanliness", "count": 312}, {"keyword": "hot springs", "count": 377}]
A45: social_media_sentiment | B45: 1323 | C45: II | D45: Antofagasta | E45: 2022 | F45: Q1 | G45: X | H45: 0.59 | I45: 1012 | J45: [{"keyword": "national parks", "count": 363}, {"keyword": "volcano trekking", "count": 355}, {"keyword": "whale watching", "count": 72}, {"keyword": "signage", "count": 200}, {"keyword": "street art", "count": 134}]
A46: social_media_sentiment | B46: 1324 | C46: II | D46: Antofagasta | E46: 2022 | F46: Q2 | G46: Instagram | H46: 0.21 | I46: 1226 | J46: [{"keyword": "local markets", "count": 178}, {"keyword": "beaches", "count": 108}, {"keyword": "desert stargazing", "count": 309}] | K46: ["overcrowding at peak season", "transport connections"]
A47: social_media_sentiment | B47: 1325 | C47: II | D47: Antofagasta | E47: 2022 | F47: Q3 | G47: TripAdvisor | H47: 0.47 | I47: 3945 | J47: [{"keyword": "seafood", "count": 124}, {"keyword": "glaciers", "count": 313}, {"keyword": "national parks", "count": 349}, {"keyword": "public transport", "count": 312}]
A48: social_media_sentiment | B48: 1326 | C48: II | D48: Antofagasta | E48: 2022 | F48: Q4 | G48: X | H48: 0.03 | I48: 3716 | J48: [{"keyword": "street art", "count": 341}, {"keyword": "safety", "count": 173}, {"keyword": "ski resorts", "count": 48}, {"keyword": "national parks", "count": 109}]
A49: social_media_sentiment | B49: 1327 | C49: II | D49: Antofagasta | E49: 2023 | F49: Q2 | G49: Instagram | H49: 0.32 | I49: 4274 | J49: [{"keyword": "seafood", "count": 351}, {"keyword": "festivals", "count": 44}, {"keyword": "national parks", "count": 113}] | K49: ["transport connections"]
A50: social_media_sentiment | B50: 1328 | C50: II | D50: Antofagasta | E50: 2023 | F50: Q3 | G50: Instagram | H50: 0.48 | I50: 2162 | J50: [{"keyword": "whale watching", "count": 25}, {"keyword": "beaches", "count": 61}, {"keyword": "festivals", "count": 117}]
A51: social_media_sentiment | B51: 1329 | C51: II | D51: Antofagasta | E51: 2024 | F51: Q1 | G51: Instagram | H51: -0.02 | I51: 4125 | J51: [{"keyword": "national parks", "count": 387}, {"keyword": "whale watching", "count": 371}, {"keyword": "festivals", "count": 126}, {"keyword": "hiking trails", "count": 317}, {"keyword": "cleanliness", "count": 275}]
A52: social_media_sentiment | B52: 1330 | C52: II | D52: Antofagasta | E52: 2024 | F52: Q2 | G52: TripAdvisor | H52: 0.68 | I52: 2911 | J52: [{"keyword": "national parks", "count": 361}, {"keyword": "glaciers", "count": 305}, {"keyword": "festivals", "count": 48}]
A53: social_media_sentiment | B53: 1331 | C53: II | D53: Antofagasta | E53: 2024 | F53: Q3 | G53: Instagram | H53: 0.48 | I53: 614 | J53: [{"keyword": "ski resorts", "count": 76}, {"keyword": "indigenous culture", "count": 387}, {"keyword": "hot springs", "count": 172}, {"keyword": "glaciers", "count": 271}, {"keyword": "hiking trails", "count": 21}]
A54: social_media_sentiment | B54: 1332 | C54: II | D54: Antofagasta | E54: 2024 | F54: Q4 | G54: X | H54: 0.42 | I54: 3745 | J54: [{"keyword": "street art", "count": 281}, {"keyword": "public transport", "count": 156}, {"keyword": "signage", "count": 118}, {"keyword": "volcano trekking", "count": 107}, {"keyword": "glaciers", "count": 39}]
A55: social_media_sentiment | B55: 1333 | C55: II | D55: Antofagasta | E55: 2025 | F55: Q1 | G55: X | H55: 0.59 | I55: 1348 | J55: [{"keyword": "festivals", "count": 56}, {"keyword": "street art", "count": 232}, {"keyword": "ski resorts", "count": 379}, {"keyword": "astronomy tourism", "count": 89}, {"keyword": "indigenous culture", "count": 243}] | K55: ["cleanliness near terminals", "price transparency"]
A56: social_media_sentiment | B56: 1334 | C56: II | D56: Antofagasta | E56: 2025 | F56: Q2 | G56: Instagram | H56: 0.41 | I56: 3990 | J56: [{"keyword": "festivals", "count": 396}, {"keyword": "local markets", "count": 278}, {"keyword": "beaches", "count": 162}, {"keyword": "safety", "count": 332}, {"keyword": "signage", "count": 39}]
A57: social_media_sentiment | B57: 1335 | C57: II | D57: Antofagasta | E57: 2025 | F57: Q3 | G57: Instagram | H57: 0.35 | I57: 2709 | J57: [{"keyword": "local markets", "count": 366}, {"keyword": "desert stargazing", "count": 305}, {"keyword": "cleanliness", "count": 189}] | K57: ["overcrowding at peak season", "signage clarity"]
A58: social_media_sentiment | B58: 1336 | C58: III | D58: Atacama | E58: 2020 | F58: Q1 | G58: X | H58: 0.56 | I58: 2233 | J58: [{"keyword": "glaciers", "count": 57}, {"keyword": "volcano trekking", "count": 308}, {"keyword": "cleanliness", "count": 358}, {"keyword": "beaches", "count": 125}]
A59: social_media_sentiment | B59: 1337 | C59: III | D59: Atacama | E59: 2020 | F59: Q2 | G59: Instagram | H59: 0.38 | I59: 2027 | J59: [{"keyword": "volcano trekking", "count": 290}, {"keyword": "local markets", "count": 232}, {"keyword": "public transport", "count": 191}, {"keyword": "glaciers", "count": 207}, {"keyword": "astronomy tourism", "count": 31}] | K59: ["transport connections", "price transparency"]
A60: social_media_sentiment | B60: 1338 | C60: III | D60: Atacama | E60: 2020 | F60: Q4 | G60: X | H60: 0.24 | I60: 4052 | J60: [{"keyword": "beaches", "count": 141}, {"keyword": "cleanliness", "count": 233}, {"keyword": "national parks", "count": 341}, {"keyword": "local markets", "count": 167}] | K60: ["wifi reliability"]
A61: social_media_sentiment | B61: 1339 | C61: III | D61: Atacama | E61: 2021 | F61: Q1 | G61: Instagram | H61: 0.3 | I61: 2080 | J61: [{"keyword": "indigenous culture", "count": 332}, {"keyword": "national parks", "count": 358}, {"keyword": "ski resorts", "count": 274}]
A62: social_media_sentiment | B62: 1340 | C62: III | D62: Atacama | E62: 2021 | F62: Q2 | G62: TripAdvisor | H62: 0.07 | I62: 419 | J62: [{"keyword": "wine tours", "count": 273}, {"keyword": "desert stargazing", "count": 200}, {"keyword": "public transport", "count": 298}]
A63: social_media_sentiment | B63: 1341 | C63: III | D63: Atacama | E63: 2021 | F63: Q3 | G63: TripAdvisor | H63: 0.48 | I63: 4155 | J63: [{"keyword": "wine tours", "count": 376}, {"keyword": "cleanliness", "count": 238}, {"keyword": "volcano trekking", "count": 30}, {"keyword": "hot springs", "count": 208}, {"keyword": "hiking trails", "count": 7}]
A64: social_media_sentiment | B64: 1342 | C64: III | D64: Atacama | E64: 2021 | F64: Q4 | G64: X | H64: 0.04 | I64: 3928 | J64: [{"keyword": "indigenous culture", "count": 82}, {"keyword": "national parks", "count": 74}, {"keyword": "ski resorts", "count": 368}, {"keyword": "desert stargazing", "count": 373}] | K64: ["signage clarity"]
A65: social_media_sentiment | B65: 1343 | C65: III | D65: Atacama | E65: 2022 | F65: Q1 | G65: X | H65: -0.13 | I65: 4038 | J65: [{"keyword": "hot springs", "count": 280}, {"keyword": "street art", "count": 289}, {"keyword": "cleanliness", "count": 76}, {"keyword": "glaciers", "count": 346}]
A66: social_media_sentiment | B66: 1344 | C66: III | D66: Atacama | E66: 2022 | F66: Q2 | G66: Instagram | H66: 0.49 | I66: 3990 | J66: [{"keyword": "festivals", "count": 42}, {"keyword": "ski resorts", "count": 165}, {"keyword": "glaciers", "count": 157}]
A67: social_media_sentiment | B67: 1345 | C67: III | D67: Atacama | E67: 2022 | F67: Q3 | G67: Instagram | H67: 0.17 | I67: 919 | J67: [{"keyword": "desert stargazing", "count": 50}, {"keyword": "cleanliness", "count": 72}, {"keyword": "street art", "count": 159}, {"keyword": "astronomy tourism", "count": 91}] | K67: ["wifi reliability"]
A68: social_media_sentiment | B68: 1346 | C68: III | D68: Atacama | E68: 2022 | F68: Q4 | G68: X | H68: 0.4 | I68: 3753 | J68: [{"keyword": "festivals", "count": 381}, {"keyword": "hiking trails", "count": 119}, {"keyword": "street art", "count": 350}] | K68: ["cleanliness near terminals"]
A69: social_media_sentiment | B69: 1347 | C69: III | D69: Atacama | E69: 2023 | F69: Q1 | G69: X | H69: 0.5 | I69: 149 | J69: [{"keyword": "hiking trails", "count": 256}, {"keyword": "volcano trekking", "count": 271}, {"keyword": "whale watching", "count": 91}, {"keyword": "cleanliness", "count": 117}, {"keyword": "national parks", "count": 173}] | K69: ["wifi reliability", "transport connections"]
A70: social_media_sentiment | B70: 1348 | C70: III | D70: Atacama | E70: 2023 | F70: Q2 | G70: Instagram | H70: -0.23 | I70: 1437 | J70: [{"keyword": "cleanliness", "count": 311}, {"keyword": "desert stargazing", "count": 350}, {"keyword": "ski resorts", "count": 33}, {"keyword": "signage", "count": 61}, {"keyword": "hiking trails", "count": 309}]
A71: social_media_sentiment | B71: 1349 | C71: III | D71: Atacama | E71: 2023 | F71: Q4 | G71: Instagram | H71: 0.3 | I71: 1774 | J71: [{"keyword": "glaciers", "count": 295}, {"keyword": "wine tours", "count": 225}, {"keyword": "whale watching", "count": 91}, {"keyword": "hot springs", "count": 176}, {"keyword": "signage", "count": 266}]
A72: social_media_sentiment | B72: 1350 | C72: III | D72: Atacama | E72: 2024 | F72: Q1 | G72: Instagram | H72: 0.02 | I72: 4990 | J72: [{"keyword": "wine tours", "count": 321}, {"keyword": "hiking trails", "count": 272}, {"keyword": "hot springs", "count": 137}, {"keyword": "desert stargazing", "count": 328}]
A73: social_media_sentiment | B73: 1351 | C73: III | D73: Atacama | E73: 2024 | F73: Q2 | G73: TripAdvisor | H73: 0.44 | I73: 62 | J73: [{"keyword": "signage", "count": 99}, {"keyword": "indigenous culture", "count": 342}, {"keyword": "seafood", "count": 396}] | K73: ["cleanliness near terminals", "overcrowding at peak season"]
A74: social_media_sentiment | B74: 1352 | C74: III | D74: Atacama | E74: 2024 | F74: Q3 | G74: Instagram | H74: 0.07 | I74: 121 | J74: [{"keyword": "public transport", "count": 181}, {"keyword": "whale watching", "count": 208}, {"keyword": "safety", "count": 170}]
A75: social_media_sentiment | B75: 1353 | C75: III | D75: Atacama | E75: 2024 | F75: Q4 | G75: TripAdvisor | H75: 0.38 | I75: 4878 | J75: [{"keyword": "beaches", "count": 382}, {"keyword": "signage", "count": 201}, {"keyword": "hiking trails", "count": 197}, {"keyword": "street art", "count": 260}] | K75: ["price transparency", "cleanliness near terminals"]
A76: social_media_sentiment | B76: 1354 | C76: III | D76: Atacama | E76: 2025 | F76: Q1 | G76: X | H76: -0.1 | I76: 1544 | J76: [{"keyword": "cleanliness", "count": 305}, {"keyword": "street art", "count": 334}, {"keyword": "hot springs", "count": 336}, {"keyword": "desert stargazing", "count": 228}, {"keyword": "local markets", "count": 74}]
A77: social_media_sentiment | B77: 1355 | C77: III | D77: Atacama | E77: 2025 | F77: Q2 | G77: TripAdvisor | H77: -0.04 | I77: 3344 | J77: [{"keyword": "astronomy tourism", "count": 176}, {"keyword": "volcano trekking", "count": 51}, {"keyword": "public transport", "count": 281}, {"keyword": "cleanliness", "count": 43}] | K77: ["price transparency", "cleanliness near terminals"]
A78: social_media_sentiment | B78: 1356 | C78: III | D78: Atacama | E78: 2025 | F78: Q3 | G78: Instagram | H78: 0.29 | I78: 3560 | J78: [{"keyword": "hiking trails", "count": 52}, {"keyword": "safety", "count": 324}, {"keyword": "local markets", "count": 190}, {"keyword": "festivals", "count": 372}]
A79: social_media_sentiment | B79: 1357 | C79: IV | D79: Coquimbo | E79: 2020 | F79: Q2 | G79: Instagram | H79: 0.29 | I79: 4884 | J79: [{"keyword": "ski resorts", "count": 16}, {"keyword": "public transport", "count": 47}, {"keyword": "national parks", "count": 339}, {"keyword": "glaciers", "count": 220}]
A80: social_media_sentiment | B80: 1358 | C80: IV | D80: Coquimbo | E80: 2020 | F80: Q3 | G80: X | H80: 0.13 | I80: 4313 | J80: [{"keyword": "festivals", "count": 32}, {"keyword": "beaches", "count": 35}, {"keyword": "hot springs", "count": 43}, {"keyword": "street art", "count": 187}]
A81: social_media_sentiment | B81: 1359 | C81: IV | D81: Coquimbo | E81: 2020 | F81: Q4 | G81: X | H81: 0.12 | I81: 2793 | J81: [{"keyword": "glaciers", "count": 99}, {"keyword": "cleanliness", "count": 146}, {"keyword": "hot springs", "count": 103}, {"keyword": "public transport", "count": 346}] | K81: ["wifi reliability", "signage clarity"]
A82: social_media_sentiment | B82: 1360 | C82: IV | D82: Coquimbo | E82: 2021 | F82: Q1 | G82: TripAdvisor | H82: 0.32 | I82: 3308 | J82: [{"keyword": "local markets", "count": 376}, {"keyword": "safety", "count": 364}, {"keyword": "astronomy tourism", "count": 229}]
A83: social_media_sentiment | B83: 1361 | C83: IV | D83: Coquimbo | E83: 2021 | F83: Q2 | G83: TripAdvisor | H83: 0.17 | I83: 4317 | J83: [{"keyword": "hiking trails", "count": 190}, {"keyword": "local markets", "count": 169}, {"keyword": "hot springs", "count": 111}]
A84: social_media_sentiment | B84: 1362 | C84: IV | D84: Coquimbo | E84: 2021 | F84: Q3 | G84: Instagram | H84: -0.06 | I84: 3063 | J84: [{"keyword": "whale watching", "count": 24}, {"keyword": "signage", "count": 87}, {"keyword": "beaches", "count": 142}] | K84: ["signage clarity", "cleanliness near terminals"]
A85: social_media_sentiment | B85: 1363 | C85: IV | D85: Coquimbo | E85: 2021 | F85: Q4 | G85: X | H85: -0.02 | I85: 3585 | J85: [{"keyword": "indigenous culture", "count": 167}, {"keyword": "desert stargazing", "count": 196}, {"keyword": "seafood", "count": 335}, {"keyword": "ski resorts", "count": 91}]
A86: social_media_sentiment | B86: 1364 | C86: IV | D86: Coquimbo | E86: 2022 | F86: Q1 | G86: TripAdvisor | H86: 0.19 | I86: 4484 | J86: [{"keyword": "beaches", "count": 194}, {"keyword": "glaciers", "count": 90}, {"keyword": "astronomy tourism", "count": 389}, {"keyword": "hiking trails", "count": 88}]
A87: social_media_sentiment | B87: 1365 | C87: IV | D87: Coquimbo | E87: 2022 | F87: Q2 | G87: TripAdvisor | H87: 0.72 | I87: 4736 | J87: [{"keyword": "volcano trekking", "count": 124}, {"keyword": "desert stargazing", "count": 232}, {"keyword": "public transport", "count": 115}, {"keyword": "national parks", "count": 354}, {"keyword": "beaches", "count": 11}]
A88: social_media_sentiment | B88: 1366 | C88: IV | D88: Coquimbo | E88: 2022 | F88: Q3 | G88: X | H88: 0.27 | I88: 1247 | J88: [{"keyword": "volcano trekking", "count": 271}, {"keyword": "whale watching", "count": 21}, {"keyword": "street art", "count": 14}]
A89: social_media_sentiment | B89: 1367 | C89: IV | D89: Coquimbo | E89: 2022 | F89: Q4 | G89: TripAdvisor | H89: 0.51 | I89: 2000 | J89: [{"keyword": "national parks", "count": 197}, {"keyword": "beaches", "count": 299}, {"keyword": "public transport", "count": 361}, {"keyword": "festivals", "count": 279}]
A90: social_media_sentiment | B90: 1368 | C90: IV | D90: Coquimbo | E90: 2023 | F90: Q1 | G90: Instagram | H90: -0.31 | I90: 2688 | J90: [{"keyword": "beaches", "count": 283}, {"keyword": "ski resorts", "count": 231}, {"keyword": "local markets", "count": 338}]
A91: social_media_sentiment | B91: 1369 | C91: IV | D91: Coquimbo | E91: 2023 | F91: Q2 | G91: X | H91: 0.43 | I91: 2005 | J91: [{"keyword": "hiking trails", "count": 10}, {"keyword": "ski resorts", "count": 111}, {"keyword": "seafood", "count": 112}, {"keyword": "signage", "count": 343}, {"keyword": "indigenous culture", "count": 345}]
A92: social_media_sentiment | B92: 1370 | C92: IV | D92: Coquimbo | E92: 2023 | F92: Q3 | G92: Instagram | H92: 0.06 | I92: 3197 | J92: [{"keyword": "signage", "count": 20}, {"keyword": "astronomy tourism", "count": 373}, {"keyword": "whale watching", "count": 306}]
A93: social_media_sentiment | B93: 1371 | C93: IV | D93: Coquimbo | E93: 2023 | F93: Q4 | G93: TripAdvisor | H93: 0.14 | I93: 3960 | J93: [{"keyword": "national parks", "count": 66}, {"keyword": "glaciers", "count": 317}, {"keyword": "safety", "count": 24}, {"keyword": "whale watching", "count": 58}, {"keyword": "beaches", "count": 388}] | K93: ["price transparency", "wifi reliability"]
A94: social_media_sentiment | B94: 1372 | C94: IV | D94: Coquimbo | E94: 2024 | F94: Q1 | G94: Instagram | H94: 0.27 | I94: 2602 | J94: [{"keyword": "astronomy tourism", "count": 20}, {"keyword": "public transport", "count": 176}, {"keyword": "desert stargazing", "count": 201}, {"keyword": "hiking trails", "count": 286}]
A95: social_media_sentiment | B95: 1373 | C95: IV | D95: Coquimbo | E95: 2024 | F95: Q4 | G95: X | H95: 0.13 | I95: 3929 | J95: [{"keyword": "volcano trekking", "count": 29}, {"keyword": "hiking trails", "count": 16}, {"keyword": "safety", "count": 308}, {"keyword": "seafood", "count": 35}]
A96: social_media_sentiment | B96: 1374 | C96: IV | D96: Coquimbo | E96: 2025 | F96: Q1 | G96: TripAdvisor | H96: 0.47 | I96: 1440 | J96: [{"keyword": "cleanliness", "count": 91}, {"keyword": "safety", "count": 128}, {"keyword": "signage", "count": 63}, {"keyword": "ski resorts", "count": 398}, {"keyword": "whale watching", "count": 85}]
A97: social_media_sentiment | B97: 1375 | C97: IV | D97: Coquimbo | E97: 2025 | F97: Q2 | G97: TripAdvisor | H97: 0.5 | I97: 2178 | J97: [{"keyword": "public transport", "count": 281}, {"keyword": "signage", "count": 156}, {"keyword": "street art", "count": 131}, {"keyword": "wine tours", "count": 316}, {"keyword": "seafood", "count": 114}]
A98: social_media_sentiment | B98: 1376 | C98: IV | D98: Coquimbo | E98: 2025 | F98: Q3 | G98: Instagram | H98: 0.18 | I98: 322 | J98: [{"keyword": "hot springs", "count": 383}, {"keyword": "beaches", "count": 209}, {"keyword": "festivals", "count": 60}, {"keyword": "hiking trails", "count": 135}]
A99: social_media_sentiment | B99: 1377 | C99: V | D99: Valparaíso | E99: 2020 | F99: Q1 | G99: TripAdvisor | H99: 0.07 | I99: 2121 | J99: [{"keyword": "seafood", "count": 176}, {"keyword": "whale watching", "count": 13}, {"keyword": "hiking trails", "count": 117}, {"keyword": "volcano trekking", "count": 69}, {"keyword": "beaches", "count": 117}]
A100: social_media_sentiment | B100: 1378 | C100: V | D100: Valparaíso | E100: 2020 | F100: Q2 | G100: TripAdvisor | H100: 0.05 | I100: 2412 | J100: [{"keyword": "seafood", "count": 48}, {"keyword": "hiking trails", "count": 346}, {"keyword": "beaches", "count": 261}, {"keyword": "ski resorts", "count": 351}]
...

Sheet DB4_IoT
